Workbook
Name Eno_TM: #REF!
Name Eno_TM: #REF!
Name Eno_TM: #REF!
Name Eno_Tons: #REF!
Name Eno_Tons: #REF!
Name Eno_Tons: #REF!
Name NTS_YR: #REF!
Name Sum_T2: #REF!
Name Sum_T2: #REF!
Name Sum_T2: #REF!
Name Sum_TTM: #REF!
Name Sum_TTM: #REF!
Name Sum_TTM: #REF!
Name ti_tbl_50: #REF!
Name ti_tbl_50: #REF!
Name ti_tbl_50: #REF!
Name ti_tbl_69: #REF!
Name ti_tbl_69: #REF!
Name ti_tbl_69: #REF!

Sheet About
A1: BCDTRtSY BAU Cargo Dist Transported Relative to Start Year | B1: Louisiana | C1: 45660 | E1: State | F1: State
B2: =LOOKUP(B1,E2:F51,F2:F51) -> LA | E2: Alabama | F2: AL
A3: Sources: | B3: See Notes section for which vehicle types use which sources | E3: Alaska | F3: AK
B4: EIA | E4: Arizona | F4: AZ
B5: 2020, 2021, 2022 | E5: Arkansas | F5: AR
B6: Annual Energy Outlook 2020, 2021, and 2022 | E6: California | F6: CA
B7: https://www.eia.gov/outlooks/aeo/tables_side.php | E7: Colorado | F7: CO
B8: Tables 7, 36, 46, 47, 49 | E8: Connecticut | F8: CT
E9: Delaware | F9: DE
B10: Bus adjustment factor, 2020-2025 | E10: Florida | F10: FL
B11: EPA | E11: Georgia | F11: GA
B12: 2022 | E12: Hawaii | F12: HI
B13: Inventory of U.S. Greenhouse Gas Emissions and Sinks: 1990-2020 | E13: Idaho | F13: ID
B14: https://www.epa.gov/ghgemissions/inventory-us-greenhouse-gas-emissions-and-sinks-1990-2020 | E14: Illinois | F14: IL
B15: Table 3-13 | E15: Indiana | F15: IN
E16: Iowa | F16: IA
B17: SEDS state data | E17: Kansas | F17: KS
B18: EIA | E18: Kentucky | F18: KY
B19: 2024 | E19: Louisiana | F19: LA
B20: SEDS | E20: Maine | F20: ME
B21: https://www.eia.gov/state/seds/ | E21: Maryland | F21: MD
E22: Massachusetts | F22: MA
E23: Michigan | F23: MI
A24: Notes | E24: Minnesota | F24: MN
A25: This variable contains ratios of cargo distance transported in each year of the | E25: Mississippi | F25: MS
A26: model run relative to the start year. The start year is the year before the | E26: Missouri | F26: MO
A27: first simulated year. So if the first year for which the model outputs data | E27: Montana | F27: MT
A28: is 2020, the start year is 2019. The start year column does not have to be | E28: Nebraska | F28: NE
A29: included in the outputs but is retained here for visual clarity. | E29: Nevada | F29: NV
A30: We use AEO 2021 to calculate start year vehicles, as AEO 2021 does not include 2019 data. | E30: New Hampshire | F30: NH
E31: New Jersey | F31: NJ
A32: We scale by passenger-miles, freight ton-miles, or vehicle-miles where available. | E32: New Mexico | F32: NM
A33: (We assume vehicle loading remains constant, so scaling by vehicle-miles is | E33: New York | F33: NY
A34: identical to scaling by passenger-miles or freight ton-miles.) | E34: North Carolina | F34: NC
E35: North Dakota | F35: ND
A36: We classify AEO's light commercial trucks category as well as light-medium and medium duty vehicles | E36: Ohio | F36: OH
A37: in "freight LDVs" and heavy duty vehicles in "freight HDVs." | E37: Oklahoma | F37: OK
E38: Oregon | F38: OR
A39: Without any calibration adjustment, the very large dip in passenger air travel in 2020 leads to discrepancies | E39: Pennsylvania | F39: PA
A40: in energy use between AEO and the EPS outputs given our current methodology. Therefore, we add a calibration | E40: Rhode Island | F40: RI
A41: adjustment factor here, which adjusts the BAU aircraft cargo distance so that final aircraft energy use aligns | E41: South Carolina | F41: SC
A42: with the energy use in AEO 2021. | E42: South Dakota | F42: SD
E43: Tennessee | F43: TN
A44: For buses, we choose to use the EPA GHG Inventory to calculate the 2020 value, due to the fact the Inventory | E44: Texas | F44: TX
A45: reports only a ~20% drop in emissions from buses vs. the AEO which reports a ~50% drop. We then scale back | E45: Utah | F45: UT
A46: up to AEO values over a period of 5 years. | E46: Vermont | F46: VT
E47: Virginia | F47: VA
E48: Washington | F48: WA
A49: For states, we use state specific fuel growth for LDVs, HDVs and aircraft for 2022. | E49: West Virginia | F49: WV
A50: This is calculated using the 2021 and 2022 SEDS data for transportation fuel consumption. Then we revert to using AEO growth rates. | E50: Wisconsin | F50: WI
E51: Wyoming | F51: WY

Sheet SEDS 2022
A1: Data_Status | B1: State | C1: MSN | D1: 2019 | E1: 2020 | F1: 2021 | G1: 2022
A2: 2022F | B2: AK | C2: ABICB | D2: -10 | E2: -7 | F2: -8 | G2: -6
A3: 2022F | B3: AK | C3: ARICB | D3: 11973 | E3: 12391 | F3: 13425 | G3: 12981
A4: 2022F | B4: AK | C4: ARTCB | D4: 11973 | E4: 12391 | F4: 13425 | G4: 12981
A5: 2022F | B5: AK | C5: ARTXB | D5: 11973 | E5: 12391 | F5: 13425 | G5: 12981
A6: 2022F | B6: AK | C6: AVACB | D6: 1245 | E6: 915 | F6: 1037 | G6: 1073
A7: 2022F | B7: AK | C7: AVTCB | D7: 1245 | E7: 915 | F7: 1037 | G7: 1073
A8: 2022F | B8: AK | C8: AVTXB | D8: 1245 | E8: 915 | F8: 1037 | G8: 1073
A9: 2022F | B9: AK | C9: B1ACB | D9: 0 | E9: 0 | F9: 0 | G9: 0
A10: 2022F | B10: AK | C10: B1TCB | D10: 0 | E10: 0 | F10: 0 | G10: 0
A11: 2022F | B11: AK | C11: BDACB | D11: 865 | E11: 865 | F11: 865 | G11: 865
A12: 2022F | B12: AK | C12: BDLCB | D12: 0 | E12: 0 | F12: 0 | G12: 0
... A14774: 2022F | B14774: WY | C14774: ZWHDP | D14774: 8906 | E14774: 8069 | F14774: 7865 | G14774: 8441

Sheet seds growth
A1: =About!B2 -> LA
E2: 2021 | F2: 2022 | G2: growth rate | H2: assigned veh type
A3: TNACB | C3: Transportation | D3: total | E3: =SUMIFS('SEDS 2022'!F:F,'SEDS 2022'!$C:$C,$A3,'SEDS 2022'!$B:$B,$A$1) -> 697925 | F3: =SUMIFS('SEDS 2022'!G:G,'SEDS 2022'!$C:$C,$A3,'SEDS 2022'!$B:$B,$A$1) -> 755840 | G3: =F3/E3 -> 1.0829817
A4: BDACB | C4: biofuel diesel | D4: biofuel diesel tf | E4: =SUMIFS('SEDS 2022'!F:F,'SEDS 2022'!$C:$C,$A4,'SEDS 2022'!$B:$B,$A$1) -> 4496 | F4: =SUMIFS('SEDS 2022'!G:G,'SEDS 2022'!$C:$C,$A4,'SEDS 2022'!$B:$B,$A$1) -> 4048 | G4: =F4/E4 -> 0.90035587
A5: EMACB | C5: biofuel gasoline | D5: biofuel gasoline tf | E5: =SUMIFS('SEDS 2022'!F:F,'SEDS 2022'!$C:$C,$A5,'SEDS 2022'!$B:$B,$A$1) -> 16805 | F5: =SUMIFS('SEDS 2022'!G:G,'SEDS 2022'!$C:$C,$A5,'SEDS 2022'!$B:$B,$A$1) -> 17757 | G5: =F5/E5 -> 1.0566498
A6: ESACB | C6: electricity | D6: electricity tf | E6: =SUMIFS('SEDS 2022'!F:F,'SEDS 2022'!$C:$C,$A6,'SEDS 2022'!$B:$B,$A$1) -> 32 | F6: =SUMIFS('SEDS 2022'!G:G,'SEDS 2022'!$C:$C,$A6,'SEDS 2022'!$B:$B,$A$1) -> 35 | G6: =F6/E6 -> 1.09375
A7: RFACB | C7: heavy or residual fuel oil | D7: heavy or residual fuel oil tf | E7: =SUMIFS('SEDS 2022'!F:F,'SEDS 2022'!$C:$C,$A7,'SEDS 2022'!$B:$B,$A$1) -> 38404 | F7: =SUMIFS('SEDS 2022'!G:G,'SEDS 2022'!$C:$C,$A7,'SEDS 2022'!$B:$B,$A$1) -> 39353 | G7: =F7/E7 -> 1.024711
A8: JFACB | B8: AVACB | C8: jet fuel | D8: jet fuel tf | E8: =SUMIFS('SEDS 2022'!F:F,'SEDS 2022'!$C:$C,$A8,'SEDS 2022'!$B:$B,$A$1) -> 16023 | F8: =SUMIFS('SEDS 2022'!G:G,'SEDS 2022'!$C:$C,$A8,'SEDS 2022'!$B:$B,$A$1) -> 20489 | G8: =F8/E8 -> 1.2787243 | H8: aircraft
A9: PQACB | C9: LPG propane or butane | D9: LPG propane or butane tf | E9: =SUMIFS('SEDS 2022'!F:F,'SEDS 2022'!$C:$C,$A9,'SEDS 2022'!$B:$B,$A$1) -> 188 | F9: =SUMIFS('SEDS 2022'!G:G,'SEDS 2022'!$C:$C,$A9,'SEDS 2022'!$B:$B,$A$1) -> 267 | G9: =F9/E9 -> 1.4202128
A10: NGACB | C10: natural gas | D10: natural gas tf | E10: =SUMIFS('SEDS 2022'!F:F,'SEDS 2022'!$C:$C,$A10,'SEDS 2022'!$B:$B,$A$1) -> 228773 | F10: =SUMIFS('SEDS 2022'!G:G,'SEDS 2022'!$C:$C,$A10,'SEDS 2022'!$B:$B,$A$1) -> 286412 | G10: =F10/E10 -> 1.2519484
A11: DFACB | C11: petroleum diesel | D11: petroleum diesel tf | E11: =SUMIFS('SEDS 2022'!F:F,'SEDS 2022'!$C:$C,$A11,'SEDS 2022'!$B:$B,$A$1) -> 154528 | F11: =SUMIFS('SEDS 2022'!G:G,'SEDS 2022'!$C:$C,$A11,'SEDS 2022'!$B:$B,$A$1) -> 156667 | G11: =F11/E11 -> 1.0138422 | H11: HDVs
A12: MGACB | C12: petroleum gasoline | D12: petroleum gasoline tf | E12: =SUMIFS('SEDS 2022'!F:F,'SEDS 2022'!$C:$C,$A12,'SEDS 2022'!$B:$B,$A$1) -> 254356 | F12: =SUMIFS('SEDS 2022'!G:G,'SEDS 2022'!$C:$C,$A12,'SEDS 2022'!$B:$B,$A$1) -> 247173 | G12: =F12/E12 -> 0.97176005 | H12: LDVs

Sheet EPA_Table 3-13
A1: Table 3-13: CO2 Emissions from Fossil Fuel Combustion in Transportation End-Use Sector (MMT CO2 Eq.)
A3: Fuel/Vehicle Type | B3: 2020 | C3: 2021 | G3: 2021 to 2020 growth rate
A4: Gasolinea | B4: 937 | C4: 1029 | F4: Buses | G4: =SUM(C8,C15,C35,C41,C45)/SUM(B45,B41,B35,B15,B8) -> 1.0416667
A5: Passenger Cars | B5: 328 | C5: 361
A6: Light-Duty Trucks | B6: 566 | C6: 620
A7: Medium- and Heavy-Duty Trucksb | B7: 24 | C7: 27
A8: Buses | B8: 3 | C8: 3
A9: Motorcycles | B9: 7 | C9: 7
A10: Recreational Boatsc | B10: 10 | C10: 11
A11: Distillate Fuel Oil (Diesel)a | B11: 455 | C11: 488
A12: Passenger Cars | B12: 3 | C12: 3
A13: Light-Duty Trucks | B13: 30 | C13: 33
A14: Medium- and Heavy-Duty Trucksb | B14: 353 | C14: 380
A15: Buses | B15: 20 | C15: 21
A16: Rail | B16: 31 | C16: 32
... A50: Biofuels-Biodieselh | B50: 17.7 | C50: 16.1
A51: + Does not exceed 0.05 MMT CO2 Eq.
A52: a On-road fuel consumption data from FHWA Table MF-21 and MF-27 were used to determine total on-road use of motor gasoline and diesel fuel (FHWA 1996 through 2023). Ratios developed from MOVES3 output are used to apportion FHWA fuel consumption data to vehicle type and fuel type (see Annex 3.2 for information about the MOVES model).
A53: b Includes medium- and heavy-duty trucks over 8,500 lbs.
A54: c In 2014, EPA incorporated the NONROAD2008 model into the MOVES model framework. The current Inventory uses the Nonroad component of MOVES3 for years 1999 through 2021. See Annex 3.2 for information about the MOVES model.
A55: d Note that large year over year fluctuations in emission estimates partially reflect nature of data collection for these sources.
A56: e Official estimates exclude emissions from the combustion of both aviation and marine international bunker fuels; however, estimates of international bunker fuel-related emissions are presented for informational purposes.
A57: f Commercial aircraft, as modeled in FAA’s Aviation Environmental Design Tool (AEDT), consists of passenger aircraft, cargo, and other chartered flights.
A58: g Pipelines reflect CO2 emissions from natural gas-powered pipelines transporting natural gas.
A59: h Ethanol and biodiesel estimates are presented for informational purposes only. See Section 3.10 of this chapter and the estimates in Land Use, Land-Use Change, and Forestry (see Chapter 6), in line with IPCC methodological guidance and UNFCCC reporting obligations, for more information on ethanol and biodiesel.
A60: i Transportation sector natural gas and LPG consumption are based on data from EIA (2021b). Prior to the 1990 to 2015 Inventory, data from DOE TEDB were used to estimate each vehicle class’s share of the total natural gas and LPG consumption. Since TEDB does not include estimates for natural gas use by medium and heavy-duty trucks or LPG use by passenger cars, EIA Alternative Fuel Vehicle Data (Browning 2017) is now used to determine each vehicle class’s share of the total natural gas and LPG consumption. These changes were first incorporated in the 1990 to 2016 Inventory and apply to the 1990 to 2021 time period.
A61: j Includes emissions from rail electricity.
A62: k Electricity consumption by passenger cars, light-duty trucks (SUVs), and buses is based on plug-in electric vehicle sales and engine efficiency data, as outlined in Browning (2018a). In prior Inventory years, CO2 emissions from electric vehicle charging were allocated to the residential and commercial sectors. They are now allocated to the transportation sector. These changes apply to the 2010 through 2021 time period.
A63: Notes: This table does not include emissions from non-transportation mobile sources, such as agricultural equipment and construction/mining equipment; it also does not include emissions associated with electricity consumption by pipelines or lubricants used in transportation. In addition, this table does not include CO2 emissions from U.S. Territories, since these are covered in a separate chapter of the Inventory. Totals may not sum due to independent rounding.

Sheet AEO 2021 Table 7
B1: highogs.d120120a | C1: 2020 | D1: 2021 | E1: 2022 | F1: 2023 | G1: 2024 | H1: 2025 | I1: 2026 | J1: 2027 | K1: 2028 | L1: 2029 | M1: 2030 | N1: 2031 | O1: 2032 | P1: 2033 | Q1: 2034 | R1: 2035 | S1: 2036 | T1: 2037 | U1: 2038 | V1: 2039 | W1: 2040 | X1: 2041 | Y1: 2042 | Z1: 2043 | AA1: 2044 | AB1: 2045 | AC1: 2046 | AD1: 2047 | AE1: 2048 | AF1: 2049 | AG1: 2050
C3: Report | D3: Annual Energy Outlook 2021
C4: Scenario | D4: ref2021 | G4: Reference case
C5: Datekey | D5: d113020a
C6: Release Date | E6: January 2021
A10: TKI000 | B10: 7. Transportation Sector Key Indicators and Delivered Energy Consumption | AH10: Compound
AH11: Growth
AH12: 2020-2050
B13: Key Indicators and Consumption | C13: 2020 | D13: 2021 | E13: 2022 | F13: 2023 | G13: 2024 | H13: 2025 | I13: 2026 | J13: 2027 | K13: 2028 | L13: 2029 | M13: 2030 | N13: 2031 | O13: 2032 | P13: 2033 | Q13: 2034 | R13: 2035 | S13: 2036 | T13: 2037 | U13: 2038 | V13: 2039 | W13: 2040 | X13: 2041 | Y13: 2042 | Z13: 2043 | AA13: 2044 | AB13: 2045 | AC13: 2046 | AD13: 2047 | AE13: 2048 | AF13: 2049 | AG13: 2050 | AH13: (percent)
B15: Key Indicators
B16: Travel Indicators
B17: (billion vehicle miles traveled)
A18: TKI000:ba_Light-DutyVeh | B18: Light-Duty Vehicles less than 8,501 pounds | C18: 2628.8213 | D18: 2807.2766 | E18: 2862.5334 | F18: 2927.623 | G18: 2985.1787 | H18: 3035.5583 | I18: 3076.646 | J18: 3107.3425 | K18: 3133.9348 | L18: 3153.6963 | M18: 3170.1406 | N18: 3182.3604 | O18: 3194.3308 | P18: 3208.3691 | Q18: 3223.0125 | R18: 3240.585 | S18: 3258.4961 | T18: 3274.8767 | U18: 3290.0166 | V18: 3306.9768 | W18: 3326.3066 | X18: 3344.3862 | Y18: 3362.8257 | Z18: 3380.6958 | AA18: 3396.752 | AB18: 3412.0305 | AC18: 3428.1084 | AD18: 3442.5149 | AE18: 3458.3401 | AF18: 3474.7087 | AG18: 3490.9399 | AH18: 0.009499
A19: TKI000:ba_CommercialLig | B19: Commercial Light Trucks 1/ | C19: 89.884674 | D19: 93.705605 | E19: 96.386086 | F19: 98.338295 | G19: 100.59341 | H19: 102.85941 | I19: 104.50481 | J19: 105.69051 | K19: 106.73648 | L19: 107.65262 | M19: 108.58299 | N19: 109.54169 | O19: 110.61884 | P19: 111.70705 | Q19: 112.95861 | R19: 114.4644 | S19: 115.90713 | T19: 117.2149 | U19: 118.58162 | V19: 120.04366 | W19: 121.52813 | X19: 123.15266 | Y19: 124.79562 | Z19: 126.54729 | AA19: 128.13809 | AB19: 129.78653 | AC19: 131.39938 | AD19: 132.81888 | AE19: 134.41592 | AF19: 136.18376 | AG19: 138.01 | AH19: 0.014396
A20: TKI000:ba_FreightTrucks | B20: Freight Trucks greater than 10,000 pounds | C20: 274.54938 | D20: 282.81525 | E20: 293.31253 | F20: 299.26825 | G20: 306.24057 | H20: 313.39252 | I20: 318.20425 | J20: 321.86676 | K20: 325.49912 | L20: 328.91818 | M20: 332.87759 | N20: 337.04804 | O20: 341.41943 | P20: 345.24298 | Q20: 349.75104 | R20: 355.3486 | S20: 360.47449 | T20: 365.30786 | U20: 370.46982 | V20: 375.98251 | W20: 381.01727 | X20: 386.70856 | Y20: 392.7948 | Z20: 399.70087 | AA20: 405.64847 | AB20: 411.79804 | AC20: 417.07053 | AD20: 422.22894 | AE20: 428.00507 | AF20: 434.11798 | AG20: 440.79153 | AH20: 0.015907
B21: (billion passenger miles traveled)
A22: TKI000:buspassmiles | B22: Bus Transportation | C22: 108.32251 | D22: 134.82925 | E22: 154.71742 | F22: 169.65283 | G22: 180.92081 | H22: 189.4493 | I22: 195.91775 | J22: 200.87158 | K22: 204.4294 | L22: 207.17819 | M22: 209.42627 | N22: 211.01544 | O22: 212.35484 | P22: 213.3685 | Q22: 214.16457 | R22: 214.70816 | S22: 215.16942 | T22: 215.53513 | U22: 215.80548 | V22: 215.98587 | W22: 216.16197 | X22: 216.26544 | Y22: 216.33122 | Z22: 216.37845 | AA22: 216.40999 | AB22: 216.44157 | AC22: 216.45151 | AD22: 216.46837 | AE22: 216.483 | AF22: 216.55254 | AG22: 216.64348 | AH22: 0.023374
A23: TKI000:railpassmiles | B23: Passenger Rail | C23: 24.970692 | D23: 29.653244 | E23: 33.486446 | F23: 36.386101 | G23: 38.577961 | H23: 40.222988 | I23: 41.396164 | J23: 42.264778 | K23: 42.515728 | L23: 42.713291 | M23: 43.137005 | N23: 43.343742 | O23: 43.818241 | P23: 44.274139 | Q23: 44.835865 | R23: 45.310886 | S23: 45.831734 | T23: 46.32793 | U23: 46.816154 | V23: 47.317448 | W23: 47.980492 | X23: 48.58215 | Y23: 49.164021 | Z23: 49.763081 | AA23: 50.334721 | AB23: 50.97802 | AC23: 51.558666 | AD23: 52.079247 | AE23: 52.647175 | AF23: 53.282265 | AG23: 53.912506 | AH23: 0.025987
B24: (billion seat miles available)
A25: TKI000:ba_Air | B25: Air | C25: 738.85895 | D25: 1081.6603 | E25: 1215.7373 | F25: 1284.3009 | G25: 1340.2419 | H25: 1397.254 | I25: 1430.9814 | J25: 1455.4497 | K25: 1476.5328 | L25: 1495.9988 | M25: 1516.3666 | N25: 1539.9563 | O25: 1569.8956 | P25: 1600.4498 | Q25: 1634.8596 | R25: 1672.6685 | S25: 1707.1351 | T25: 1738.4458 | U25: 1770.8867 | V25: 1807.5973 | W25: 1848.892 | X25: 1889.7706 | Y25: 1930.5969 | Z25: 1971.072 | AA25: 2010.4889 | AB25: 2052.9485 | AC25: 2092.6599 | AD25: 2129.1379 | AE25: 2171.0725 | AF25: 2213.2192 | AG25: 2256.3169 | AH25: 0.037914
B26: (billion ton miles traveled)
A27: TKI000:ba_Rail | B27: Rail | C27: 1508.557 | D27: 1600.7733 | E27: 1616.5277 | F27: 1618.1086 | G27: 1617.9658 | H27: 1567.8839 | I27: 1587.1537 | J27: 1586.3214 | K27: 1606.0509 | L27: 1623.5897 | M27: 1641.5112 | N27: 1654.2195 | O27: 1664.4609 | P27: 1678.1671 | Q27: 1686.5093 | R27: 1700.8228 | S27: 1714.3484 | T27: 1725.9465 | U27: 1730.047 | V27: 1747.595 | W27: 1753.4669 | X27: 1765.8125 | Y27: 1783.1677 | Z27: 1804.6465 | AA27: 1808.4172 | AB27: 1822.5868 | AC27: 1832.4125 | AD27: 1846.7275 | AE27: 1860.8992 | AF27: 1876.0131 | AG27: 1898.7479 | AH27: 0.007697
A28: TKI000:ba_DomesticShipp | B28: Domestic Shipping | C28: 347.68133 | D28: 359.32346 | E28: 357.10059 | F28: 354.90668 | G28: 352.6954 | H28: 348.07819 | I28: 341.28058 | J28: 333.10046 | K28: 325.25259 | L28: 316.86505 | M28: 308.73145 | N28: 305.11627 | O28: 301.85187 | P28: 298.30835 | Q28: 295.38019 | R28: 292.62634 | S28: 289.63 | T28: 286.27258 | U28: 282.6651 | V28: 279.71716 | W28: 276.01688 | X28: 275.42545 | Y28: 275.00784 | Z28: 275.36859 | AA28: 274.91849 | AB28: 274.56326 | AC28: 273.54471 | AD28: 272.61859 | AE28: 271.43494 | AF28: 270.55728 | AG28: 270.13117 | AH28: -0.008377
B30: Energy Efficiency Indicators
B31: (miles per gallon)
A32: TKI000:ca_AvgCAFEStand | B32: New Light-Duty Vehicle CAFE Standard 2/ | C32: 34.471165 | D32: 35.386478 | E32: 36.015511 | F32: 36.532135 | G32: 36.999756 | H32: 37.485561 | I32: 38.067947 | J32: 38.072563 | K32: 38.080814 | L32: 38.095245 | M32: 38.18074 | N32: 38.191765 | O32: 38.206318 | P32: 38.220623 | Q32: 38.249493 | R32: 38.23008 | S32: 38.209507 | T32: 38.204479 | U32: 38.204224 | V32: 38.187893 | W32: 38.180141 | X32: 38.173969 | Y32: 38.160957 | Z32: 38.151768 | AA32: 38.148342 | AB32: 38.153297 | AC32: 38.143864 | AD32: 38.134365 | AE32: 38.120548 | AF32: 38.116928 | AG32: 38.114223 | AH32: 0.003354
A33: TKI000:ca_CarCAFEStand | B33: New Car 2/ | C33: 42.096588 | D33: 44.275085 | E33: 44.804096 | F33: 45.431927 | G33: 46.163593 | H33: 46.83271 | I33: 47.617275 | J33: 47.640335 | K33: 47.640335 | L33: 47.644814 | M33: 47.681995 | N33: 47.681995 | O33: 47.681995 | P33: 47.681995 | Q33: 47.681995 | R33: 47.681995 | S33: 47.681995 | T33: 47.681995 | U33: 47.681995 | V33: 47.681995 | W33: 47.681995 | X33: 47.681995 | Y33: 47.681995 | Z33: 47.683205 | AA33: 47.684814 | AB33: 47.687138 | AC33: 47.687138 | AD33: 47.687138 | AE33: 47.687138 | AF33: 47.689449 | AG33: 47.689449 | AH33: 0.004167
A34: TKI000:ca_TwukCAFEStand | B34: New Light Truck 2/ | C34: 30.906752 | D34: 31.515783 | E34: 31.942911 | F34: 32.461285 | G34: 32.91795 | H34: 33.400791 | I34: 33.955074 | J34: 33.955074 | K34: 33.955074 | L34: 33.955074 | M34: 33.955074 | N34: 33.955093 | O34: 33.955093 | P34: 33.955093 | Q34: 33.955093 | R34: 33.955128 | S34: 33.955128 | T34: 33.955128 | U34: 33.955128 | V34: 33.955128 | W34: 33.955128 | X34: 33.955128 | Y34: 33.955128 | Z34: 33.955128 | AA34: 33.955128 | AB34: 33.955128 | AC34: 33.955128 | AD34: 33.955128 | AE34: 33.955128 | AF34: 33.955128 | AG34: 33.955128 | AH34: 0.00314
A35: TKI000:ca_NewVehCred | B35: Compliance New Light-Duty Vehicle 3/ | C35: 35.428043 | D35: 36.588161 | E35: 37.27243 | F35: 37.693687 | G35: 38.000156 | H35: 38.414772 | I35: 38.930225 | J35: 39.067493 | K35: 39.131561 | L35: 39.187084 | M35: 39.367001 | N35: 39.458767 | O35: 39.570412 | P35: 39.688381 | Q35: 39.842903 | R35: 39.925739 | S35: 40.007633 | T35: 40.122059 | U35: 40.263226 | V35: 40.363659 | W35: 40.483315 | X35: 40.567554 | Y35: 40.636898 | Z35: 40.715225 | AA35: 40.813824 | AB35: 40.933929 | AC35: 41.032745 | AD35: 41.136253 | AE35: 41.233734 | AF35: 41.366283 | AG35: 41.510693 | AH35: 0.005296
A36: TKI000:ca_NewCarCred | B36: New Car 3/ | C36: 43.264011 | D36: 45.133469 | E36: 45.638382 | F36: 46.329559 | G36: 46.974045 | H36: 47.544498 | I36: 48.288284 | J36: 48.41925 | K36: 48.519196 | L36: 48.602192 | M36: 48.75803 | N36: 48.944359 | O36: 49.116051 | P36: 49.343533 | Q36: 49.588879 | R36: 49.838387 | S36: 50.062164 | T36: 50.324268 | U36: 50.609341 | V36: 50.887779 | W36: 51.161552 | X36: 51.375084 | Y36: 51.577618 | Z36: 51.784939 | AA36: 52.021469 | AB36: 52.278286 | AC36: 52.554256 | AD36: 52.823685 | AE36: 53.105881 | AF36: 53.415283 | AG36: 53.766708 | AH36: 0.007271
A37: TKI000:ca_NewTwukCred | B37: New Light Truck 3/ | C37: 31.76507 | D37: 32.790131 | E37: 33.304337 | F37: 33.675228 | G37: 33.948895 | H37: 34.370636 | I37: 34.850887 | J37: 34.987331 | K37: 35.027725 | L37: 35.055889 | M37: 35.139996 | N37: 35.184067 | O37: 35.253815 | P37: 35.313755 | Q37: 35.395432 | R37: 35.447819 | S37: 35.509632 | T37: 35.58049 | U37: 35.672146 | V37: 35.736599 | W37: 35.81567 | X37: 35.86631 | Y37: 35.911537 | Z37: 35.962078 | AA37: 36.021683 | AB37: 36.09063 | AC37: 36.147751 | AD37: 36.213341 | AE37: 36.274784 | AF37: 36.358318 | AG37: 36.442936 | AH37: 0.00459
A38: TKI000:ca_TestedNewVeh | B38: Tested New Light-Duty Vehicle 4/ | C38: 35.306622 | D38: 36.467899 | E38: 37.145805 | F38: 37.564754 | G38: 37.869587 | H38: 38.261166 | I38: 38.678329 | J38: 38.78212 | K38: 38.833714 | L38: 38.876083 | M38: 39.031017 | N38: 39.097122 | O38: 39.178814 | P38: 39.263397 | Q38: 39.380604 | R38: 39.428646 | S38: 39.476784 | T38: 39.553841 | U38: 39.655148 | V38: 39.718605 | W38: 39.800255 | X38: 39.857685 | Y38: 39.902508 | Z38: 39.954895 | AA38: 40.024872 | AB38: 40.112934 | AC38: 40.181061 | AD38: 40.254047 | AE38: 40.320404 | AF38: 40.416508 | AG38: 40.5215 | AH38: 0.004603
A39: TKI000:ca_TestedNewCar | B39: New Car 4/ | C39: 42.996372 | D39: 44.88583 | E39: 45.388092 | F39: 46.068283 | G39: 46.702301 | H39: 47.265957 | I39: 47.99147 | J39: 48.105293 | K39: 48.179577 | L39: 48.231701 | M39: 48.343479 | N39: 48.473526 | O39: 48.589264 | P39: 48.747791 | Q39: 48.918312 | R39: 49.08532 | S39: 49.232788 | T39: 49.410698 | U39: 49.605431 | V39: 49.791992 | W39: 49.975594 | X39: 50.118858 | Y39: 50.253036 | Z39: 50.390747 | AA39: 50.551331 | AB39: 50.726044 | AC39: 50.913406 | AD39: 51.097149 | AE39: 51.287189 | AF39: 51.498287 | AG39: 51.738174 | AH39: 0.006188
A40: TKI000:ca_TestedNewTwuk | B40: New Light Truck 4/ | C40: 31.69734 | D40: 32.714512 | E40: 33.224262 | F40: 33.594929 | G40: 33.868374 | H40: 34.261593 | I40: 34.620468 | J40: 34.71925 | K40: 34.751755 | L40: 34.772854 | M40: 34.839573 | N40: 34.86882 | O40: 34.918171 | P40: 34.957504 | Q40: 35.015827 | R40: 35.049236 | S40: 35.091114 | T40: 35.140182 | U40: 35.208858 | V40: 35.253445 | W40: 35.311043 | X40: 35.348305 | Y40: 35.381889 | Z40: 35.41943 | AA40: 35.464706 | AB40: 35.517353 | AC40: 35.560341 | AD40: 35.610996 | AE40: 35.657856 | AF40: 35.722626 | AG40: 35.788242 | AH40: 0.004054
A41: TKI000:ca_OnRoadNewVeh | B41: On-Road New Light-Duty Vehicle 5/ | C41: 28.801699 | D41: 29.748508 | E41: 30.302168 | F41: 30.643736 | G41: 30.892097 | H41: 31.211321 | I41: 31.551422 | J41: 31.636091 | K41: 31.678196 | L41: 31.712803 | M41: 31.839462 | N41: 31.893412 | O41: 31.960094 | P41: 32.029114 | Q41: 32.124813 | R41: 32.16391 | S41: 32.203083 | T41: 32.2659 | U41: 32.348515 | V41: 32.400196 | W41: 32.466755 | X41: 32.513561 | Y41: 32.550056 | Z41: 32.592743 | AA41: 32.649788 | AB41: 32.721619 | AC41: 32.77713 | AD41: 32.836617 | AE41: 32.890667 | AF41: 32.969021 | AG41: 33.054626 | AH41: 0.004601
A42: TKI000:ca_OnRoadNewCar | B42: New Car 5/ | C42: 35.111473 | D42: 36.65443 | E42: 37.064587 | F42: 37.620041 | G42: 38.137787 | H42: 38.598076 | I42: 39.190544 | J42: 39.283493 | K42: 39.344154 | L42: 39.386719 | M42: 39.477997 | N42: 39.584198 | O42: 39.678711 | P42: 39.808167 | Q42: 39.947414 | R42: 40.083797 | S42: 40.20422 | T42: 40.349506 | U42: 40.508526 | V42: 40.660873 | W42: 40.810806 | X42: 40.927799 | Y42: 41.037373 | Z42: 41.149826 | AA42: 41.280964 | AB42: 41.423634 | AC42: 41.576637 | AD42: 41.726685 | AE42: 41.881874 | AF42: 42.05426 | AG42: 42.250156 | AH42: 0.006188
A43: TKI000:ca_OnRoadNewTwuk | B43: New Light Truck 5/ | C43: 25.844681 | D43: 26.67404 | E43: 27.08967 | F43: 27.391895 | G43: 27.614851 | H43: 27.935465 | I43: 28.228077 | J43: 28.30862 | K43: 28.335123 | L43: 28.352325 | M43: 28.406727 | N43: 28.430573 | O43: 28.470812 | P43: 28.502882 | Q43: 28.550436 | R43: 28.577677 | S43: 28.611822 | T43: 28.651831 | U43: 28.707827 | V43: 28.744179 | W43: 28.791143 | X43: 28.821524 | Y43: 28.848907 | Z43: 28.879517 | AA43: 28.916433 | AB43: 28.95936 | AC43: 28.99441 | AD43: 29.035711 | AE43: 29.073919 | AF43: 29.12673 | AG43: 29.180231 | AH43: 0.004054
... A47: TKI000:ca_FreightTruck | B47: Freight Truck | C47: 7.238182 | D47: 7.310616 | E47: 7.389947 | F47: 7.476684 | G47: 7.574702 | H47: 7.686319 | I47: 7.80973 | J47: 7.944551 | K47: 8.083447 | L47: 8.230841 | M47: 8.382581 | N47: 8.536425 | O47: 8.686997 | P47: 8.827357 | Q47: 8.956337 | R47: 9.073474 | S47: 9.178899 | T47: 9.273054 | U47: 9.358724 | V47: 9.437573 | W47: 9.508476 | X47: 9.572987 | Y47: 9.62975 | Z47: 9.67997 | AA47: 9.724974 | AB47: 9.767028 | AC47: 9.806892 | AD47: 9.846315 | AE47: 9.885777 | AF47: 9.92395 | AG47: 9.961658 | AH47: 0.010703
B48: (seat miles per gallon)
A49: TKI000:ca_Aircraft | B49: Aircraft | C49: 71.028343 | D49: 72.22039 | E49: 72.564766 | F49: 73.078918 | G49: 73.855469 | H49: 74.440651 | I49: 74.946922 | J49: 75.432518 | K49: 75.920792 | L49: 76.399239 | M49: 76.903839 | N49: 77.42765 | O49: 77.983635 | P49: 78.569893 | Q49: 79.171509 | R49: 79.79718 | S49: 80.421959 | T49: 81.046387 | U49: 81.662766 | V49: 82.260727 | W49: 82.849083 | X49: 83.43293 | Y49: 84.016846 | Z49: 84.607124 | AA49: 85.178467 | AB49: 85.733246 | AC49: 86.278442 | AD49: 86.813042 | AE49: 87.369904 | AF49: 87.921379 | AG49: 88.469986 | AH49: 0.007346
B50: (ton miles/thousand Btu)
A51: TKI000:ca_Rail | B51: Rail | C51: 3.489371 | D51: 3.512003 | E51: 3.534782 | F51: 3.55771 | G51: 3.580785 | H51: 3.60401 | I51: 3.627386 | J51: 3.650914 | K51: 3.674594 | L51: 3.698428 | M51: 3.722416 | N51: 3.74656 | O51: 3.77086 | P51: 3.795318 | Q51: 3.819935 | R51: 3.844712 | S51: 3.869649 | T51: 3.894748 | U51: 3.920009 | V51: 3.945435 | W51: 3.971025 | X51: 3.996782 | Y51: 4.022705 | Z51: 4.048797 | AA51: 4.075058 | AB51: 4.101489 | AC51: 4.128091 | AD51: 4.154866 | AE51: 4.181815 | AF51: 4.208939 | AG51: 4.236238 | AH51: 0.006486
A52: TKI000:ca_DomesticShipp | B52: Domestic Shipping | C52: 4.84196 | D52: 4.870726 | E52: 4.899663 | F52: 4.928772 | G52: 4.958054 | H52: 4.987509 | I52: 5.01714 | J52: 5.046947 | K52: 5.076931 | L52: 5.107092 | M52: 5.137434 | N52: 5.167955 | O52: 5.198658 | P52: 5.229543 | Q52: 5.260611 | R52: 5.291864 | S52: 5.323303 | T52: 5.354929 | U52: 5.386742 | V52: 5.418745 | W52: 5.450938 | X52: 5.483322 | Y52: 5.515898 | Z52: 5.548667 | AA52: 5.581632 | AB52: 5.614792 | AC52: 5.64815 | AD52: 5.681705 | AE52: 5.71546 | AF52: 5.749416 | AG52: 5.783573 | AH52: 0.005941
B54: Energy Use by Mode
B55: (quadrillion Btu)
A56: TKI000:da_Light-DutyVeh | B56: Light-Duty Vehicles | C56: 13.684958 | D56: 14.333231 | E56: 14.327022 | F56: 14.365352 | G56: 14.366455 | H56: 14.341867 | I56: 14.287132 | J56: 14.207239 | K56: 14.125376 | L56: 14.028779 | M56: 13.931946 | N56: 13.831038 | O56: 13.740598 | P56: 13.671222 | Q56: 13.614177 | R56: 13.578903 | S56: 13.555063 | T56: 13.533011 | U56: 13.512934 | V56: 13.507698 | W56: 13.519425 | X56: 13.531686 | Y56: 13.55102 | Z56: 13.573046 | AA56: 13.591692 | AB56: 13.608699 | AC56: 13.631719 | AD56: 13.65046 | AE56: 13.676695 | AF56: 13.70651 | AG56: 13.736445 | AH56: 0.000125
A57: TKI000:da_CommercialLig | B57: Commercial Light Trucks 1/ | C57: 0.800598 | D57: 0.824583 | E57: 0.83718 | F57: 0.842737 | G57: 0.851008 | H57: 0.861964 | I57: 0.867177 | J57: 0.868256 | K57: 0.868721 | L57: 0.868144 | M57: 0.86827 | N57: 0.869091 | O57: 0.871659 | P57: 0.875056 | Q57: 0.880524 | R57: 0.888546 | S57: 0.896605 | T57: 0.904579 | U57: 0.913077 | V57: 0.922396 | W57: 0.932011 | X57: 0.942835 | Y57: 0.95338 | Z57: 0.965235 | AA57: 0.976007 | AB57: 0.987214 | AC57: 0.999347 | AD57: 1.008795 | AE57: 1.01946 | AF57: 1.031487 | AG57: 1.044088 | AH57: 0.008891
A58: TKI000:da_BusTransporta | B58: Bus Transportation | C58: 0.123601 | D58: 0.155229 | E58: 0.178087 | F58: 0.194794 | G58: 0.207087 | H58: 0.215933 | I58: 0.222447 | J58: 0.227387 | K58: 0.229827 | L58: 0.231575 | M58: 0.233385 | N58: 0.233909 | O58: 0.234577 | P58: 0.234898 | Q58: 0.235117 | R58: 0.234732 | S58: 0.234535 | T58: 0.234329 | U58: 0.233979 | V58: 0.23339 | W58: 0.232922 | X58: 0.232252 | Y58: 0.231514 | Z58: 0.230767 | AA58: 0.230025 | AB58: 0.229276 | AC58: 0.228442 | AD58: 0.227697 | AE58: 0.226858 | AF58: 0.226287 | AG58: 0.225795 | AH58: 0.020289
A59: TKI000:da_FreightTrucks | B59: Freight Trucks | C59: 5.215993 | D59: 5.320461 | E59: 5.459595 | F59: 5.506526 | G59: 5.562604 | H59: 5.610408 | I59: 5.606836 | J59: 5.575173 | K59: 5.54105 | L59: 5.498658 | M59: 5.463652 | N59: 5.431874 | O59: 5.406318 | P59: 5.379243 | Q59: 5.370211 | R59: 5.384785 | S59: 5.398619 | T59: 5.414024 | U59: 5.438496 | V59: 5.471154 | W59: 5.50076 | X59: 5.54297 | Y59: 5.59491 | Z59: 5.661906 | AA59: 5.718006 | AB59: 5.778462 | AC59: 5.827639 | AD59: 5.875145 | AE59: 5.930928 | AF59: 5.991611 | AG59: 6.059749 | AH59: 0.00501
A60: TKI000:da_Rail,Passenge | B60: Rail, Passenger | C60: 0.029437 | D60: 0.035251 | E60: 0.039934 | F60: 0.043478 | G60: 0.046156 | H60: 0.048166 | I60: 0.049615 | J60: 0.050695 | K60: 0.051001 | L60: 0.05125 | M60: 0.051752 | N60: 0.052019 | O60: 0.052574 | P60: 0.053111 | Q60: 0.053765 | R60: 0.05433 | S60: 0.054952 | T60: 0.05555 | U60: 0.056141 | V60: 0.056752 | W60: 0.057542 | X60: 0.058268 | Y60: 0.058979 | Z60: 0.059712 | AA60: 0.060418 | AB60: 0.061203 | AC60: 0.061918 | AD60: 0.062563 | AE60: 0.063254 | AF60: 0.064012 | AG60: 0.064756 | AH60: 0.026627
A61: TKI000:da_Rail,Freight | B61: Rail, Freight | C61: 0.432329 | D61: 0.455801 | E61: 0.45732 | F61: 0.454818 | G61: 0.451847 | H61: 0.435039 | I61: 0.437548 | J61: 0.4345 | K61: 0.437069 | L61: 0.438995 | M61: 0.44098 | N61: 0.44153 | O61: 0.441401 | P61: 0.442168 | Q61: 0.441502 | R61: 0.44238 | S61: 0.443024 | T61: 0.443147 | U61: 0.441338 | V61: 0.442941 | W61: 0.441565 | X61: 0.441809 | Y61: 0.443276 | Z61: 0.445724 | AA61: 0.443777 | AB61: 0.444372 | AC61: 0.443889 | AD61: 0.444473 | AE61: 0.444998 | AF61: 0.445721 | AG61: 0.448216 | AH61: 0.001204
A62: TKI000:da_Shipping,Dome | B62: Shipping, Domestic | C62: 0.077343 | D62: 0.079141 | E62: 0.078228 | F62: 0.07735 | G62: 0.076447 | H62: 0.075056 | I62: 0.073205 | J62: 0.071058 | K62: 0.068995 | L62: 0.066834 | M62: 0.064753 | N62: 0.063638 | O62: 0.062605 | P62: 0.061511 | Q62: 0.060562 | R62: 0.059665 | S62: 0.058721 | T62: 0.057711 | U62: 0.056659 | V62: 0.055745 | W62: 0.054692 | X62: 0.054265 | Y62: 0.053874 | Z62: 0.053634 | AA62: 0.05324 | AB62: 0.052873 | AC62: 0.052373 | AD62: 0.051891 | AE62: 0.05137 | AF62: 0.05091 | AG62: 0.050533 | AH62: -0.014087
A63: TKI000:da_Shipping,Inte | B63: Shipping, International | C63: 0.855887 | D63: 0.881465 | E63: 0.973998 | F63: 0.992193 | G63: 0.941402 | H63: 0.944552 | I63: 0.956481 | J63: 0.933812 | K63: 0.934805 | L63: 0.926796 | M63: 0.92926 | N63: 0.946328 | O63: 0.931566 | P63: 0.932016 | Q63: 0.929677 | R63: 0.944409 | S63: 0.930073 | T63: 0.929561 | U63: 0.939661 | V63: 0.926163 | W63: 0.924429 | X63: 0.937035 | Y63: 0.921133 | Z63: 0.92034 | AA63: 0.913829 | AB63: 0.914233 | AC63: 0.910465 | AD63: 0.908206 | AE63: 0.908689 | AF63: 0.907332 | AG63: 0.904865 | AH63: 0.001857
A64: TKI000:da_RecreationalB | B64: Recreational Boats | C64: 0.195878 | D64: 0.196657 | E64: 0.199716 | F64: 0.201514 | G64: 0.202257 | H64: 0.202574 | I64: 0.201854 | J64: 0.200378 | K64: 0.198674 | L64: 0.19683 | M64: 0.195069 | N64: 0.193556 | O64: 0.192489 | P64: 0.191383 | Q64: 0.190484 | R64: 0.189818 | S64: 0.18891 | T64: 0.187759 | U64: 0.186658 | V64: 0.185802 | W64: 0.185223 | X64: 0.184588 | Y64: 0.183882 | Z64: 0.183175 | AA64: 0.182329 | AB64: 0.18168 | AC64: 0.180906 | AD64: 0.17988 | AE64: 0.17914 | AF64: 0.178366 | AG64: 0.177572 | AH64: -0.003265
A65: TKI000:da_Air | B65: Air | C65: 1.860485 | D65: 2.530984 | E65: 2.826346 | F65: 2.963305 | G65: 3.051768 | H65: 3.120219 | I65: 3.144242 | J65: 3.161629 | K65: 3.182792 | L65: 3.201851 | M65: 3.222472 | N65: 3.248707 | O65: 3.287299 | P65: 3.325297 | Q65: 3.36779 | R65: 3.416815 | S65: 3.457473 | T65: 3.492202 | U65: 3.528905 | V65: 3.570296 | W65: 3.622022 | X65: 3.669847 | Y65: 3.719 | Z65: 3.765759 | AA65: 3.814193 | AB65: 3.866814 | AC65: 3.914752 | AD65: 3.951365 | AE65: 3.990626 | AF65: 4.026413 | AG65: 4.062809 | AH65: 0.026376
A66: TKI000:da_MilitaryUse | B66: Military Use | C66: 0.535966 | D66: 0.545011 | E66: 0.545749 | F66: 0.53257 | G66: 0.52388 | H66: 0.523357 | I66: 0.5221 | J66: 0.52193 | K66: 0.524808 | L66: 0.52365 | M66: 0.521666 | N66: 0.521585 | O66: 0.52242 | P66: 0.523287 | Q66: 0.524164 | R66: 0.525042 | S66: 0.525958 | T66: 0.526906 | U66: 0.527867 | V66: 0.528832 | W66: 0.529807 | X66: 0.530791 | Y66: 0.531775 | Z66: 0.532766 | AA66: 0.533758 | AB66: 0.534753 | AC66: 0.535749 | AD66: 0.536745 | AE66: 0.53774 | AF66: 0.538735 | AG66: 0.539727 | AH66: 0.000233
A67: TKI000:da_Lubricants | B67: Lubricants | C67: 0.121224 | D67: 0.1234 | E67: 0.124821 | F67: 0.125915 | G67: 0.126656 | H67: 0.127041 | I67: 0.127207 | J67: 0.126854 | K67: 0.126597 | L67: 0.126378 | M67: 0.126074 | N67: 0.125802 | O67: 0.125585 | P67: 0.125401 | Q67: 0.125289 | R67: 0.125205 | S67: 0.125084 | T67: 0.124934 | U67: 0.12483 | V67: 0.124758 | W67: 0.124673 | X67: 0.124589 | Y67: 0.124522 | Z67: 0.12444 | AA67: 0.124423 | AB67: 0.124498 | AC67: 0.124516 | AD67: 0.124474 | AE67: 0.124496 | AF67: 0.12447 | AG67: 0.124386 | AH67: 0.000858
... A69: TKI000:da_Total | B69: Total | C69: 24.63995 | D69: 26.246357 | E69: 26.803347 | F69: 27.032192 | G69: 27.130775 | H69: 27.230783 | I69: 27.186893 | J69: 27.080057 | K69: 26.990782 | L69: 26.860777 | M69: 26.742741 | N69: 26.653553 | O69: 26.566212 | P69: 26.51256 | Q69: 26.490156 | R69: 26.545183 | S69: 26.577869 | T69: 26.62192 | U69: 26.686522 | V69: 26.75659 | W69: 26.859634 | X69: 26.988043 | Y69: 27.108532 | Z69: 27.264854 | AA69: 27.401077 | AB69: 27.549936 | AC69: 27.685604 | AD69: 27.804758 | AE69: 27.932571 | AF69: 28.069273 | AG69: 28.223778 | AH69: 0.004537
B71: (million barrels per day oil equivalent)
A72: TKI000:ea_Light-DutyVeh | B72: Light-Duty Vehicles | C72: 7.422104 | D72: 7.773714 | E72: 7.769763 | F72: 7.790549 | G72: 7.790876 | H72: 7.778635 | I72: 7.749986 | J72: 7.707629 | K72: 7.66415 | L72: 7.612647 | M72: 7.560986 | N72: 7.507026 | O72: 7.458717 | P72: 7.421792 | Q72: 7.391498 | R72: 7.373047 | S72: 7.360369 | T72: 7.34863 | U72: 7.337916 | V72: 7.33523 | W72: 7.341699 | X72: 7.348314 | Y72: 7.358773 | Z72: 7.37068 | AA72: 7.380744 | AB72: 7.389912 | AC72: 7.40236 | AD72: 7.412508 | AE72: 7.426698 | AF72: 7.442851 | AG72: 7.459049 | AH72: 0.000166
A73: TKI000:ea_CommercialLig | B73: Commercial Light Trucks 1/ | C73: 0.417402 | D73: 0.429752 | E73: 0.4361 | F73: 0.438805 | G73: 0.442896 | H73: 0.448514 | I73: 0.451192 | J73: 0.451773 | K73: 0.452056 | L73: 0.451855 | M73: 0.452067 | N73: 0.452658 | O73: 0.454179 | P73: 0.456158 | Q73: 0.459232 | R73: 0.463664 | S73: 0.46811 | T73: 0.472552 | U73: 0.477285 | V73: 0.48244 | W73: 0.487753 | X73: 0.493671 | Y73: 0.499459 | Z73: 0.505901 | AA73: 0.511755 | AB73: 0.517801 | AC73: 0.524376 | AD73: 0.529585 | AE73: 0.535473 | AF73: 0.542111 | AG73: 0.549078 | AH73: 0.009181
A74: TKI000:ea_BusTransporta | B74: Bus Transportation | C74: 0.059765 | D74: 0.07508 | E74: 0.08616 | F74: 0.094233 | G74: 0.100171 | H74: 0.104438 | I74: 0.107584 | J74: 0.109979 | K74: 0.111142 | L74: 0.111985 | M74: 0.112868 | N74: 0.113118 | O74: 0.113448 | P74: 0.113605 | Q74: 0.113716 | R74: 0.11353 | S74: 0.113436 | T74: 0.113336 | U74: 0.113171 | V74: 0.112886 | W74: 0.112663 | X74: 0.112337 | Y74: 0.11198 | Z74: 0.11162 | AA74: 0.111264 | AB74: 0.110882 | AC74: 0.110487 | AD74: 0.110127 | AE74: 0.109734 | AF74: 0.109462 | AG74: 0.109221 | AH74: 0.020302
A75: TKI000:ea_FreightTrucks | B75: Freight Trucks | C75: 2.511301 | D75: 2.562341 | E75: 2.62972 | F75: 2.651934 | G75: 2.678503 | H75: 2.701084 | I75: 2.699315 | J75: 2.684517 | K75: 2.668267 | L75: 2.648567 | M75: 2.632661 | N75: 2.618124 | O75: 2.60683 | P75: 2.594657 | Q75: 2.591201 | R75: 2.599064 | S75: 2.606463 | T75: 2.614655 | U75: 2.627334 | V75: 2.643946 | W75: 2.65917 | X75: 2.680398 | Y75: 2.706399 | Z75: 2.73978 | AA75: 2.767942 | AB75: 2.797641 | AC75: 2.822753 | AD75: 2.846913 | AE75: 2.875512 | AF75: 2.906283 | AG75: 2.940435 | AH75: 0.005272
A76: TKI000:ea_Rail,Passenge | B76: Rail, Passenger | C76: 0.013936 | D76: 0.016692 | E76: 0.018912 | F76: 0.02059 | G76: 0.021857 | H76: 0.022807 | I76: 0.023493 | J76: 0.024005 | K76: 0.024148 | L76: 0.024265 | M76: 0.024503 | N76: 0.02463 | O76: 0.024893 | P76: 0.025147 | Q76: 0.025457 | R76: 0.025725 | S76: 0.026019 | T76: 0.026302 | U76: 0.026582 | V76: 0.026871 | W76: 0.027246 | X76: 0.027589 | Y76: 0.027926 | Z76: 0.028273 | AA76: 0.028608 | AB76: 0.028976 | AC76: 0.029316 | AD76: 0.029622 | AE76: 0.029951 | AF76: 0.030311 | AG76: 0.030663 | AH76: 0.026634
A77: TKI000:ea_Rail,Freight | B77: Rail, Freight | C77: 0.2052 | D77: 0.216413 | E77: 0.217179 | F77: 0.215971 | G77: 0.214533 | H77: 0.206519 | I77: 0.207688 | J77: 0.206239 | K77: 0.20741 | L77: 0.208304 | M77: 0.209237 | N77: 0.209471 | O77: 0.2094 | P77: 0.209744 | Q77: 0.209412 | R77: 0.20981 | S77: 0.210093 | T77: 0.210129 | U77: 0.209256 | V77: 0.209996 | W77: 0.209331 | X77: 0.209426 | Y77: 0.210104 | Z77: 0.211251 | AA77: 0.210315 | AB77: 0.210549 | AC77: 0.210321 | AD77: 0.210586 | AE77: 0.210842 | AF77: 0.21118 | AG77: 0.212342 | AH77: 0.001141
A78: TKI000:ea_Shipping,Dome | B78: Shipping, Domestic | C78: 0.036641 | D78: 0.037508 | E78: 0.037086 | F78: 0.03667 | G78: 0.03624 | H78: 0.035579 | I78: 0.034701 | J78: 0.033688 | K78: 0.032706 | L78: 0.031683 | M78: 0.030701 | N78: 0.030174 | O78: 0.029688 | P78: 0.029171 | Q78: 0.028723 | R78: 0.0283 | S78: 0.027854 | T78: 0.027376 | U78: 0.026879 | V78: 0.026447 | W78: 0.02595 | X78: 0.025747 | Y78: 0.025561 | Z78: 0.025448 | AA78: 0.025261 | AB78: 0.025081 | AC78: 0.024846 | AD78: 0.024618 | AE78: 0.024375 | AF78: 0.024158 | AG78: 0.023978 | AH78: -0.014035
A79: TKI000:ea_Shipping,Inte | B79: Shipping, International | C79: 0.390127 | D79: 0.399914 | E79: 0.434956 | F79: 0.441884 | G79: 0.422805 | H79: 0.424046 | I79: 0.428597 | J79: 0.420109 | K79: 0.420515 | L79: 0.417549 | M79: 0.418554 | N79: 0.425043 | O79: 0.419537 | P79: 0.41976 | Q79: 0.418936 | R79: 0.424556 | S79: 0.419202 | T79: 0.419055 | U79: 0.422916 | V79: 0.417875 | W79: 0.417271 | X79: 0.422074 | Y79: 0.416121 | Z79: 0.415873 | AA79: 0.413463 | AB79: 0.413624 | AC79: 0.412266 | AD79: 0.41146 | AE79: 0.411718 | AF79: 0.411262 | AG79: 0.410365 | AH79: 0.001687
A80: TKI000:ea_RecreationalB | B80: Recreational Boats | C80: 0.106203 | D80: 0.106628 | E80: 0.108291 | F80: 0.10927 | G80: 0.109676 | H80: 0.109872 | I80: 0.109505 | J80: 0.108728 | K80: 0.107827 | L80: 0.10685 | M80: 0.105917 | N80: 0.105118 | O80: 0.104561 | P80: 0.103983 | Q80: 0.103517 | R80: 0.103178 | S80: 0.102702 | T80: 0.102093 | U80: 0.101512 | V80: 0.101063 | W80: 0.100765 | X80: 0.100435 | Y80: 0.100065 | Z80: 0.099694 | AA80: 0.099248 | AB80: 0.098909 | AC80: 0.098502 | AD80: 0.097958 | AE80: 0.097569 | AF80: 0.097161 | AG80: 0.096743 | AH80: -0.003105
A81: TKI000:ea_Air | B81: Air | C81: 0.900305 | D81: 1.224288 | E81: 1.367005 | F81: 1.433183 | G81: 1.475928 | H81: 1.509005 | I81: 1.520615 | J81: 1.529019 | K81: 1.539247 | L81: 1.548459 | M81: 1.558426 | N81: 1.571105 | O81: 1.589755 | P81: 1.608117 | Q81: 1.628653 | R81: 1.652344 | S81: 1.671992 | T81: 1.688775 | U81: 1.706511 | V81: 1.726514 | W81: 1.75151 | X81: 1.77462 | Y81: 1.798373 | Z81: 1.820968 | AA81: 1.844373 | AB81: 1.869801 | AC81: 1.892966 | AD81: 1.910659 | AE81: 1.929632 | AF81: 1.946926 | AG81: 1.964514 | AH81: 0.02635
A82: TKI000:ea_MilitaryUse | B82: Military Use | C82: 0.257081 | D82: 0.261438 | E82: 0.261803 | F82: 0.255477 | G82: 0.251303 | H82: 0.251044 | I82: 0.250438 | J82: 0.25036 | K82: 0.251731 | L82: 0.251176 | M82: 0.250227 | N82: 0.250187 | O82: 0.250591 | P82: 0.251006 | Q82: 0.251428 | R82: 0.25185 | S82: 0.252288 | T82: 0.252742 | U82: 0.253204 | V82: 0.253666 | W82: 0.254136 | X82: 0.254607 | Y82: 0.255078 | Z82: 0.255554 | AA82: 0.256032 | AB82: 0.256496 | AC82: 0.25698 | AD82: 0.257459 | AE82: 0.257947 | AF82: 0.258428 | AG82: 0.258902 | AH82: 0.000235
A83: TKI000:ea_Lubricants | B83: Lubricants | C83: 0.057262 | D83: 0.05829 | E83: 0.058961 | F83: 0.059478 | G83: 0.059828 | H83: 0.06001 | I83: 0.060088 | J83: 0.059921 | K83: 0.0598 | L83: 0.059697 | M83: 0.059553 | N83: 0.059424 | O83: 0.059322 | P83: 0.059235 | Q83: 0.059183 | R83: 0.059143 | S83: 0.059086 | T83: 0.059015 | U83: 0.058966 | V83: 0.058931 | W83: 0.058892 | X83: 0.058852 | Y83: 0.05882 | Z83: 0.058781 | AA83: 0.058773 | AB83: 0.058809 | AC83: 0.058817 | AD83: 0.058797 | AE83: 0.058808 | AF83: 0.058795 | AG83: 0.058756 | AH83: 0.000858
... A85: TKI000:ea_Total | B85: Total | C85: 12.710937 | D85: 13.523485 | E85: 13.782738 | F85: 13.893643 | G85: 13.946235 | H85: 13.993832 | I85: 13.969633 | J85: 13.917164 | K85: 13.870161 | L85: 13.804184 | M85: 13.743266 | N85: 13.694123 | O85: 13.650218 | P85: 13.62207 | Q85: 13.610144 | R85: 13.63513 | S85: 13.652452 | T85: 13.673915 | U85: 13.704461 | V85: 13.741007 | W85: 13.793367 | X85: 13.856253 | Y85: 13.918808 | Z85: 13.997322 | AA85: 14.066484 | AB85: 14.140247 | AC85: 14.209555 | AD85: 14.270186 | AE85: 14.335911 | AF85: 14.406158 | AG85: 14.484777 | AH85: 0.004364
B87: 1/ Commercial trucks 8,501 to 10,000 pounds gross vehicle weight rating.
B88: 2/ CAFE standard based on projected new vehicle sales.
B89: 3/ Includes CAFE credits for alternative fueled vehicle sales and credit banking.
B90: 4/ Environmental Protection Agency rated miles per gallon.
B91: 5/ Tested new vehicle efficiency revised for on-road performance.
B92: 6/ Combined "on-the-road" estimate for all cars and light trucks.
B93: CAFE = Corporate average fuel economy.
B94: Btu = British thermal unit.
B95: Note: Totals may not equal sum of components due to independent rounding.
B96: Sources: 2020: U.S. Energy Information Administration (EIA), Short-Term Energy Outlook, October 2020 and EIA,
B97: AEO2021 National Energy Modeling System run highogs.d120120a. Projections: EIA, AEO2021 National Energy Modeling System run highogs.d120120a.

Sheet AEO 2021 Table 35
E1: 2020 | F1: 2021 | G1: 2022 | H1: 2023 | I1: 2024 | J1: 2025 | K1: 2026 | L1: 2027 | M1: 2028 | N1: 2029 | O1: 2030 | P1: 2031 | Q1: 2032 | R1: 2033 | S1: 2034 | T1: 2035 | U1: 2036 | V1: 2037 | W1: 2038 | X1: 2039 | Y1: 2040 | Z1: 2041 | AA1: 2042 | AB1: 2043 | AC1: 2044 | AD1: 2045 | AE1: 2046 | AF1: 2047 | AG1: 2048 | AH1: 2049 | AI1: 2050 | AJ1: Growth (2020-2050)
A10: Table 35. Transportation Sector Energy Use by Mode and Type
A11: https://www.eia.gov/outlooks/aeo/data/browser/#/?id=45-AEO2021&region=0-0&cases=highogs&start=2019&end=2050&f=A&sourcekey=0
A12: Mon Mar 08 2021 15:04:42 GMT-0800 (Pacific Standard Time)
A13: Source: U.S. Energy Information Administration
B14: full name | C14: api key | D14: units | E14: 2020 | F14: 2021 | G14: 2022 | H14: 2023 | I14: 2024 | J14: 2025 | K14: 2026 | L14: 2027 | M14: 2028 | N14: 2029 | O14: 2030 | P14: 2031 | Q14: 2032 | R14: 2033 | S14: 2034 | T14: 2035 | U14: 2036 | V14: 2037 | W14: 2038 | X14: 2039 | Y14: 2040 | Z14: 2041 | AA14: 2042 | AB14: 2043 | AC14: 2044 | AD14: 2045 | AE14: 2046 | AF14: 2047 | AG14: 2048 | AH14: 2049 | AI14: 2050 | AJ14: Growth (2020-2050)
A15: Energy Use by Mode | C15: 45-AEO2021.2.
A16: Highway | C16: 45-AEO2021.3.
A17: Light-Duty Vehicles | B17: Transportation Energy Use: Highway: Light-Duty Vehicles: High oil and gas supply | C17: 45-AEO2021.4.highogs-d120120a | D17: trillion Btu | E17: 13684.959 | F17: 14333.232 | G17: 14327.021 | H17: 14365.353 | I17: 14366.454 | J17: 14341.867 | K17: 14287.134 | L17: 14207.24 | M17: 14125.377 | N17: 14028.782 | O17: 13931.946 | P17: 13831.038 | Q17: 13740.6 | R17: 13671.223 | S17: 13614.178 | T17: 13578.905 | U17: 13555.065 | V17: 13533.014 | W17: 13512.937 | X17: 13507.699 | Y17: 13519.428 | Z17: 13531.689 | AA17: 13551.022 | AB17: 13573.049 | AC17: 13591.697 | AD17: 13608.703 | AE17: 13631.723 | AF17: 13650.464 | AG17: 13676.699 | AH17: 13706.515 | AI17: 13736.45 | AJ17: 0
A18: Automobiles | B18: Transportation Energy Use: Highway: Light-Duty Vehicles: Automobiles: High oil and gas supply | C18: 45-AEO2021.5.highogs-d120120a | D18: trillion Btu | E18: 5675.0977 | F18: 5849.8979 | G18: 5755.2529 | H18: 5674.1973 | I18: 5571.2588 | J18: 5452.5518 | K18: 5322.6035 | L18: 5185.96 | M18: 5050.46 | N18: 4913.0923 | O18: 4785.4287 | P18: 4662.6523 | Q18: 4550.6763 | R18: 4453.6479 | S18: 4370.249 | T18: 4301.7231 | U18: 4245.416 | V18: 4198.5293 | W18: 4159.6685 | X18: 4129.9312 | Y18: 4109.8428 | Z18: 4093.1614 | AA18: 4081.1697 | AB18: 4071.9587 | AC18: 4063.4624 | AD18: 4055.2773 | AE18: 4048.9263 | AF18: 4041.3586 | AG18: 4035.5654 | AH18: 4031.2227 | AI18: 4027.0671 | AJ18: -0.011
A19: Light Trucks | B19: Transportation Energy Use: Highway: Light-Duty Vehicles: Light Trucks: High oil and gas supply | C19: 45-AEO2021.6.highogs-d120120a | D19: trillion Btu | E19: 7993.563 | F19: 8466.5332 | G19: 8555.2402 | H19: 8674.8594 | I19: 8779.1953 | J19: 8873.6572 | K19: 8949.2451 | L19: 9006.3877 | M19: 9060.4141 | N19: 9101.5811 | O19: 9132.7764 | P19: 9154.9971 | Q19: 9176.8564 | R19: 9204.7871 | S19: 9231.3809 | T19: 9264.832 | U19: 9297.46 | V19: 9322.4297 | W19: 9341.3252 | X19: 9365.9111 | Y19: 9397.7852 | Z19: 9426.7773 | AA19: 9458.1357 | AB19: 9489.3994 | AC19: 9516.5684 | AD19: 9541.7832 | AE19: 9571.1719 | AF19: 9597.5029 | AG19: 9629.5479 | AH19: 9663.7188 | AI19: 9697.8213 | AJ19: 0.006
A20: Motorcycles | B20: Transportation Energy Use: Highway: Light-Duty Vehicles: Motorcycles: High oil and gas supply | C20: 45-AEO2021.7.highogs-d120120a | D20: trillion Btu | E20: 16.299149 | F20: 16.800869 | G20: 16.528765 | H20: 16.295639 | I20: 15.999691 | J20: 15.658419 | K20: 15.284882 | L20: 14.89215 | M20: 14.502714 | N20: 14.107929 | O20: 13.741054 | P20: 13.388216 | Q20: 13.066401 | R20: 12.787572 | S20: 12.547906 | T20: 12.350933 | U20: 12.189022 | V20: 12.054244 | W20: 11.942542 | X20: 11.85706 | Y20: 11.799364 | Z20: 11.751442 | AA20: 11.71702 | AB20: 11.690611 | AC20: 11.666224 | AD20: 11.642757 | AE20: 11.624537 | AF20: 11.602818 | AG20: 11.586204 | AH20: 11.573715 | AI20: 11.561806 | AJ20: -0.011
A21: Commercial Light Trucks | B21: Transportation Energy Use: Highway: Commercial Light Trucks: High oil and gas supply | C21: 45-AEO2021.8.highogs-d120120a | D21: trillion Btu | E21: 800.59766 | F21: 824.58264 | G21: 837.18012 | H21: 842.73663 | I21: 851.00818 | J21: 861.96362 | K21: 867.17664 | L21: 868.25635 | M21: 868.72144 | N21: 868.14349 | O21: 868.26971 | P21: 869.091 | Q21: 871.65924 | R21: 875.05597 | S21: 880.52374 | T21: 888.54584 | U21: 896.60486 | V21: 904.57898 | W21: 913.07678 | X21: 922.39557 | Y21: 932.01129 | Z21: 942.83514 | AA21: 953.38037 | AB21: 965.23499 | AC21: 976.00677 | AD21: 987.21423 | AE21: 999.34717 | AF21: 1008.7945 | AG21: 1019.4604 | AH21: 1031.4871 | AI21: 1044.0883 | AJ21: 0.009
A22: Buses | B22: Transportation Energy Use: Highway: Buses: High oil and gas supply | C22: 45-AEO2021.9.highogs-d120120a | D22: trillion Btu | E22: 123.60058 | F22: 155.22908 | G22: 178.08673 | H22: 194.79402 | I22: 207.08707 | J22: 215.93285 | K22: 222.4467 | L22: 227.38673 | M22: 229.82677 | N22: 231.57542 | O22: 233.38449 | P22: 233.90918 | Q22: 234.57722 | R22: 234.89816 | S22: 235.11737 | T22: 234.73181 | U22: 234.535 | V22: 234.32896 | W22: 233.97902 | X22: 233.39026 | Y22: 232.92192 | Z22: 232.25186 | AA22: 231.51384 | AB22: 230.76698 | AC22: 230.02493 | AD22: 229.27586 | AE22: 228.442 | AF22: 227.6967 | AG22: 226.85817 | AH22: 226.28667 | AI22: 225.79506 | AJ22: 0.02
A23: Transit | B23: Transportation Energy Use: Highway: Buses: Transit: High oil and gas supply | C23: 45-AEO2021.10.highogs-d120120a | D23: trillion Btu | E23: 65.868385 | F23: 77.343925 | G23: 85.037193 | H23: 90.397377 | I23: 94.148392 | J23: 96.454201 | K23: 98.028534 | L23: 99.228485 | M23: 98.787506 | N23: 98.326218 | O23: 98.456612 | P23: 97.730179 | Q23: 97.429573 | R23: 97.078491 | S23: 96.865768 | T23: 96.19072 | U23: 95.827606 | V23: 95.546768 | W23: 95.188217 | X23: 94.635986 | Y23: 94.23497 | Z23: 93.65612 | AA23: 93.025208 | AB23: 92.393784 | AC23: 91.770996 | AD23: 91.134651 | AE23: 90.408363 | AF23: 89.765427 | AG23: 89.013596 | AH23: 88.517876 | AI23: 88.092033 | AJ23: 0.01
A24: Intercity | B24: Transportation Energy Use: Highway: Buses: Intercity: High oil and gas supply | C24: 45-AEO2021.11.highogs-d120120a | D24: trillion Btu | E24: 21.389296 | F24: 24.819853 | G24: 27.510082 | H24: 29.622658 | I24: 31.287823 | J24: 32.605827 | K24: 33.663296 | L24: 34.520813 | M24: 35.224197 | N24: 35.81303 | O24: 36.317593 | P24: 36.759636 | Q24: 37.152344 | R24: 37.510296 | S24: 37.844872 | T24: 38.157986 | U24: 38.449917 | V24: 38.72361 | W24: 38.985104 | X24: 39.238808 | Y24: 39.486942 | Z24: 39.72662 | AA24: 39.958668 | AB24: 40.184944 | AC24: 40.404293 | AD24: 40.622166 | AE24: 40.834713 | AF24: 41.040451 | AG24: 41.248081 | AH24: 41.453495 | AI24: 41.657665 | AJ24: 0.022
A25: School | B25: Transportation Energy Use: Highway: Buses: School: High oil and gas supply | C25: 45-AEO2021.12.highogs-d120120a | D25: trillion Btu | E25: 36.342903 | F25: 53.065319 | G25: 65.539474 | H25: 74.77401 | I25: 81.650841 | J25: 86.872803 | K25: 90.754913 | L25: 93.637444 | M25: 95.815033 | N25: 97.436134 | O25: 98.610291 | P25: 99.419357 | Q25: 99.995285 | R25: 100.30936 | S25: 100.40678 | T25: 100.38309 | U25: 100.25748 | V25: 100.05856 | W25: 99.805702 | X25: 99.51545 | Y25: 99.200005 | Z25: 98.869118 | AA25: 98.529976 | AB25: 98.188255 | AC25: 97.849648 | AD25: 97.519051 | AE25: 97.198906 | AF25: 96.890816 | AG25: 96.596497 | AH25: 96.315292 | AI25: 96.04538 | AJ25: 0.033
A26: Freight Trucks | B26: Transportation Energy Use: Highway: Freight Trucks: High oil and gas supply | C26: 45-AEO2021.13.highogs-d120120a | D26: trillion Btu | E26: 5217.8584 | F26: 5322.7695 | G26: 5462.249 | H26: 5509.6768 | I26: 5566.189 | J26: 5614.4268 | K26: 5611.2627 | L26: 5579.9849 | M26: 5546.2661 | N26: 5504.2886 | O26: 5469.7124 | P26: 5438.3926 | Q26: 5413.3032 | R26: 5386.6934 | S26: 5378.145 | T26: 5393.2607 | U26: 5407.6289 | V26: 5423.5879 | W26: 5448.6401 | X26: 5481.9277 | Y26: 5512.1758 | Z26: 5555.085 | AA26: 5607.7852 | AB26: 5675.5957 | AC26: 5732.5215 | AD26: 5793.834 | AE26: 5843.8721 | AF26: 5892.3438 | AG26: 5949.0996 | AH26: 6010.8965 | AI26: 6080.1992 | AJ26: 0.005
A27: Light Medium | B27: Transportation Energy Use: Highway: Freight Trucks: Light Medium: High oil and gas supply | C27: 45-AEO2021.14.highogs-d120120a | D27: trillion Btu | E27: 623.06995 | F27: 645.39587 | G27: 666.46094 | H27: 672.76428 | I27: 679.08014 | J27: 685.09302 | K27: 686.81488 | L27: 689.4306 | M27: 695.90314 | N27: 704.39606 | O27: 715.78516 | P27: 728.40607 | Q27: 741.20001 | R27: 752.46381 | S27: 764.91388 | T27: 778.96106 | U27: 790.86975 | V27: 801.79034 | W27: 813.50751 | X27: 825.59967 | Y27: 835.62042 | Z27: 847.15546 | AA27: 859.51312 | AB27: 873.85864 | AC27: 886.58179 | AD27: 900.4129 | AE27: 912.65735 | AF27: 925.97638 | AG27: 941.71063 | AH27: 957.63281 | AI27: 974.67029 | AJ27: 0.015
A28: Medium | B28: Transportation Energy Use: Highway: Freight Trucks: Medium: High oil and gas supply | C28: 45-AEO2021.15.highogs-d120120a | D28: trillion Btu | E28: 857.06537 | F28: 869.86615 | G28: 890.51807 | H28: 896.80109 | I28: 905.21356 | J28: 912.46588 | K28: 913.59228 | L28: 912.76141 | M28: 914.32025 | N28: 915.86731 | O28: 919.06012 | P28: 922.55646 | Q28: 927.62286 | R28: 931.74396 | S28: 938.57819 | T28: 949.5282 | U28: 960.74689 | V28: 973.51715 | W28: 988.40875 | X28: 1006.5817 | Y28: 1024.9167 | Z28: 1046.2407 | AA28: 1069.5592 | AB28: 1096.8451 | AC28: 1122.9235 | AD28: 1150.4531 | AE28: 1176.5758 | AF28: 1203.0889 | AG28: 1232.1707 | AH28: 1263.6315 | AI28: 1297.5896 | AJ28: 0.014
A29: Large (> 26000 pounds) | B29: Transportation Energy Use: Highway: Freight Trucks: Large: High oil and gas supply | C29: 45-AEO2021.16.highogs-d120120a | D29: trillion Btu | E29: 3737.7229 | F29: 3807.5073 | G29: 3905.2695 | H29: 3940.1116 | I29: 3981.8948 | J29: 4016.8679 | K29: 4010.8555 | L29: 3977.7935 | M29: 3936.0427 | N29: 3884.0256 | O29: 3834.8677 | P29: 3787.4297 | Q29: 3744.4802 | R29: 3702.4858 | S29: 3674.6531 | T29: 3664.7715 | U29: 3656.0122 | V29: 3648.28 | W29: 3646.7239 | X29: 3649.7461 | Y29: 3651.6387 | Z29: 3661.6887 | AA29: 3678.7134 | AB29: 3704.8914 | AC29: 3723.0164 | AD29: 3742.968 | AE29: 3754.6394 | AF29: 3763.2793 | AG29: 3775.218 | AH29: 3789.6326 | AI29: 3807.9399 | AJ29: 0.001
A30: Non-Highway | C30: 45-AEO2021.18.
A31: Air | B31: Transportation Energy Use: Non-Highway: Air: High oil and gas supply | C31: 45-AEO2021.19.highogs-d120120a | D31: trillion Btu | E31: 1860.4854 | F31: 2530.9844 | G31: 2826.3455 | H31: 2963.3054 | I31: 3051.7676 | J31: 3120.2192 | K31: 3144.2419 | L31: 3161.6294 | M31: 3182.7922 | N31: 3201.8508 | O31: 3222.4722 | P31: 3248.7065 | Q31: 3287.2988 | R31: 3325.2964 | S31: 3367.7896 | T31: 3416.8149 | U31: 3457.4727 | V31: 3492.2017 | W31: 3528.9043 | X31: 3570.2961 | Y31: 3622.0222 | Z31: 3669.8469 | AA31: 3718.9998 | AB31: 3765.7593 | AC31: 3814.1929 | AD31: 3866.814 | AE31: 3914.7515 | AF31: 3951.364 | AG31: 3990.6257 | AH31: 4026.4133 | AI31: 4062.8081 | AJ31: 0.026
A32: General Aviation | B32: Transportation Energy Use: Non-Highway: Air: General Aviation: High oil and gas supply | C32: 45-AEO2021.20.highogs-d120120a | D32: trillion Btu | E32: 109.97633 | F32: 141.88948 | G32: 155.94163 | H32: 162.45311 | I32: 166.65692 | J32: 169.90941 | K32: 171.04748 | L32: 171.87045 | M32: 172.87425 | N32: 173.77844 | O32: 174.75746 | P32: 176.00456 | Q32: 177.84047 | R32: 179.64813 | S32: 181.67046 | T32: 184.0038 | U32: 185.9389 | V32: 187.59193 | W32: 189.3391 | X32: 191.30975 | Y32: 193.77246 | Z32: 196.04944 | AA32: 198.38971 | AB32: 200.61627 | AC32: 202.92221 | AD32: 205.4279 | AE32: 207.71048 | AF32: 209.45377 | AG32: 211.3233 | AH32: 213.02757 | AI32: 214.76041 | AJ32: 0.023
A33: Domestic Passenger | B33: Transportation Energy Use: Non-Highway: Air: Domestic Passenger: High oil and gas supply | C33: 45-AEO2021.21.highogs-d120120a | D33: trillion Btu | E33: 1029.3035 | F33: 1377.4302 | G33: 1491.1099 | H33: 1527.3287 | I33: 1540.603 | J33: 1575.2826 | K33: 1594.6243 | L33: 1603.1229 | M33: 1606.5917 | N33: 1607.7135 | O33: 1610.0349 | P33: 1616.2908 | Q33: 1629.0068 | R33: 1642.5435 | S33: 1659.3156 | T33: 1678.5675 | U33: 1694.2118 | V33: 1706.4603 | W33: 1719.7704 | X33: 1737.08 | Y33: 1758.8617 | Z33: 1779.666 | AA33: 1799.6539 | AB33: 1818.678 | AC33: 1836.4475 | AD33: 1856.6439 | AE33: 1873.9916 | AF33: 1887.5896 | AG33: 1904.7295 | AH33: 1921.5889 | AI33: 1938.8723 | AJ33: 0.021
A34: International Passenger | B34: Transportation Energy Use: Non-Highway: Air: International Passenger: High oil and gas supply | C34: 45-AEO2021.22.highogs-d120120a | D34: trillion Btu | E34: 162.01057 | F34: 492.52274 | G34: 669.41522 | H34: 750.97778 | I34: 811.16065 | J34: 837.4071 | K34: 840.55621 | L34: 845.41003 | M34: 854.7381 | N34: 864.04321 | O34: 873.57477 | P34: 884.18176 | Q34: 898.26648 | R34: 911.64954 | S34: 925.93701 | T34: 942.49945 | U34: 956.36585 | V34: 968.7132 | W34: 981.62439 | X34: 995.19794 | Y34: 1012.1129 | Z34: 1027.5292 | AA34: 1044.0427 | AB34: 1059.8073 | AC34: 1076.9177 | AD34: 1095.1249 | AE34: 1112.1973 | AF34: 1125.2657 | AG34: 1138.3204 | AH34: 1149.8088 | AI34: 1161.4449 | AJ34: 0.068
A35: Dedicated Freight | B35: Transportation Energy Use: Non-Highway: Air: Dedicated Freight: High oil and gas supply | C35: 45-AEO2021.23.highogs-d120120a | D35: trillion Btu | E35: 559.19495 | F35: 519.14203 | G35: 509.87872 | H35: 522.54559 | I35: 533.34705 | J35: 537.62024 | K35: 538.01386 | L35: 541.22595 | M35: 548.58813 | N35: 556.31574 | O35: 564.1051 | P35: 572.22961 | Q35: 582.18518 | R35: 591.45514 | S35: 600.86682 | T35: 611.74402 | U35: 620.95605 | V35: 629.43628 | W35: 638.17041 | X35: 646.7085 | Y35: 657.27508 | Z35: 666.6023 | AA35: 676.91339 | AB35: 686.65765 | AC35: 697.90521 | AD35: 709.61707 | AE35: 720.85217 | AF35: 729.05499 | AG35: 736.25275 | AH35: 741.98798 | AI35: 747.73035 | AJ35: 0.01
A36: Water | B36: Transportation Energy Use: Non-Highway: Water: High oil and gas supply | C36: 45-AEO2021.24.highogs-d120120a | D36: trillion Btu | E36: 1129.1088 | F36: 1157.2632 | G36: 1251.9425 | H36: 1271.0579 | I36: 1220.1064 | J36: 1222.1813 | K36: 1231.5403 | L36: 1205.2488 | M36: 1202.4742 | N36: 1190.4596 | O36: 1189.082 | P36: 1203.5217 | Q36: 1186.6602 | R36: 1184.9104 | S36: 1180.7228 | T36: 1193.8921 | U36: 1177.7051 | V36: 1175.0314 | W36: 1182.9781 | X36: 1167.7097 | Y36: 1164.3445 | Z36: 1175.8888 | AA36: 1158.8889 | AB36: 1157.1489 | AC36: 1149.3973 | AD36: 1148.7852 | AE36: 1143.7438 | AF36: 1139.9766 | AG36: 1139.2001 | AH36: 1136.608 | AI36: 1132.9697 | AJ36: 0
A37: Freight | B37: Transportation Energy Use: Non-Highway: Water: Freight: High oil and gas supply | C37: 45-AEO2021.25.highogs-d120120a | D37: trillion Btu | E37: 933.23035 | F37: 960.6062 | G37: 1052.2262 | H37: 1069.5435 | I37: 1017.8489 | J37: 1019.6077 | K37: 1029.6858 | L37: 1004.8707 | M37: 1003.7998 | N37: 993.62921 | O37: 994.01324 | P37: 1009.9661 | Q37: 994.1709 | R37: 993.52716 | S37: 990.23901 | T37: 1004.0739 | U37: 988.7948 | V37: 987.27228 | W37: 996.31964 | X37: 981.9082 | Y37: 979.12146 | Z37: 991.30054 | AA37: 975.00702 | AB37: 973.97424 | AC37: 967.06848 | AD37: 967.10553 | AE37: 962.83832 | AF37: 960.09705 | AG37: 960.05969 | AH37: 958.24249 | AI37: 955.39801 | AJ37: 0.001
A38: Domestic Shipping | B38: Transportation Energy Use: Non-Highway: Water: Freight: Domestic Shipping: High oil and gas supply | C38: 45-AEO2021.26.highogs-d120120a | D38: trillion Btu | E38: 77.343407 | F38: 79.141403 | G38: 78.228264 | H38: 77.350044 | I38: 76.446533 | J38: 75.055573 | K38: 73.204681 | L38: 71.058418 | M38: 68.994972 | N38: 66.833633 | O38: 64.753128 | P38: 63.638058 | Q38: 62.605038 | R38: 61.510983 | S38: 60.561947 | T38: 59.665359 | U38: 58.721436 | V38: 57.711258 | W38: 56.658974 | X38: 55.745102 | Y38: 54.692238 | Z38: 54.265388 | AA38: 53.873783 | AB38: 53.634262 | AC38: 53.239914 | AD38: 52.87286 | AE38: 52.373196 | AF38: 51.890907 | AG38: 51.370388 | AH38: 50.910122 | AI38: 50.533489 | AJ38: -0.014
A39: International Shipping | B39: Transportation Energy Use: Non-Highway: Water: Freight: International Shipping: High oil and gas supply | C39: 45-AEO2021.27.highogs-d120120a | D39: trillion Btu | E39: 855.88696 | F39: 881.46478 | G39: 973.99793 | H39: 992.19336 | I39: 941.40234 | J39: 944.55212 | K39: 956.48108 | L39: 933.81226 | M39: 934.80481 | N39: 926.79559 | O39: 929.26013 | P39: 946.32806 | Q39: 931.56586 | R39: 932.01617 | S39: 929.67706 | T39: 944.40857 | U39: 930.07336 | V39: 929.56103 | W39: 939.66065 | X39: 926.16309 | Y39: 924.4292 | Z39: 937.03516 | AA39: 921.13324 | AB39: 920.33997 | AC39: 913.82855 | AD39: 914.23267 | AE39: 910.46515 | AF39: 908.20612 | AG39: 908.68933 | AH39: 907.3324 | AI39: 904.8645 | AJ39: 0.002
A40: Recreational Boats | B40: Transportation Energy Use: Non-Highway: Water: Recreational Boats: High oil and gas supply | C40: 45-AEO2021.28.highogs-d120120a | D40: trillion Btu | E40: 195.87843 | F40: 196.65694 | G40: 199.71631 | H40: 201.51434 | I40: 202.25748 | J40: 202.57369 | K40: 201.85445 | L40: 200.37804 | M40: 198.67445 | N40: 196.83032 | O40: 195.06877 | P40: 193.55562 | Q40: 192.48926 | R40: 191.38321 | S40: 190.48383 | T40: 189.81821 | U40: 188.91023 | V40: 187.75908 | W40: 186.65848 | X40: 185.8015 | Y40: 185.22307 | Z40: 184.58832 | AA40: 183.88181 | AB40: 183.17465 | AC40: 182.32883 | AD40: 181.67963 | AE40: 180.9055 | AF40: 179.87953 | AG40: 179.14038 | AH40: 178.36557 | AI40: 177.57169 | AJ40: -0.003
A41: Rail | B41: Transportation Energy Use: Non-Highway: Rail: High oil and gas supply | C41: 45-AEO2021.29.highogs-d120120a | D41: trillion Btu | E41: 461.76639 | F41: 491.05136 | G41: 497.25409 | H41: 498.29584 | I41: 498.00287 | J41: 483.20465 | K41: 487.16257 | L41: 485.19531 | M41: 488.07013 | N41: 490.24463 | O41: 492.73157 | P41: 493.54889 | Q41: 493.9744 | R41: 495.27838 | S41: 495.26675 | T41: 496.70953 | U41: 497.9765 | V41: 498.69684 | W41: 497.479 | X41: 499.69305 | Y41: 499.10703 | Z41: 500.07611 | AA41: 502.25479 | AB41: 505.43637 | AC41: 504.1955 | AD41: 505.57495 | AE41: 505.80637 | AF41: 507.0365 | AG41: 508.25165 | AH41: 509.73273 | AI41: 512.97174 | AJ41: 0.004
A42: Freight | B42: Transportation Energy Use: Non-Highway: Rail: Freight: High oil and gas supply | C42: 45-AEO2021.30.highogs-d120120a | D42: trillion Btu | E42: 432.32916 | F42: 455.80057 | G42: 457.32019 | H42: 454.81757 | I42: 451.84665 | J42: 435.03867 | K42: 437.54752 | L42: 434.49982 | M42: 437.06894 | N42: 438.99457 | O42: 440.98004 | P42: 441.53027 | Q42: 441.40082 | R42: 442.16769 | S42: 441.50205 | T42: 442.37979 | U42: 443.02426 | V42: 443.14713 | W42: 441.33752 | X42: 442.94101 | Y42: 441.56534 | Z42: 441.80859 | AA42: 443.27573 | AB42: 445.72418 | AC42: 443.77713 | AD42: 444.37201 | AE42: 443.88855 | AF42: 444.47339 | AG42: 444.99793 | AH42: 445.72116 | AI42: 448.21558 | AJ42: 0.001
... A53: Total | B53: Transportation Energy Use: Total: High oil and gas supply | C53: 45-AEO2021.43.highogs-d120120a | D53: trillion Btu | E53: 24641.816 | F53: 26248.666 | G53: 26805.998 | H53: 27035.342 | I53: 27134.359 | J53: 27234.799 | K53: 27191.32 | L53: 27084.865 | M53: 26996.002 | N53: 26866.41 | O53: 26748.799 | P53: 26660.07 | Q53: 26573.197 | R53: 26520.012 | S53: 26498.09 | T53: 26553.664 | U53: 26586.883 | V53: 26631.479 | W53: 26696.67 | X53: 26767.367 | Y53: 26871.051 | Z53: 27000.164 | AA53: 27121.412 | AB53: 27278.543 | AC53: 27415.6 | AD53: 27565.312 | AE53: 27701.846 | AF53: 27821.959 | AG53: 27950.746 | AH53: 28088.564 | AI53: 28244.232 | AJ53: 0.005
A54: Energy Use by Type | C54: 45-AEO2021.45.
A55: Motor Gasoline excluding E85 | B55: Transportation Energy Use: Petroleum: Motor Gasoline: High oil and gas supply | C55: 45-AEO2021.46.highogs-d120120a | D55: trillion Btu | E55: 14809.331 | F55: 15470.562 | G55: 15477.318 | H55: 15509.706 | I55: 15508.433 | J55: 15483.517 | K55: 15421.747 | L55: 15333.079 | M55: 15245.05 | N55: 15143.332 | O55: 15043.969 | P55: 14940.797 | Q55: 14850.533 | R55: 14780.868 | S55: 14725.552 | T55: 14695.301 | U55: 14674.445 | V55: 14655.884 | W55: 14640.091 | X55: 14640.239 | Y55: 14655.854 | Z55: 14675.101 | AA55: 14702.387 | AB55: 14734.696 | AC55: 14761.429 | AD55: 14788.444 | AE55: 14820.81 | AF55: 14848.021 | AG55: 14885.904 | AH55: 14929.089 | AI55: 14974.693 | AJ55: 0
A56: E85 | B56: Transportation Energy Use: E85: High oil and gas supply | C56: 45-AEO2021.47.highogs-d120120a | D56: trillion Btu | E56: 33.666061 | F56: 36.292164 | G56: 35.002701 | H56: 36.768921 | I56: 37.090172 | J56: 37.279301 | K56: 37.273434 | L56: 36.962608 | M56: 36.692116 | N56: 36.407269 | O56: 36.183594 | P56: 36.116623 | Q56: 36.088921 | R56: 36.198486 | S56: 36.388977 | T56: 36.925545 | U56: 37.477287 | V56: 38.130039 | W56: 38.828465 | X56: 39.735065 | Y56: 40.706123 | Z56: 41.727245 | AA56: 42.842529 | AB56: 43.978745 | AC56: 45.153854 | AD56: 46.265217 | AE56: 47.409328 | AF56: 48.760159 | AG56: 49.995644 | AH56: 51.544422 | AI56: 53.091187 | AJ56: 0.015
A57: Diesel | B57: Transportation Energy Use: Petroleum: Diesel: High oil and gas supply | C57: 45-AEO2021.48.highogs-d120120a | D57: trillion Btu | E57: 6144.374 | F57: 6254.561 | G57: 6296.688 | H57: 6333.9224 | I57: 6469.3887 | J57: 6508.3208 | K57: 6497.1807 | L57: 6493.1206 | M57: 6455.3403 | N57: 6414.4653 | O57: 6368.2964 | P57: 6301.3911 | Q57: 6279.1006 | R57: 6236.5176 | S57: 6213.1655 | T57: 6192.251 | U57: 6207.4717 | V57: 6203.5488 | W57: 6192.0122 | X57: 6220.2158 | Y57: 6226.5527 | Z57: 6228.9126 | AA57: 6273.5908 | AB57: 6314.6074 | AC57: 6347.5444 | AD57: 6376.3735 | AE57: 6399.9995 | AF57: 6418.7915 | AG57: 6440.9194 | AH57: 6466.8232 | AI57: 6500.1226 | AJ57: 0.002
A58: Jet Fuel (kerosene & naphtha) | B58: Transportation Energy Use: Petroleum: Jet Fuel: High oil and gas supply | C58: 45-AEO2021.49.highogs-d120120a | D58: trillion Btu | E58: 2239.7639 | F58: 2917.0544 | G58: 3212.9678 | H58: 3340.0581 | I58: 3422.0215 | J58: 3490.0879 | K58: 3513.1729 | L58: 3530.4417 | M58: 3553.7649 | N58: 3571.9607 | O58: 3591.0972 | P58: 3617.2712 | Q58: 3656.4937 | R58: 3695.1418 | S58: 3738.2942 | T58: 3787.9761 | U58: 3829.3232 | V58: 3864.7639 | W58: 3902.1855 | X58: 3944.3027 | Y58: 3996.7605 | Z58: 4045.3213 | AA58: 4095.2144 | AB58: 4142.7163 | AC58: 4191.8945 | AD58: 4245.2622 | AE58: 4293.9473 | AF58: 4331.3066 | AG58: 4371.3149 | AH58: 4407.8477 | AI58: 4444.9878 | AJ58: 0.023
A59: Residual Fuel Oil | B59: Transportation Energy Use: Petroleum: Residual Fuel Oil: High oil and gas supply | C59: 45-AEO2021.50.highogs-d120120a | D59: trillion Btu | E59: 434.51096 | F59: 495.77799 | G59: 725.47064 | H59: 768.43817 | I59: 637.95599 | J59: 643.69513 | K59: 671.79657 | L59: 613.03705 | M59: 614.04077 | N59: 592.20502 | O59: 596.73608 | P59: 638.2135 | Q59: 599.47522 | R59: 599.14294 | S59: 591.7016 | T59: 627.17792 | U59: 589.56049 | V59: 586.8938 | W59: 610.94092 | X59: 575.47443 | Y59: 569.64368 | Z59: 599.98962 | AA59: 558.53235 | AB59: 555.12524 | AC59: 537.4079 | AD59: 537.04724 | AE59: 526.17023 | AF59: 519.23303 | AG59: 519.10999 | AH59: 514.34662 | AI59: 506.8952 | AJ59: 0.005
A60: Aviation Gasoline | B60: Transportation Energy Use: Petroleum: Aviation Gasoline: High oil and gas supply | C60: 45-AEO2021.51.highogs-d120120a | D60: trillion Btu | E60: 22.450933 | F60: 22.434891 | G60: 22.421618 | H60: 22.410635 | I60: 22.401548 | J60: 22.394032 | K60: 22.387812 | L60: 22.382666 | M60: 22.378407 | N60: 22.374884 | O60: 22.371969 | P60: 22.369558 | Q60: 22.367563 | R60: 22.365911 | S60: 22.364546 | T60: 22.363417 | U60: 22.36248 | V60: 22.361708 | W60: 22.361067 | X60: 22.360538 | Y60: 22.3601 | Z60: 22.359737 | AA60: 22.359438 | AB60: 22.35919 | AC60: 22.358984 | AD60: 22.358814 | AE60: 22.358673 | AF60: 22.358557 | AG60: 22.358461 | AH60: 22.358381 | AI60: 22.358315 | AJ60: 0
A61: Propane | B61: Transportation Energy Use: Petroleum: Propane: High oil and gas supply | C61: 45-AEO2021.52.highogs-d120120a | D61: trillion Btu | E61: 5.55008 | F61: 6.081212 | G61: 6.44719 | H61: 6.641568 | I61: 6.762898 | J61: 6.878024 | K61: 6.961869 | L61: 7.054108 | M61: 7.103945 | N61: 7.166772 | O61: 7.258247 | P61: 7.319052 | Q61: 7.419724 | R61: 7.521624 | S61: 7.697729 | T61: 7.864295 | U61: 8.053552 | V61: 8.252381 | W61: 8.475512 | X61: 8.70771 | Y61: 8.956078 | Z61: 9.219524 | AA61: 9.490154 | AB61: 9.800427 | AC61: 10.104954 | AD61: 10.434702 | AE61: 10.753673 | AF61: 11.084869 | AG61: 11.440404 | AH61: 11.822479 | AI61: 12.232215 | AJ61: 0.027
A62: Lubricants | B62: Transportation Energy Use: Petroleum: Lubricants: High oil and gas supply | C62: 45-AEO2021.53.highogs-d120120a | D62: trillion Btu | E62: 121.22439 | F62: 123.40012 | G62: 124.82059 | H62: 125.91473 | I62: 126.65642 | J62: 127.04057 | K62: 127.20718 | L62: 126.85352 | M62: 126.59703 | N62: 126.37843 | O62: 126.07404 | P62: 125.8016 | Q62: 125.58483 | R62: 125.40055 | S62: 125.28949 | T62: 125.20488 | U62: 125.08443 | V62: 124.93435 | W62: 124.83044 | X62: 124.75782 | Y62: 124.67342 | Z62: 124.58897 | AA62: 124.5218 | AB62: 124.43999 | AC62: 124.42282 | AD62: 124.4984 | AE62: 124.51592 | AF62: 124.47363 | AG62: 124.49622 | AH62: 124.46999 | AI62: 124.38553 | AJ62: 0.001
A63: Petroleum and Other Liquids Subtotal | B63: Transportation Energy Use: Petroleum Subtotal: High oil and gas supply | C63: 45-AEO2021.54.highogs-d120120a | D63: trillion Btu | E63: 23810.873 | F63: 25326.166 | G63: 25901.135 | H63: 26143.859 | I63: 26230.709 | J63: 26319.215 | K63: 26297.729 | L63: 26162.932 | M63: 26060.969 | N63: 25914.291 | O63: 25791.986 | P63: 25689.277 | Q63: 25577.062 | R63: 25503.158 | S63: 25460.453 | T63: 25495.064 | U63: 25493.779 | V63: 25504.77 | W63: 25539.725 | X63: 25575.793 | Y63: 25645.508 | Z63: 25747.221 | AA63: 25828.938 | AB63: 25947.725 | AC63: 26040.316 | AD63: 26150.686 | AE63: 26245.965 | AF63: 26324.029 | AG63: 26425.539 | AH63: 26528.301 | AI63: 26638.766 | AJ63: 0.004
A64: M85 | B64: Transportation Energy Use: M85: High oil and gas supply | C64: 45-AEO2021.55.highogs-d120120a | D64: trillion Btu | E64: 0 | F64: 0 | G64: 0 | H64: 0 | I64: 0 | J64: 0 | K64: 0 | L64: 0 | M64: 0 | N64: 0 | O64: 0 | P64: 0 | Q64: 0 | R64: 0 | S64: 0 | T64: 0 | U64: 0 | V64: 0 | W64: 0 | X64: 0 | Y64: 0 | Z64: 0 | AA64: 0 | AB64: 0 | AC64: 0 | AD64: 0 | AE64: 0 | AF64: 0 | AG64: 0 | AH64: 0 | AI64: 0 | AJ64: - -
A65: Electricity | B65: Transportation Energy Use: Electricity: High oil and gas supply | C65: 45-AEO2021.56.highogs-d120120a | D65: trillion Btu | E65: 35.168571 | F65: 42.269836 | G65: 48.229595 | H65: 53.729454 | I65: 58.952888 | J65: 64.151711 | K65: 70.346672 | L65: 76.722725 | M65: 83.064751 | N65: 89.701584 | O65: 97.082611 | P65: 104.90831 | Q65: 113.70185 | R65: 123.35428 | S65: 133.98796 | T65: 145.52536 | U65: 157.87439 | V65: 170.92923 | W65: 184.78879 | X65: 199.451 | Y65: 215.07665 | Z65: 230.8228 | AA65: 246.89191 | AB65: 263.1506 | AC65: 280.03836 | AD65: 296.74304 | AE65: 313.74149 | AF65: 330.81247 | AG65: 348.42777 | AH65: 366.78662 | AI65: 385.29108 | AJ65: 0.083
A66: Compressed/Liquefied Natural Gas | B66: Transportation Energy Use: Natural Gas: High oil and gas supply | C66: 45-AEO2021.57.highogs-d120120a | D66: trillion Btu | E66: 87.254913 | F66: 112.34695 | G66: 98.182472 | H66: 102.5098 | I66: 117.44493 | J66: 122.34285 | K66: 127.29278 | L66: 138.77521 | M66: 145.19153 | N66: 155.24695 | O66: 159.69446 | P66: 164.35971 | Q66: 177.78354 | R66: 187.52266 | S66: 198.24445 | T66: 203.44011 | U66: 216.74155 | V66: 227.36365 | W66: 235.34441 | X66: 249.95869 | Y66: 263.73206 | Z66: 272.09653 | AA66: 290.60043 | AB66: 304.73328 | AC66: 320.40601 | AD66: 335.67789 | AE66: 350.99786 | AF66: 365.8024 | AG66: 379.2001 | AH66: 395.63809 | AI66: 413.71472 | AJ66: 0.053
A67: Hydrogen | B67: Transportation Energy Use: Hydrogen: High oil and gas supply | C67: 45-AEO2021.58.highogs-d120120a | D67: trillion Btu | E67: 0.277361 | F67: 0.294108 | G67: 0.298122 | H67: 0.302102 | I67: 0.305806 | J67: 0.310281 | K67: 0.315117 | L67: 0.321134 | M67: 0.32824 | N67: 0.336525 | O67: 0.346451 | P67: 0.357042 | Q67: 0.367403 | R67: 0.379223 | S67: 0.392209 | T67: 0.408699 | U67: 0.428046 | V67: 0.450503 | W67: 0.474421 | X67: 0.500565 | Y67: 0.530612 | Z67: 0.558742 | AA67: 0.588498 | AB67: 0.640967 | AC67: 0.669637 | AD67: 0.698541 | AE67: 0.727324 | AF67: 0.755534 | AG67: 0.783753 | AH67: 0.811744 | AI67: 0.839392 | AJ67: 0.038
A68: Pipeline Fuel Natural Gas | B68: Transportation Energy Use: Pipeline Fuel Natural Gas: High oil and gas supply | C68: 45-AEO2021.59.highogs-d120120a | D68: trillion Btu | E68: 706.25012 | F68: 765.14197 | G68: 755.34998 | H68: 731.63831 | I68: 723.20685 | J68: 724.60596 | K68: 691.04956 | L68: 701.14313 | M68: 701.06634 | N68: 701.03687 | O68: 693.45966 | P68: 694.47479 | Q68: 697.11835 | R68: 697.96668 | S68: 696.89435 | T68: 700.55658 | U68: 708.85254 | V68: 718.20209 | W68: 725.97797 | X68: 730.66339 | Y68: 734.56103 | Z68: 737.10724 | AA68: 741.27094 | AB68: 748.35034 | AC68: 759.38428 | AD68: 765.85901 | AE68: 773.89398 | AF68: 783.06421 | AG68: 778.31659 | AH68: 777.42078 | AI68: 784.83752 | AJ68: 0.004
A69: Total Consumption | B69: Transportation: Total Energy Use: High oil and gas supply | C69: 45-AEO2021.61.highogs-d120120a | D69: trillion Btu | E69: 24639.824 | F69: 26246.221 | G69: 26803.195 | H69: 27032.039 | I69: 27130.621 | J69: 27230.627 | K69: 27186.73 | L69: 27079.893 | M69: 26990.619 | N69: 26860.611 | O69: 26742.568 | P69: 26653.377 | Q69: 26566.033 | R69: 26512.381 | S69: 26489.973 | T69: 26544.994 | U69: 26577.676 | V69: 26621.715 | W69: 26686.311 | X69: 26756.367 | Y69: 26859.408 | Z69: 26987.805 | AA69: 27108.289 | AB69: 27264.598 | AC69: 27400.816 | AD69: 27549.664 | AE69: 27685.326 | AF69: 27804.465 | AG69: 27932.266 | AH69: 28068.959 | AI69: 28223.449 | AJ69: 0.005

Sheet AEO 2021 Table 46
A1: AEO.2021.HIGHOGS.ECI_VMT_NA_CLTR_TDS_NA_NA_BLNMLS.A
A2: Units | B2: billion miles
A3: A
A4: 43466 | B4: 2019-01-01 - 2050-01-01
A5: Fleet Vehicle Miles Traveled : Commercial Light Trucks : TDI Diesel, High oil and gas supply, AEO2021
A7: date | B7: value
A8: 2050 | B8: 48.533054
A9: 2049 | B9: 48.228958
A10: 2048 | B10: 47.872959
A11: 2047 | B11: 47.527718
A12: 2046 | B12: 47.220272
A13: 2045 | B13: 46.824818
A14: 2044 | B14: 46.39399
A15: 2043 | B15: 45.972202
A16: 2042 | B16: 45.519039
A17: 2041 | B17: 45.136539
A18: 2040 | B18: 44.77256
A19: 2039 | B19: 44.485531
... A38: 2020 | B38: 32.357178

Sheet AEO 2021 Table 47
E1: 2020 | F1: 2021 | G1: 2022 | H1: 2023 | I1: 2024 | J1: 2025 | K1: 2026 | L1: 2027 | M1: 2028 | N1: 2029 | O1: 2030 | P1: 2031 | Q1: 2032 | R1: 2033 | S1: 2034 | T1: 2035 | U1: 2036 | V1: 2037 | W1: 2038 | X1: 2039 | Y1: 2040 | Z1: 2041 | AA1: 2042 | AB1: 2043 | AC1: 2044 | AD1: 2045 | AE1: 2046 | AF1: 2047 | AG1: 2048 | AH1: 2049 | AI1: 2050 | AJ1: Growth (2020-2050)
A10: Table 47. Air Travel Energy Use
A11: https://www.eia.gov/outlooks/aeo/data/browser/#/?id=57-AEO2021&cases=highogs&sourcekey=0
A12: Mon Mar 08 2021 15:07:46 GMT-0800 (Pacific Standard Time)
A13: Source: U.S. Energy Information Administration
B14: full name | C14: api key | D14: units | E14: 2020 | F14: 2021 | G14: 2022 | H14: 2023 | I14: 2024 | J14: 2025 | K14: 2026 | L14: 2027 | M14: 2028 | N14: 2029 | O14: 2030 | P14: 2031 | Q14: 2032 | R14: 2033 | S14: 2034 | T14: 2035 | U14: 2036 | V14: 2037 | W14: 2038 | X14: 2039 | Y14: 2040 | Z14: 2041 | AA14: 2042 | AB14: 2043 | AC14: 2044 | AD14: 2045 | AE14: 2046 | AF14: 2047 | AG14: 2048 | AH14: 2049 | AI14: 2050 | AJ14: Growth (2020-2050)
A15: Fuel Cost (1987 dollars per million Btu) | B15: Air Travel: Fuel Cost: High oil and gas supply | C15: 57-AEO2021.2.highogs-d120120a | D15: 1987 $/MMBtu | E15: 4.815659 | F15: 5.225039 | G15: 5.661561 | H15: 6.07062 | I15: 6.344047 | J15: 6.384036 | K15: 6.625891 | L15: 6.825773 | M15: 6.943011 | N15: 7.10312 | O15: 7.293634 | P15: 7.380465 | Q15: 7.53721 | R15: 7.630815 | S15: 7.699437 | T15: 7.693654 | U15: 7.658198 | V15: 7.757175 | W15: 7.87585 | X15: 7.833405 | Y15: 8.049649 | Z15: 8.140811 | AA15: 8.218174 | AB15: 8.324425 | AC15: 8.451997 | AD15: 8.607639 | AE15: 8.685135 | AF15: 8.749039 | AG15: 8.773533 | AH15: 8.89049 | AI15: 8.968845 | AJ15: 0.021
A16: Ticket Price (1996 cents per passenger mile) | C16: 57-AEO2021.4.
A17: Domestic | B17: Air Travel: Ticket Price: Domestic: High oil and gas supply | C17: 57-AEO2021.5.highogs-d120120a | D17: 1996 cents | E17: 8.859536 | F17: 9.207203 | G17: 9.549512 | H17: 9.865418 | I17: 10.143012 | J17: 10.368609 | K17: 10.613405 | L17: 10.853698 | M17: 11.059388 | N17: 11.263126 | O17: 11.468404 | P17: 11.644133 | Q17: 11.822231 | R17: 11.981596 | S17: 12.12817 | T17: 12.254734 | U17: 12.377423 | V17: 12.518564 | W17: 12.655679 | X17: 12.75572 | Y17: 12.902014 | Z17: 13.019755 | AA17: 13.130799 | AB17: 13.245197 | AC17: 13.362012 | AD17: 13.480856 | AE17: 13.583618 | AF17: 13.678144 | AG17: 13.760929 | AH17: 13.856179 | AI17: 13.943871 | AJ17: 0.015
A18: International | B18: Air Travel: Ticket Price: International: High oil and gas supply | C18: 57-AEO2021.6.highogs-d120120a | D18: 1996 cents | E18: 11.967103 | F18: 12.894226 | G18: 13.546987 | H18: 14.025295 | I18: 14.390685 | J18: 14.679313 | K18: 14.935001 | L18: 15.16576 | M18: 15.374655 | N18: 15.575786 | O18: 15.773184 | P18: 15.961397 | Q18: 16.150122 | R18: 16.334641 | S18: 16.516947 | T18: 16.695312 | U18: 16.873196 | V18: 17.056742 | W18: 17.240631 | X18: 17.4165 | Y18: 17.605228 | Z18: 17.787903 | AA18: 17.969934 | AB18: 18.15366 | AC18: 18.338688 | AD18: 18.524971 | AE18: 18.707729 | AF18: 18.889225 | AG18: 19.068621 | AH18: 19.252192 | AI18: 19.434509 | AJ18: 0.016
A19: Non-U.S. | B19: Air Travel: Ticket Price: Non U.S.: High oil and gas supply | C19: 57-AEO2021.7.highogs-d120120a | D19: 1996 cents | E19: 11.967103 | F19: 12.894226 | G19: 13.546987 | H19: 14.025295 | I19: 14.390685 | J19: 14.679313 | K19: 14.935001 | L19: 15.16576 | M19: 15.374655 | N19: 15.575786 | O19: 15.773184 | P19: 15.961397 | Q19: 16.150122 | R19: 16.334641 | S19: 16.516947 | T19: 16.695312 | U19: 16.873196 | V19: 17.056742 | W19: 17.240631 | X19: 17.4165 | Y19: 17.605228 | Z19: 17.787903 | AA19: 17.969934 | AB19: 18.15366 | AC19: 18.338688 | AD19: 18.524971 | AE19: 18.707729 | AF19: 18.889225 | AG19: 19.068621 | AH19: 19.252192 | AI19: 19.434509 | AJ19: 0.016
A20: Load Factor (fraction of seats filled) | C20: 57-AEO2021.9.
A21: U.S. Domestic | B21: Air Travel: Load Factor: U.S. Domestic: High oil and gas supply | C21: 57-AEO2021.10.highogs-d120120a | D21: fraction | E21: 0.581099 | F21: 0.726373 | G21: 0.799011 | H21: 0.838961 | I21: 0.859821 | J21: 0.859821 | K21: 0.860774 | L21: 0.861627 | M21: 0.862389 | N21: 0.863072 | O21: 0.863687 | P21: 0.864239 | Q21: 0.86474 | R21: 0.865194 | S21: 0.865608 | T21: 0.865987 | U21: 0.866335 | V21: 0.866655 | W21: 0.866951 | X21: 0.867225 | Y21: 0.86752 | Z21: 0.867816 | AA21: 0.868112 | AB21: 0.868408 | AC21: 0.868704 | AD21: 0.869001 | AE21: 0.869297 | AF21: 0.869594 | AG21: 0.86989 | AH21: 0.870187 | AI21: 0.870484 | AJ21: 0.014
A22: U.S. International | B22: Air Travel: Load Factor: U.S. International: High oil and gas supply | C22: 57-AEO2021.11.highogs-d120120a | D22: fraction | E22: 0.67798 | F22: 0.745778 | G22: 0.797982 | H22: 0.821921 | I22: 0.824666 | J22: 0.824666 | K22: 0.824715 | L22: 0.824764 | M22: 0.82481 | N22: 0.824855 | O22: 0.8249 | P22: 0.824943 | Q22: 0.824987 | R22: 0.82503 | S22: 0.825073 | T22: 0.825116 | U22: 0.825159 | V22: 0.825201 | W22: 0.825241 | X22: 0.82528 | Y22: 0.825321 | Z22: 0.825362 | AA22: 0.825402 | AB22: 0.825443 | AC22: 0.825484 | AD22: 0.825524 | AE22: 0.825565 | AF22: 0.825606 | AG22: 0.825646 | AH22: 0.825687 | AI22: 0.825727 | AJ22: 0.007
A23: Driver Variables | C23: 57-AEO2021.13.
A24: Population (millions) | C24: 57-AEO2021.29.
A25: United States | B25: Air Travel: Drivers: Population: U.S.: High oil and gas supply | C25: 57-AEO2021.30.highogs-d120120a | D25: millions | E25: 330.40802 | F25: 332.66257 | G25: 334.98496 | H25: 337.28607 | I25: 339.56256 | J25: 341.81274 | K25: 344.03778 | L25: 346.23038 | M25: 348.38626 | N25: 350.51099 | O25: 352.59775 | P25: 354.63107 | Q25: 356.61285 | R25: 358.54746 | S25: 360.43543 | T25: 362.27774 | U25: 364.07599 | V25: 365.83209 | W25: 367.54804 | X25: 369.2262 | Y25: 370.86914 | Z25: 372.47977 | AA25: 374.06146 | AB25: 375.61777 | AC25: 377.15305 | AD25: 378.672 | AE25: 380.17905 | AF25: 381.67728 | AG25: 383.17071 | AH25: 384.66336 | AI25: 386.1586 | AJ25: 0.005
A26: Canada | B26: Air Travel: Drivers: Population: Canada: High oil and gas supply | C26: 57-AEO2021.31.highogs-d120120a | D26: millions | E26: 37.954399 | F26: 38.284569 | G26: 38.694302 | H26: 39.1026 | I26: 39.509079 | J26: 39.913521 | K26: 40.315201 | L26: 40.713902 | M26: 41.1092 | N26: 41.500671 | O26: 41.8881 | P26: 42.271 | Q26: 42.6493 | R26: 43.0228 | S26: 43.391499 | T26: 43.755501 | U26: 44.114731 | V26: 44.469398 | W26: 44.819481 | X26: 45.165298 | Y26: 45.506802 | Z26: 45.84388 | AA26: 46.176899 | AB26: 46.5056 | AC26: 46.831772 | AD26: 47.1562 | AE26: 47.479069 | AF26: 47.8008 | AG26: 48.12167 | AH26: 48.442322 | AI26: 48.763081 | AJ26: 0.008
A27: Central America | B27: Air Travel: Drivers: Population: Central America: High oil and gas supply | C27: 57-AEO2021.32.highogs-d120120a | D27: millions | E27: 223.32042 | F27: 225.61029 | G27: 227.87177 | H27: 230.10426 | I27: 232.30614 | J27: 234.4767 | K27: 236.53438 | L27: 238.5605 | M27: 240.55659 | N27: 242.52452 | O27: 244.46452 | P27: 246.26724 | Q27: 248.04324 | R27: 249.78932 | S27: 251.50108 | T27: 253.17491 | U27: 254.71349 | V27: 256.21668 | W27: 257.68503 | X27: 259.11847 | Y27: 260.51691 | Z27: 261.77008 | AA27: 262.98868 | AB27: 264.17175 | AC27: 265.32071 | AD27: 266.43298 | AE27: 267.38092 | AF27: 268.28256 | AG27: 269.15918 | AH27: 270.03339 | AI27: 270.9209 | AJ27: 0.006
A28: South America | B28: Air Travel: Drivers: Population: South America: High oil and gas supply | C28: 57-AEO2021.33.highogs-d120120a | D28: millions | E28: 430.70032 | F28: 433.89069 | G28: 437.24808 | H28: 440.69479 | I28: 444.09705 | J28: 447.36014 | K28: 450.48035 | L28: 453.44321 | M28: 456.26621 | N28: 458.98441 | O28: 461.62607 | P28: 464.07138 | Q28: 466.42432 | R28: 468.68573 | S28: 470.8587 | T28: 472.94543 | U28: 474.80039 | V28: 476.57565 | W28: 478.27377 | X28: 479.89575 | Y28: 481.44193 | Z28: 482.76858 | AA28: 484.01843 | AB28: 485.1962 | AC28: 486.30759 | AD28: 487.35217 | AE28: 488.16757 | AF28: 488.89957 | AG28: 489.58212 | AH28: 490.25284 | AI28: 490.93707 | AJ28: 0.004
A29: Europe | B29: Air Travel: Drivers: Population: Europe: High oil and gas supply | C29: 57-AEO2021.34.highogs-d120120a | D29: millions | E29: 631.30512 | F29: 632.64197 | G29: 633.69061 | H29: 634.54712 | I29: 635.32483 | J29: 636.11169 | K29: 636.90045 | L29: 637.65955 | M29: 638.40143 | N29: 639.13501 | O29: 639.86548 | P29: 640.57477 | Q29: 641.27387 | R29: 641.9436 | S29: 642.55975 | T29: 643.11066 | U29: 643.59149 | V29: 644.02026 | W29: 644.39563 | X29: 644.71454 | Y29: 644.96997 | Z29: 645.15045 | AA29: 645.26129 | AB29: 645.29871 | AC29: 645.26233 | AD29: 645.15008 | AE29: 644.94629 | AF29: 644.65442 | AG29: 644.28961 | AH29: 643.86713 | AI29: 643.39825 | AJ29: 0.001
A30: Africa | B30: Air Travel: Drivers: Population: Africa: High oil and gas supply | C30: 57-AEO2021.35.highogs-d120120a | D30: millions | E30: 1237.5863 | F30: 1269.3195 | G30: 1301.0847 | H30: 1332.8693 | I30: 1364.6515 | J30: 1396.4197 | K30: 1430.4786 | L30: 1464.5223 | M30: 1498.5533 | N30: 1532.5752 | O30: 1566.5935 | P30: 1602.6628 | Q30: 1638.724 | R30: 1674.7766 | S30: 1710.8201 | T30: 1746.8513 | U30: 1784.5621 | V30: 1822.2616 | W30: 1859.9501 | X30: 1897.6271 | Y30: 1935.2927 | Z30: 1974.2361 | AA30: 2013.1689 | AB30: 2052.0891 | AC30: 2090.9966 | AD30: 2129.8879 | AE30: 2169.5337 | AF30: 2209.1592 | AG30: 2248.7764 | AH30: 2288.3933 | AI30: 2328.0171 | AJ30: 0.021
A31: Mideast | B31: Air Travel: Drivers: Population: Mideast: High oil and gas supply | C31: 57-AEO2021.36.highogs-d120120a | D31: millions | E31: 363.01025 | F31: 370.27365 | G31: 377.6571 | H31: 384.60693 | I31: 391.44876 | J31: 398.2377 | K31: 404.39142 | L31: 410.4957 | M31: 416.58557 | N31: 422.6619 | O31: 428.73337 | P31: 434.43762 | Q31: 440.14346 | R31: 445.8414 | S31: 451.53378 | T31: 457.21707 | U31: 462.81811 | V31: 468.40582 | W31: 473.97998 | X31: 479.54068 | Y31: 485.08743 | Z31: 490.45166 | AA31: 495.79648 | AB31: 501.12061 | AC31: 506.42529 | AD31: 511.70911 | AE31: 516.69 | AF31: 521.64764 | AG31: 526.58185 | AH31: 531.48944 | AI31: 536.37134 | AJ31: 0.013
A32: Commonwealth of Independent States | B32: Air Travel: Drivers: Population: CIS: High oil and gas supply | C32: 57-AEO2021.37.highogs-d120120a | D32: millions | E32: 295.35101 | F32: 296.15237 | G32: 296.86581 | H32: 297.51209 | I32: 298.11151 | J32: 298.68005 | K32: 299.02649 | L32: 299.32474 | M32: 299.5896 | N32: 299.83374 | O32: 300.06818 | P32: 300.23135 | Q32: 300.371 | R32: 300.50034 | S32: 300.63248 | T32: 300.77875 | U32: 300.92786 | V32: 301.07996 | W32: 301.24084 | X32: 301.41635 | Y32: 301.61285 | Z32: 301.76486 | AA32: 301.93426 | AB32: 302.11798 | AC32: 302.31299 | AD32: 302.51758 | AE32: 302.60272 | AF32: 302.70096 | AG32: 302.80655 | AH32: 302.91498 | AI32: 303.01962 | AJ32: 0.001
A33: China | B33: Air Travel: Drivers: Population: China: High oil and gas supply | C33: 57-AEO2021.38.highogs-d120120a | D33: millions | E33: 1448.0883 | F33: 1452.8788 | G33: 1457.0895 | H33: 1460.7587 | I33: 1463.9377 | J33: 1466.6562 | K33: 1468.8712 | L33: 1470.5696 | M33: 1471.8082 | N33: 1472.6461 | O33: 1473.1196 | P33: 1473.2137 | Q33: 1472.9061 | R33: 1472.21 | S33: 1471.1553 | T33: 1469.7617 | U33: 1468.007 | V33: 1465.8787 | W33: 1463.4116 | X33: 1460.6281 | Y33: 1457.5527 | Z33: 1454.1775 | AA33: 1450.4868 | AB33: 1446.4911 | AC33: 1442.207 | AD33: 1437.6382 | AE33: 1432.7634 | AF33: 1427.5873 | AG33: 1422.1361 | AH33: 1416.4418 | AI33: 1410.5277 | AJ33: -0.001
A34: Northeast Asia | B34: Air Travel: Drivers: Population: NE Asia: High oil and gas supply | C34: 57-AEO2021.39.highogs-d120120a | D34: millions | E34: 203.51221 | F34: 203.23331 | G34: 202.90195 | H34: 202.52177 | I34: 202.09805 | J34: 201.63512 | K34: 201.11179 | L34: 200.55272 | M34: 199.95962 | N34: 199.33458 | O34: 198.67931 | P34: 197.96204 | Q34: 197.2198 | R34: 196.45235 | S34: 195.65695 | T34: 194.83237 | U34: 193.94443 | V34: 193.0322 | W34: 192.09723 | X34: 191.14259 | Y34: 190.16898 | Z34: 189.1526 | AA34: 188.11893 | AB34: 187.07098 | AC34: 186.01092 | AD34: 184.94035 | AE34: 183.84473 | AF34: 182.73785 | AG34: 181.62061 | AH34: 180.49268 | AI34: 179.35403 | AJ34: -0.004
A35: Southeast Asia | B35: Air Travel: Drivers: Population: SE Asia: High oil and gas supply | C35: 57-AEO2021.40.highogs-d120120a | D35: millions | E35: 693.59418 | F35: 700.03998 | G35: 706.37653 | H35: 712.60217 | I35: 718.71643 | J35: 724.72162 | K35: 730.40924 | L35: 735.99176 | M35: 741.46039 | N35: 746.80859 | O35: 752.02484 | P35: 756.83569 | Q35: 761.53821 | R35: 766.12176 | S35: 770.55542 | T35: 774.8374 | U35: 778.74304 | V35: 782.51917 | W35: 786.14233 | X35: 789.6203 | Y35: 792.96741 | Z35: 795.98102 | AA35: 798.84332 | AB35: 801.56574 | AC35: 804.15692 | AD35: 806.6189 | AE35: 808.73743 | AF35: 810.71435 | AG35: 812.56384 | AH35: 814.29297 | AI35: 815.89392 | AJ35: 0.005
A36: Southwest Asia | B36: Air Travel: Drivers: Population: SW Asia: High oil and gas supply | C36: 57-AEO2021.41.highogs-d120120a | D36: millions | E36: 1857.2878 | F36: 1878.0052 | G36: 1898.5497 | H36: 1918.882 | I36: 1938.9694 | J36: 1958.7787 | K36: 1977.7747 | L36: 1996.5376 | M36: 2015.0287 | N36: 2033.1875 | O36: 2050.9705 | P36: 2067.8467 | Q36: 2084.4138 | R36: 2100.6111 | S36: 2116.3733 | T36: 2131.6484 | U36: 2145.9319 | V36: 2159.7583 | W36: 2173.1479 | X36: 2186.0955 | Y36: 2198.5999 | Z36: 2210.1047 | AA36: 2221.1475 | AB36: 2231.7664 | AC36: 2242.0012 | AD36: 2251.8889 | AE36: 2260.7429 | AF36: 2269.2097 | AG36: 2277.3125 | AH36: 2285.0732 | AI36: 2292.5129 | AJ36: 0.007
A37: Oceania | B37: Air Travel: Drivers: Population: Oceania: High oil and gas supply | C37: 57-AEO2021.42.highogs-d120120a | D37: millions | E37: 41.872662 | F37: 42.303894 | G37: 42.843819 | H37: 43.472218 | I37: 44.120659 | J37: 44.75853 | K37: 45.396641 | L37: 46.033989 | M37: 46.673676 | N37: 47.314445 | O37: 47.953533 | P37: 48.592503 | Q37: 49.227642 | R37: 49.858459 | S37: 50.485577 | T37: 51.109753 | U37: 51.73032 | V37: 52.349121 | W37: 52.966591 | X37: 53.582478 | Y37: 54.196819 | Z37: 54.80682 | AA37: 55.41539 | AB37: 56.022621 | AC37: 56.62817 | AD37: 57.231895 | AE37: 57.828495 | AF37: 58.423195 | AG37: 59.016624 | AH37: 59.610176 | AI37: 60.202911 | AJ37: 0.012
A38: Travel Demand | C38: 57-AEO2021.44.
A39: Revenue Passenger Miles (billion miles) | C39: 57-AEO2021.45.
A40: Domestic | C40: 57-AEO2021.46.
A41: United States | B41: Air Travel: Travel Demand: Revenue Passenger Miles: Domestic: U.S.: High oil and gas supply | C41: 57-AEO2021.47.highogs-d120120a | D41: billion miles | E41: 369.82538 | F41: 580.62579 | G41: 676.04077 | H41: 724.85773 | I41: 752.83508 | J41: 778.23169 | K41: 796.84308 | L41: 809.83221 | M41: 820.70532 | N41: 830.52338 | O41: 840.79163 | P41: 852.89044 | Q41: 868.67493 | R41: 884.73956 | S41: 903.00507 | T41: 923.19763 | U41: 941.32788 | V41: 957.51031 | W41: 974.28094 | X41: 993.48871 | Y41: 1015.3478 | Z41: 1036.8887 | AA41: 1058.3246 | AB41: 1079.4786 | AC41: 1099.9337 | AD41: 1122.0978 | AE41: 1142.5673 | AF41: 1161.061 | AG41: 1182.67 | AH41: 1204.316 | AI41: 1226.429 | AJ41: 0.041
A42: Canada | B42: Air Travel: Travel Demand: Revenue Passenger Miles: Domestic: Canada: High oil and gas supply | C42: 57-AEO2021.48.highogs-d120120a | D42: billion miles | E42: 18.525003 | F42: 29.084255 | G42: 33.863708 | H42: 36.30901 | I42: 37.220688 | J42: 38.157196 | K42: 39.119949 | L42: 40.100441 | M42: 41.096569 | N42: 42.11042 | O42: 43.140255 | P42: 44.19162 | Q42: 45.265965 | R42: 46.364067 | S42: 47.481873 | T42: 48.616447 | U42: 49.779911 | V42: 50.961964 | W42: 52.162964 | X42: 53.385956 | Y42: 54.629051 | Z42: 55.882683 | AA42: 57.156471 | AB42: 58.449677 | AC42: 59.764442 | AD42: 61.102516 | AE42: 62.464691 | AF42: 63.850094 | AG42: 65.25589 | AH42: 66.68174 | AI42: 68.131744 | AJ42: 0.044
A43: Central America | B43: Air Travel: Travel Demand: Revenue Passenger Miles: Domestic: Central America: High oil and gas supply | C43: 57-AEO2021.49.highogs-d120120a | D43: billion miles | E43: 17.453876 | F43: 27.402586 | G43: 31.905685 | H43: 34.209599 | I43: 35.160442 | J43: 36.130829 | K43: 37.11787 | L43: 38.126411 | M43: 39.156616 | N43: 40.208355 | O43: 41.279537 | P43: 42.35775 | Q43: 43.454456 | R43: 44.573467 | S43: 45.715443 | T43: 46.88184 | U43: 48.058697 | V43: 49.259151 | W43: 50.484474 | X43: 51.735348 | Y43: 53.012226 | Z43: 54.303322 | AA43: 55.619781 | AB43: 56.962555 | AC43: 58.332153 | AD43: 59.72858 | AE43: 61.122387 | AF43: 62.541126 | AG43: 63.987324 | AH43: 65.463959 | AI43: 66.973106 | AJ43: 0.046
A44: South America | B44: Air Travel: Travel Demand: Revenue Passenger Miles: Domestic: South America: High oil and gas supply | C44: 57-AEO2021.50.highogs-d120120a | D44: billion miles | E44: 55.321846 | F44: 86.855293 | G44: 101.12833 | H44: 108.43082 | I44: 115.76936 | J44: 123.41761 | K44: 131.45252 | L44: 139.75444 | M44: 148.38783 | N44: 157.33893 | O44: 166.57526 | P44: 176.16415 | Q44: 186.22926 | R44: 196.82834 | S44: 207.99194 | T44: 219.75845 | U44: 232.06998 | V44: 245.03912 | W44: 258.69659 | X44: 273.07733 | Y44: 288.21436 | Z44: 303.92282 | AA44: 320.45532 | AB44: 337.85367 | AC44: 356.16492 | AD44: 375.43466 | AE44: 395.43231 | AF44: 416.45608 | AG44: 438.55322 | AH44: 461.77103 | AI44: 486.16522 | AJ44: 0.075
A45: Europe | B45: Air Travel: Travel Demand: Revenue Passenger Miles: Domestic: Europe: High oil and gas supply | C45: 57-AEO2021.51.highogs-d120120a | D45: billion miles | E45: 316.60953 | F45: 497.07693 | G45: 578.76221 | H45: 620.55469 | I45: 646.80829 | J45: 671.63062 | K45: 695.7608 | L45: 720.1615 | M45: 745.03186 | N45: 770.19171 | O45: 795.60901 | P45: 821.55493 | Q45: 847.85956 | R45: 874.79309 | S45: 902.60052 | T45: 931.23901 | U45: 960.7298 | V45: 991.18616 | W45: 1022.6212 | X45: 1055.0826 | Y45: 1088.6486 | Z45: 1123.2905 | AA45: 1158.9957 | AB45: 1195.7516 | AC45: 1233.5331 | AD45: 1272.4342 | AE45: 1312.4834 | AF45: 1353.7244 | AG45: 1396.3245 | AH45: 1440.3989 | AI45: 1485.9657 | AJ45: 0.053
A46: Africa | B46: Air Travel: Travel Demand: Revenue Passenger Miles: Domestic: Africa: High oil and gas supply | C46: 57-AEO2021.52.highogs-d120120a | D46: billion miles | E46: 17.486584 | F46: 32.437614 | G46: 39.204922 | H46: 42.667267 | I46: 45.441738 | J46: 48.311897 | K46: 51.282871 | L46: 54.407349 | M46: 57.689175 | N46: 61.139008 | O46: 64.76963 | P46: 68.577629 | Q46: 72.600006 | R46: 76.861214 | S46: 81.380829 | T46: 86.179779 | U46: 91.262474 | V46: 96.651337 | W46: 102.3629 | X46: 108.42369 | Y46: 114.84943 | Z46: 121.62924 | AA46: 128.81429 | AB46: 136.43881 | AC46: 144.53152 | AD46: 153.11896 | AE46: 162.18381 | AF46: 171.80678 | AG46: 182.02756 | AH46: 192.8931 | AI46: 204.44766 | AJ46: 0.085
A47: Mideast | B47: Air Travel: Travel Demand: Revenue Passenger Miles: Domestic: Mideast: High oil and gas supply | C47: 57-AEO2021.53.highogs-d120120a | D47: billion miles | E47: 38.344875 | F47: 60.201454 | G47: 70.094429 | H47: 75.155952 | I47: 78.739883 | J47: 82.252831 | K47: 85.878456 | L47: 89.631821 | M47: 93.553322 | N47: 97.598724 | O47: 101.78121 | P47: 106.13272 | Q47: 110.64435 | R47: 115.34994 | S47: 120.25143 | T47: 125.35908 | U47: 130.62488 | V47: 136.08115 | W47: 141.75139 | X47: 147.64004 | Y47: 153.74091 | Z47: 160.01938 | AA47: 166.51738 | AB47: 173.24608 | AC47: 180.21156 | AD47: 187.42691 | AE47: 194.89969 | AF47: 202.64676 | AG47: 210.67555 | AH47: 218.99519 | AI47: 227.63222 | AJ47: 0.061
A48: Commonwealth of Independent States | B48: Air Travel: Travel Demand: Revenue Passenger Miles: Domestic: CIS: High oil and gas supply | C48: 57-AEO2021.54.highogs-d120120a | D48: billion miles | E48: 70.372009 | F48: 97.113365 | G48: 109.21735 | H48: 115.41009 | I48: 118.43157 | J48: 121.34063 | K48: 124.02645 | L48: 126.76453 | M48: 129.60115 | N48: 132.54344 | O48: 135.58772 | P48: 138.76421 | Q48: 142.06958 | R48: 145.46306 | S48: 148.90518 | T48: 152.36157 | U48: 155.74182 | V48: 159.15016 | W48: 162.59885 | X48: 166.10902 | Y48: 169.69312 | Z48: 173.24847 | AA48: 176.8634 | AB48: 180.54356 | AC48: 184.29125 | AD48: 188.10719 | AE48: 191.86749 | AF48: 195.68025 | AG48: 199.56403 | AH48: 203.53575 | AI48: 207.6064 | AJ48: 0.037
A49: China | B49: Air Travel: Travel Demand: Revenue Passenger Miles: Domestic: China: High oil and gas supply | C49: 57-AEO2021.55.highogs-d120120a | D49: billion miles | E49: 322.65189 | F49: 445.25958 | G49: 500.75571 | H49: 529.14905 | I49: 563.79492 | J49: 600.16229 | K49: 636.24744 | L49: 672.70203 | M49: 709.95038 | N49: 747.70599 | O49: 785.86993 | P49: 824.81647 | Q49: 863.92505 | R49: 903.23718 | S49: 942.72809 | T49: 982.66113 | U49: 1022.9439 | V49: 1063.2118 | W49: 1103.4707 | X49: 1144.1088 | Y49: 1185.5891 | Z49: 1228.238 | AA49: 1272.0452 | AB49: 1316.6273 | AC49: 1361.4971 | AD49: 1406.0875 | AE49: 1450.2505 | AF49: 1494.3059 | AG49: 1538.059 | AH49: 1581.0083 | AI49: 1622.6553 | AJ49: 0.055
A50: Northeast Asia | B50: Air Travel: Travel Demand: Revenue Passenger Miles: Domestic: NE Asia: High oil and gas supply | C50: 57-AEO2021.56.highogs-d120120a | D50: billion miles | E50: 37.983845 | F50: 61.913666 | G50: 72.745056 | H50: 78.286697 | I50: 79.509041 | J50: 80.612335 | K50: 81.640823 | L50: 82.618645 | M50: 83.551384 | N50: 84.439468 | O50: 85.284935 | P50: 86.064423 | Q50: 86.789017 | R50: 87.501488 | S50: 88.208656 | T50: 88.908485 | U50: 89.593925 | V50: 90.267281 | W50: 90.929108 | X50: 91.587013 | Y50: 92.24575 | Z50: 92.903259 | AA50: 93.564262 | AB50: 94.224846 | AC50: 94.885628 | AD50: 95.547722 | AE50: 96.206131 | AF50: 96.864891 | AG50: 97.527603 | AH50: 98.197266 | AI50: 98.875748 | AJ50: 0.032
A51: Southeast Asia | B51: Air Travel: Travel Demand: Revenue Passenger Miles: Domestic: SE Asia: High oil and gas supply | C51: 57-AEO2021.57.highogs-d120120a | D51: billion miles | E51: 91.591103 | F51: 143.79802 | G51: 167.42853 | H51: 179.51857 | I51: 192.48387 | J51: 205.84511 | K51: 219.71851 | L51: 234.07787 | M51: 248.89903 | N51: 264.13733 | O51: 279.73605 | P51: 295.91055 | Q51: 312.68527 | R51: 330.0827 | S51: 348.19043 | T51: 367.04813 | U51: 386.51221 | V51: 406.76389 | W51: 427.85422 | X51: 449.80554 | Y51: 472.6983 | Z51: 496.45749 | AA51: 521.16278 | AB51: 546.7785 | AC51: 573.38159 | AD51: 600.94647 | AE51: 628.88501 | AF51: 657.68213 | AG51: 687.45367 | AH51: 718.3219 | AI51: 750.4455 | AJ51: 0.073
A52: Southwest Asia | B52: Air Travel: Travel Demand: Revenue Passenger Miles: Domestic: SW Asia: High oil and gas supply | C52: 57-AEO2021.58.highogs-d120120a | D52: billion miles | E52: 42.749336 | F52: 67.116455 | G52: 78.145782 | H52: 83.788704 | I52: 91.737885 | J52: 100.33836 | K52: 109.57109 | L52: 119.58209 | M52: 130.4118 | N52: 141.95897 | O52: 154.03793 | P52: 166.51022 | Q52: 179.20828 | R52: 192.00363 | S52: 204.84288 | T52: 218.07712 | U52: 231.87807 | V52: 246.34757 | W52: 261.52185 | X52: 277.41717 | Y52: 294.05609 | Z52: 311.32965 | AA52: 329.32654 | AB52: 348.09708 | AC52: 367.64569 | AD52: 387.98361 | AE52: 409.00678 | AF52: 430.76804 | AG52: 453.32584 | AH52: 476.67316 | AI52: 500.83752 | AJ52: 0.085
A53: Oceania | B53: Air Travel: Travel Demand: Revenue Passenger Miles: Domestic: Oceania: High oil and gas supply | C53: 57-AEO2021.59.highogs-d120120a | D53: billion miles | E53: 33.617504 | F53: 52.77948 | G53: 61.452797 | H53: 65.890312 | I53: 69.145271 | J53: 71.958427 | K53: 74.646049 | L53: 77.407784 | M53: 80.247612 | N53: 83.166588 | O53: 86.168419 | P53: 89.253082 | Q53: 92.405357 | R53: 95.613235 | S53: 98.872574 | T53: 102.17998 | U53: 105.51692 | V53: 108.8607 | W53: 112.14288 | X53: 115.39744 | Y53: 118.73898 | Z53: 122.16554 | AA53: 125.68075 | AB53: 129.28754 | AC53: 132.9883 | AD53: 136.78754 | AE53: 140.68867 | AF53: 144.69415 | AG53: 148.80844 | AH53: 153.03239 | AI53: 157.37184 | AJ53: 0.053
A54: International | C54: 57-AEO2021.60.
A55: United States | B55: Air Travel: Travel Demand: Revenue Passenger Miles: International: U.S.: High oil and gas supply | C55: 57-AEO2021.61.highogs-d120120a | D55: billion miles | E55: 65.570099 | F55: 203.26729 | G55: 285.88559 | H55: 335.4566 | I55: 372.63483 | J55: 394.94174 | K55: 405.67648 | L55: 414.17032 | M55: 421.85757 | N55: 429.17264 | O55: 436.74332 | P55: 445.15549 | Q55: 455.21204 | R55: 465.47653 | S55: 476.77606 | T55: 489.00378 | U55: 500.44461 | V55: 511.13968 | W55: 522.18555 | X55: 534.39581 | Y55: 547.87726 | Z55: 561.33588 | AA55: 574.86658 | AB55: 588.39252 | AC55: 601.72943 | AD55: 615.95178 | AE55: 629.54541 | AF55: 642.37738 | AG55: 656.73962 | AH55: 671.25531 | AI55: 686.12293 | AJ55: 0.081
A56: Canada | B56: Air Travel: Travel Demand: Revenue Passenger Miles: International: Canada: High oil and gas supply | C56: 57-AEO2021.62.highogs-d120120a | D56: billion miles | E56: 14.672773 | F56: 45.485588 | G56: 63.973286 | H56: 75.065895 | I56: 83.385361 | J56: 88.377029 | K56: 90.958076 | L56: 93.600037 | M56: 96.294205 | N56: 99.051109 | O56: 101.86331 | P56: 104.7577 | Q56: 107.74153 | R56: 110.81943 | S56: 113.97297 | T56: 117.18838 | U56: 120.52329 | V56: 123.92911 | W56: 127.40781 | X56: 130.9733 | Y56: 134.61702 | Z56: 138.29324 | AA56: 142.0473 | AB56: 145.87653 | AC56: 149.7861 | AD56: 153.78218 | AE56: 157.86806 | AF56: 162.03792 | AG56: 166.27649 | AH56: 170.57942 | AI56: 174.96552 | AJ56: 0.086
A57: Central America | B57: Air Travel: Travel Demand: Revenue Passenger Miles: International: Central America: High oil and gas supply | C57: 57-AEO2021.63.highogs-d120120a | D57: billion miles | E57: 18.003374 | F57: 55.810452 | G57: 78.494705 | H57: 92.105255 | I57: 102.31316 | J57: 108.43791 | K57: 112.81432 | L57: 117.35099 | M57: 122.05265 | N57: 126.923 | O57: 131.95924 | P57: 137.12674 | Q57: 142.46431 | R57: 147.98975 | S57: 153.71037 | T57: 159.63664 | U57: 165.72672 | V57: 172.02902 | W57: 178.55362 | X57: 185.30893 | Y57: 192.30258 | Z57: 199.50006 | AA57: 206.94493 | AB57: 214.64732 | AC57: 222.61583 | AD57: 230.85744 | AE57: 239.26366 | AF57: 247.9469 | AG57: 256.92361 | AH57: 266.21265 | AI57: 275.83002 | AJ57: 0.095
A58: South America | B58: Air Travel: Travel Demand: Revenue Passenger Miles: International: South America: High oil and gas supply | C58: 57-AEO2021.64.highogs-d120120a | D58: billion miles | E58: 13.002868 | F58: 40.308884 | G58: 56.692497 | H58: 66.522667 | I58: 73.895287 | J58: 78.318863 | K58: 82.077789 | L58: 85.938332 | M58: 89.917984 | N58: 94.019157 | O58: 98.240234 | P58: 102.58093 | Q58: 107.08217 | R58: 111.75675 | S58: 116.61185 | T58: 121.65599 | U58: 126.85339 | V58: 132.25114 | W58: 137.85614 | X58: 143.67578 | Y58: 149.71684 | Z58: 155.91588 | AA58: 162.34851 | AB58: 169.02371 | AC58: 175.95175 | AD58: 183.14114 | AE58: 190.5117 | AF58: 198.15027 | AG58: 206.074 | AH58: 214.30229 | AI58: 222.85399 | AJ58: 0.099
A59: Europe | B59: Air Travel: Travel Demand: Revenue Passenger Miles: International: Europe: High oil and gas supply | C59: 57-AEO2021.65.highogs-d120120a | D59: billion miles | E59: 94.620331 | F59: 293.32297 | G59: 412.54456 | H59: 484.07752 | I59: 537.72723 | J59: 569.91705 | K59: 591.83167 | L59: 614.21887 | M59: 637.21295 | N59: 660.71783 | O59: 684.72632 | P59: 709.40973 | Q59: 734.67914 | R59: 760.7063 | S59: 787.64777 | T59: 815.48633 | U59: 844.24689 | V59: 874.02087 | W59: 904.83142 | X59: 936.72302 | Y59: 969.75775 | Z59: 1003.9291 | AA59: 1039.2471 | AB59: 1075.7183 | AC59: 1113.3428 | AD59: 1152.1962 | AE59: 1192.3058 | AF59: 1233.7183 | AG59: 1276.5686 | AH59: 1320.96 | AI59: 1366.9329 | AJ59: 0.093
A60: Africa | B60: Air Travel: Travel Demand: Revenue Passenger Miles: International: Africa: High oil and gas supply | C60: 57-AEO2021.66.highogs-d120120a | D60: billion miles | E60: 13.566049 | F60: 42.054741 | G60: 59.147961 | H60: 69.403893 | I60: 77.09584 | J60: 81.711006 | K60: 85.881401 | L60: 90.216217 | M60: 94.715645 | N60: 99.390778 | O60: 104.25558 | P60: 109.298 | Q60: 114.56918 | R60: 120.09891 | S60: 125.90818 | T60: 132.01904 | U60: 138.42781 | V60: 145.15707 | W60: 152.21997 | X60: 159.64351 | Y60: 167.43776 | Z60: 175.57419 | AA60: 184.11291 | AB60: 193.08794 | AC60: 202.52382 | AD60: 212.44098 | AE60: 222.79884 | AF60: 233.69058 | AG60: 245.15062 | AH60: 257.22125 | AI60: 269.93924 | AJ60: 0.105
A61: Mideast | B61: Air Travel: Travel Demand: Revenue Passenger Miles: International: Mideast: High oil and gas supply | C61: 57-AEO2021.67.highogs-d120120a | D61: billion miles | E61: 68.406685 | F61: 153.18611 | G61: 204.05377 | H61: 234.57436 | I61: 257.46481 | J61: 271.1991 | K61: 284.82852 | L61: 299.03766 | M61: 313.87616 | N61: 329.36932 | O61: 345.55145 | P61: 362.15256 | Q61: 379.48703 | R61: 397.57797 | S61: 416.45868 | T61: 436.15863 | U61: 456.63828 | V61: 477.99573 | W61: 500.26679 | X61: 523.48859 | Y61: 547.69873 | Z61: 572.74072 | AA61: 598.83221 | AB61: 626.01361 | AC61: 654.32959 | AD61: 683.82324 | AE61: 714.1546 | AF61: 745.72894 | AG61: 778.5943 | AH61: 812.79614 | AI61: 848.38794 | AJ61: 0.088
A62: Commonwealth of Independent States | B62: Air Travel: Travel Demand: Revenue Passenger Miles: International: CIS: High oil and gas supply | C62: 57-AEO2021.68.highogs-d120120a | D62: billion miles | E62: 11.722843 | F62: 36.340809 | G62: 51.111591 | H62: 59.974056 | I62: 66.620903 | J62: 70.609016 | K62: 73.09964 | L62: 75.673409 | M62: 78.359222 | N62: 81.164581 | O62: 84.090942 | P62: 87.158897 | Q62: 90.371284 | R62: 93.707642 | S62: 97.147156 | T62: 100.67101 | U62: 104.22345 | V62: 107.87114 | W62: 111.62434 | X62: 115.49968 | Y62: 119.50872 | Z62: 123.5842 | AA62: 127.7888 | AB62: 132.12967 | AC62: 136.61189 | AD62: 141.23961 | AE62: 145.92397 | AF62: 150.74739 | AG62: 155.72696 | AH62: 160.87924 | AI62: 166.21695 | AJ62: 0.092
A63: China | B63: Air Travel: Travel Demand: Revenue Passenger Miles: International: China: High oil and gas supply | C63: 57-AEO2021.69.highogs-d120120a | D63: billion miles | E63: 35.273876 | F63: 109.34899 | G63: 153.79408 | H63: 180.46112 | I63: 200.46141 | J63: 212.46156 | K63: 224.35466 | L63: 236.53804 | M63: 249.10504 | N63: 262.01666 | O63: 275.26788 | P63: 288.93747 | Q63: 302.91779 | R63: 317.22726 | S63: 331.87354 | T63: 346.91757 | U63: 362.34909 | V63: 378.10678 | W63: 394.20401 | X63: 410.7258 | Y63: 427.77374 | Z63: 445.42065 | AA63: 463.67426 | AB63: 482.47348 | AC63: 501.73639 | AD63: 521.36145 | AE63: 541.32306 | AF63: 561.69177 | AG63: 582.44037 | AH63: 603.4798 | AI63: 624.71722 | AJ63: 0.101
A64: Northeast Asia | B64: Air Travel: Travel Demand: Revenue Passenger Miles: International: NE Asia: High oil and gas supply | C64: 57-AEO2021.70.highogs-d120120a | D64: billion miles | E64: 28.045706 | F64: 86.941673 | G64: 122.27925 | H64: 143.4818 | I64: 159.38371 | J64: 168.92487 | K64: 173.36366 | L64: 177.35877 | M64: 180.95363 | N64: 184.13841 | O64: 186.92436 | P64: 189.17274 | Q64: 190.86563 | R64: 192.48216 | S64: 194.11275 | T64: 195.744 | U64: 197.44258 | V64: 199.08099 | W64: 200.66232 | X64: 202.26215 | Y64: 203.93388 | Z64: 205.76344 | AA64: 207.69791 | AB64: 209.68344 | AC64: 211.72054 | AD64: 213.81732 | AE64: 215.98955 | AF64: 218.22203 | AG64: 220.55528 | AH64: 223.02905 | AI64: 225.66971 | AJ64: 0.072
A65: Southeast Asia | B65: Air Travel: Travel Demand: Revenue Passenger Miles: International: SE Asia: High oil and gas supply | C65: 57-AEO2021.71.highogs-d120120a | D65: billion miles | E65: 21.643387 | F65: 126.89863 | G65: 190.05179 | H65: 227.94367 | I65: 256.36258 | J65: 273.41394 | K65: 289.28082 | L65: 305.2157 | M65: 321.13416 | N65: 336.9155 | O65: 352.42365 | P65: 368.10632 | Q65: 383.90146 | R65: 399.81357 | S65: 415.96918 | T65: 432.39505 | U65: 448.85962 | V65: 465.57364 | W65: 482.58496 | X65: 499.87982 | Y65: 517.53766 | Z65: 535.45215 | AA65: 553.64624 | AB65: 572.00946 | AC65: 590.61169 | AD65: 609.36267 | AE65: 627.41431 | AF65: 645.40796 | AG65: 663.47107 | AH65: 681.73303 | AI65: 700.37152 | AJ65: 0.123
A66: Southwest Asia | B66: Air Travel: Travel Demand: Revenue Passenger Miles: International: SW Asia: High oil and gas supply | C66: 57-AEO2021.72.highogs-d120120a | D66: billion miles | E66: 6.562674 | F66: 38.478001 | G66: 57.627201 | H66: 69.116722 | I66: 77.733849 | J66: 82.904129 | K66: 89.352066 | L66: 96.253311 | M66: 103.62447 | N66: 111.39778 | O66: 119.46008 | P66: 127.72341 | Q66: 136.103 | R66: 144.53044 | S66: 152.98093 | T66: 161.65552 | U66: 170.64056 | V66: 180.00096 | W66: 189.75528 | X66: 199.91042 | Y66: 210.47678 | Z66: 221.38066 | AA66: 232.68089 | AB66: 244.40404 | AC66: 256.55225 | AD66: 269.13156 | AE66: 282.06607 | AF66: 295.40161 | AG66: 309.16885 | AH66: 323.36472 | AI66: 338.00391 | AJ66: 0.14
A67: Oceania | B67: Air Travel: Travel Demand: Revenue Passenger Miles: International: Oceania: High oil and gas supply | C67: 57-AEO2021.73.highogs-d120120a | D67: billion miles | E67: 7.173075 | F67: 42.056881 | G67: 62.987167 | H67: 75.545334 | I67: 84.963966 | J67: 90.615143 | K67: 93.977692 | L67: 97.440178 | M67: 101.01068 | N67: 104.69011 | O67: 108.478 | P67: 112.37884 | Q67: 116.38269 | R67: 120.4857 | S67: 124.68911 | T67: 128.99475 | U67: 133.39592 | V67: 137.88853 | W67: 142.44711 | X67: 147.08736 | Y67: 151.85921 | Z67: 156.759 | AA67: 161.79628 | AB67: 166.97514 | AC67: 172.29864 | AD67: 177.77121 | AE67: 183.3858 | AF67: 189.15707 | AG67: 195.09128 | AH67: 201.19511 | AI67: 207.47226 | AJ67: 0.119
A68: Freight Revenue Ton Miles (billion miles) | C68: 57-AEO2021.75.
A69: United States | B69: Air Travel: Travel Demand: Revenue Ton Miles: Freight: US: High oil and gas supply | C69: 57-AEO2021.76.highogs-d120120a | D69: billion miles | E69: 43.981495 | F69: 45.429356 | G69: 47.498997 | H69: 49.332542 | I69: 50.937168 | J69: 52.453938 | K69: 53.721714 | L69: 54.783749 | M69: 55.773514 | N69: 56.731701 | O69: 57.716473 | P69: 58.781715 | Q69: 60.002583 | R69: 61.245003 | S69: 62.586121 | T69: 64.015724 | U69: 65.374031 | V69: 66.665184 | W69: 67.991356 | X69: 69.428192 | Y69: 70.985435 | Z69: 72.543022 | AA69: 74.110046 | AB69: 75.67971 | AC69: 77.235405 | AD69: 78.876617 | AE69: 80.464165 | AF69: 81.986366 | AG69: 83.654358 | AH69: 85.341866 | AI69: 87.067459 | AJ69: 0.023
A70: Canada | B70: Air Travel: Travel Demand: Revenue Ton Miles: Freight: Canada: High oil and gas supply | C70: 57-AEO2021.77.highogs-d120120a | D70: billion miles | E70: 2.164612 | F70: 2.281979 | G70: 2.337295 | H70: 2.383461 | I70: 2.415567 | J70: 2.449279 | K70: 2.48485 | L70: 2.520722 | M70: 2.556529 | N70: 2.592648 | O70: 2.62876 | P70: 2.665842 | Q70: 2.704094 | R70: 2.743615 | S70: 2.783667 | T70: 2.823704 | U70: 2.865712 | V70: 2.907897 | W70: 2.950283 | X70: 2.993284 | Y70: 3.036555 | Z70: 3.07853 | AA70: 3.120687 | AB70: 3.162902 | AC70: 3.205233 | AD70: 3.247794 | AE70: 3.29063 | AF70: 3.333485 | AG70: 3.375829 | AH70: 3.417473 | AI70: 3.458941 | AJ70: 0.016
A71: Central America | B71: Air Travel: Travel Demand: Revenue Ton Miles: Freight: Central America: High oil and gas supply | C71: 57-AEO2021.78.highogs-d120120a | D71: billion miles | E71: 0.680138 | F71: 0.736806 | G71: 0.770957 | H71: 0.800632 | I71: 0.828619 | J71: 0.857051 | K71: 0.886102 | L71: 0.915699 | M71: 0.945831 | N71: 0.976467 | O71: 1.007465 | P71: 1.038599 | Q71: 1.070029 | R71: 1.101981 | S71: 1.1345 | T71: 1.167677 | U71: 1.201186 | V71: 1.235285 | W71: 1.270031 | X71: 1.305448 | Y71: 1.341549 | Z71: 1.378261 | AA71: 1.415614 | AB71: 1.453655 | AC71: 1.492391 | AD71: 1.531825 | AE71: 1.571064 | AF71: 1.610966 | AG71: 1.65153 | AH71: 1.692764 | AI71: 1.73466 | AJ71: 0.032
A72: South America | B72: Air Travel: Travel Demand: Revenue Ton Miles: Freight: South America: High oil and gas supply | C72: 57-AEO2021.79.highogs-d120120a | D72: billion miles | E72: 3.443945 | F72: 3.671853 | G72: 3.850933 | H72: 4.018598 | I72: 4.165071 | J72: 4.307099 | K72: 4.447438 | L72: 4.580935 | M72: 4.709958 | N72: 4.833791 | O72: 4.951213 | P72: 5.064372 | Q72: 5.176888 | R72: 5.289841 | S72: 5.403333 | T72: 5.517631 | U72: 5.630352 | V72: 5.743828 | W72: 5.857991 | X72: 5.972835 | Y72: 6.088274 | Z72: 6.199485 | AA72: 6.311456 | AB72: 6.424189 | AC72: 6.537744 | AD72: 6.652106 | AE72: 6.762324 | AF72: 6.873188 | AG72: 6.984646 | AH72: 7.096625 | AI72: 7.209146 | AJ72: 0.025
A73: Europe | B73: Air Travel: Travel Demand: Revenue Ton Miles: Freight: Europe: High oil and gas supply | C73: 57-AEO2021.80.highogs-d120120a | D73: billion miles | E73: 30.556461 | F73: 32.565449 | G73: 34.04142 | H73: 35.044312 | I73: 35.827061 | J73: 36.498543 | K73: 37.100815 | L73: 37.682922 | M73: 38.254745 | N73: 38.807972 | O73: 39.341606 | P73: 39.867779 | Q73: 40.378994 | R73: 40.886597 | S73: 41.399906 | T73: 41.915913 | U73: 42.434448 | V73: 42.959206 | W73: 43.489521 | X73: 44.025993 | Y73: 44.570202 | Z73: 45.119671 | AA73: 45.672829 | AB73: 46.228092 | AC73: 46.783607 | AD73: 47.341537 | AE73: 47.901539 | AF73: 48.463985 | AG73: 49.033245 | AH73: 49.61174 | AI73: 50.198711 | AJ73: 0.017
A74: Africa | B74: Air Travel: Travel Demand: Revenue Ton Miles: Freight: Africa: High oil and gas supply | C74: 57-AEO2021.81.highogs-d120120a | D74: billion miles | E74: 2.718639 | F74: 2.851637 | G74: 2.970391 | H74: 3.082338 | I74: 3.198966 | J74: 3.314263 | K74: 3.428552 | L74: 3.544565 | M74: 3.662143 | N74: 3.781496 | O74: 3.902905 | P74: 4.025911 | Q74: 4.151836 | R74: 4.281348 | S74: 4.414794 | T74: 4.552517 | U74: 4.69418 | V74: 4.840026 | W74: 4.990097 | X74: 5.144794 | Y74: 5.304032 | Z74: 5.466792 | AA74: 5.634241 | AB74: 5.806863 | AC74: 5.984863 | AD74: 6.168319 | AE74: 6.35591 | AF74: 6.54939 | AG74: 6.749088 | AH74: 6.955466 | AI74: 7.168818 | AJ74: 0.033
A75: Mideast | B75: Air Travel: Travel Demand: Revenue Ton Miles: Freight: Mideast: High oil and gas supply | C75: 57-AEO2021.82.highogs-d120120a | D75: billion miles | E75: 21.300634 | F75: 21.79257 | G75: 22.839779 | H75: 23.771973 | I75: 24.548313 | J75: 25.272507 | K75: 26.002253 | L75: 26.742912 | M75: 27.505835 | N75: 28.276066 | O75: 29.056536 | P75: 29.854353 | Q75: 30.666574 | R75: 31.501448 | S75: 32.357819 | T75: 33.236824 | U75: 34.123375 | V75: 35.025249 | W75: 35.947193 | X75: 36.888668 | Y75: 37.846371 | Z75: 38.809383 | AA75: 39.787594 | AB75: 40.782192 | AC75: 41.793034 | AD75: 42.821609 | AE75: 43.866886 | AF75: 44.932095 | AG75: 46.017059 | AH75: 47.121964 | AI75: 48.25079 | AJ75: 0.028
A76: Commonwealth of Independent States | B76: Air Travel: Travel Demand: Revenue Ton Miles: Freight: CIS: High oil and gas supply | C76: 57-AEO2021.83.highogs-d120120a | D76: billion miles | E76: 7.542699 | F76: 7.877234 | G76: 8.302364 | H76: 8.646373 | I76: 9.003555 | J76: 9.332201 | K76: 9.616932 | L76: 9.909141 | M76: 10.218139 | N76: 10.544869 | O76: 10.888 | P76: 11.257322 | Q76: 11.649852 | R76: 12.056036 | S76: 12.466384 | T76: 12.872409 | U76: 13.254387 | V76: 13.635102 | W76: 14.016713 | X76: 14.403337 | Y76: 14.7971 | Z76: 15.17918 | AA76: 15.565066 | AB76: 15.955992 | AC76: 16.352449 | AD76: 16.754496 | AE76: 17.143694 | AF76: 17.534578 | AG76: 17.931538 | AH76: 18.338486 | AI76: 18.7582 | AJ76: 0.031
A77: China | B77: Air Travel: Travel Demand: Revenue Ton Miles: Freight: China: High oil and gas supply | C77: 57-AEO2021.84.highogs-d120120a | D77: billion miles | E77: 24.198942 | F77: 26.141851 | G77: 27.475876 | H77: 28.782633 | I77: 30.11961 | J77: 31.466648 | K77: 32.750057 | L77: 33.997581 | M77: 35.226109 | N77: 36.427605 | O77: 37.600807 | P77: 38.758659 | Q77: 39.883366 | R77: 40.97818 | S77: 42.044289 | T77: 43.09053 | U77: 44.115196 | V77: 45.109791 | W77: 46.07621 | X77: 47.025524 | Y77: 47.96965 | Z77: 48.916031 | AA77: 49.863655 | AB77: 50.803391 | AC77: 51.724632 | AD77: 52.615891 | AE77: 53.47522 | AF77: 54.310696 | AG77: 55.119438 | AH77: 55.892765 | AI77: 56.622608 | AJ77: 0.029
A78: Northeast Asia | B78: Air Travel: Travel Demand: Revenue Ton Miles: Freight: NE Asia: High oil and gas supply | C78: 57-AEO2021.85.highogs-d120120a | D78: billion miles | E78: 19.38155 | F78: 20.598074 | G78: 22.126936 | H78: 23.279057 | I78: 24.201975 | J78: 24.953934 | K78: 25.605349 | L78: 26.183161 | M78: 26.693991 | N78: 27.136654 | O78: 27.513117 | P78: 27.797167 | Q78: 27.992924 | R78: 28.171379 | S78: 28.345251 | T78: 28.512152 | U78: 28.675215 | V78: 28.822847 | W78: 28.955744 | X78: 29.085375 | Y78: 29.219444 | Z78: 29.365313 | AA78: 29.519981 | AB78: 29.676079 | AC78: 29.833902 | AD78: 29.994741 | AE78: 30.157551 | AF78: 30.322783 | AG78: 30.496027 | AH78: 30.682388 | AI78: 30.885082 | AJ78: 0.016
A79: Southeast Asia | B79: Air Travel: Travel Demand: Revenue Ton Miles: Freight: SE Asia: High oil and gas supply | C79: 57-AEO2021.86.highogs-d120120a | D79: billion miles | E79: 10.717637 | F79: 11.242664 | G79: 11.801711 | H79: 12.304582 | I79: 12.796515 | J79: 13.283494 | K79: 13.768234 | L79: 14.251025 | M79: 14.731154 | N79: 15.207453 | O79: 15.67858 | P79: 16.148643 | Q79: 16.619749 | R79: 17.092098 | S79: 17.56719 | T79: 18.045431 | U79: 18.521793 | V79: 19.001442 | W79: 19.48476 | X79: 19.971697 | Y79: 20.46335 | Z79: 20.956322 | AA79: 21.452829 | AB79: 21.951828 | AC79: 22.454243 | AD79: 22.959194 | AE79: 23.4554 | AF79: 23.952169 | AG79: 24.451094 | AH79: 24.953636 | AI79: 25.461512 | AJ79: 0.029
A80: Southwest Asia | B80: Air Travel: Travel Demand: Revenue Ton Miles: Freight: SW Asia: High oil and gas supply | C80: 57-AEO2021.87.highogs-d120120a | D80: billion miles | E80: 2.834066 | F80: 3.046368 | G80: 3.212164 | H80: 3.410831 | I80: 3.61828 | J80: 3.831448 | K80: 4.048899 | L80: 4.273014 | M80: 4.503598 | N80: 4.73813 | O80: 4.973223 | P80: 5.206446 | Q80: 5.436059 | R80: 5.660756 | S80: 5.880398 | T80: 6.100022 | U80: 6.321425 | V80: 6.546057 | W80: 6.774097 | X80: 7.005462 | Y80: 7.240137 | Z80: 7.476269 | AA80: 7.71507 | AB80: 7.956885 | AC80: 8.201584 | AD80: 8.449116 | AE80: 8.69773 | AF80: 8.948387 | AG80: 9.201494 | AH80: 9.456876 | AI80: 9.714658 | AJ80: 0.042
... A82: Total World | B82: Air Travel: Travel Demand: Revenue Ton Miles: Freight: World: High oil and gas supply | C82: 57-AEO2021.89.highogs-d120120a | D82: billion miles | E82: 172.60286 | F82: 181.47017 | G82: 190.67506 | H82: 198.51294 | I82: 205.53584 | J82: 212.08423 | K82: 218.10426 | L82: 223.81117 | M82: 229.39374 | N82: 234.85721 | O82: 240.25493 | P82: 245.66066 | Q82: 251.12701 | R82: 256.60428 | S82: 262.18304 | T82: 267.85465 | U82: 273.42017 | V82: 278.90433 | W82: 284.41476 | X82: 290.05658 | Y82: 295.86688 | Z82: 301.69519 | AA82: 307.58176 | AB82: 313.50397 | AC82: 319.43451 | AD82: 325.46594 | AE82: 331.41577 | AF82: 337.31686 | AG82: 343.39352 | AH82: 349.52408 | AI82: 355.73096 | AJ82: 0.024
A83: Seat Miles Demanded (billion miles) | C83: 57-AEO2021.91.
A84: United States | B84: Air Travel: Seat Miles Demanded: U.S.: High oil and gas supply | C84: 57-AEO2021.92.highogs-d120120a | D84: billion miles | E84: 738.85895 | F84: 1081.6603 | G84: 1215.7373 | H84: 1284.3009 | I84: 1340.2419 | J84: 1397.254 | K84: 1430.9814 | L84: 1455.4497 | M84: 1476.5328 | N84: 1495.9988 | O84: 1516.3666 | P84: 1539.9563 | Q84: 1569.8956 | R84: 1600.4498 | S84: 1634.8596 | T84: 1672.6685 | U84: 1707.1351 | V84: 1738.4458 | W84: 1770.8867 | X84: 1807.5973 | Y84: 1848.892 | Z84: 1889.7706 | AA84: 1930.5969 | AB84: 1971.072 | AC84: 2010.4889 | AD84: 2052.9485 | AE84: 2092.6599 | AF84: 2129.1379 | AG84: 2171.0725 | AH84: 2213.2192 | AI84: 2256.3169 | AJ84: 0.038
A85: Narrow Body Aircraft | B85: Air Travel: Seat Miles Demanded: U.S.: Narrow Body Aircraft: High oil and gas supply | C85: 57-AEO2021.93.highogs-d120120a | D85: billion miles | E85: 562.94067 | F85: 755.66083 | G85: 824.98547 | H85: 859.5769 | I85: 887.13696 | J85: 925.1814 | K85: 951.38074 | L85: 971.20312 | M85: 988.65778 | N85: 1004.9517 | O85: 1021.8361 | P85: 1040.946 | Q85: 1064.5021 | R85: 1088.4945 | S85: 1115.2185 | T85: 1144.3712 | U85: 1171.1705 | V85: 1195.7264 | W85: 1221.0873 | X85: 1249.5074 | Y85: 1281.2241 | Z85: 1312.6592 | AA85: 1344.0698 | AB85: 1375.2372 | AC85: 1405.6436 | AD85: 1438.2614 | AE85: 1468.8855 | AF85: 1497.1487 | AG85: 1529.3839 | AH85: 1561.7722 | AI85: 1594.8539 | AJ85: 0.035
A86: Wide Body Aircraft | B86: Air Travel: Seat Miles Demanded: U.S.: Wide Body Aircraft: High oil and gas supply | C86: 57-AEO2021.94.highogs-d120120a | D86: billion miles | E86: 99.122467 | F86: 231.48749 | G86: 293.59433 | H86: 328.61057 | I86: 358.73859 | J86: 377.81155 | K86: 386.5163 | L86: 392.95956 | M86: 398.56216 | N86: 403.75223 | O86: 409.13821 | P86: 415.27875 | Q86: 422.92777 | R86: 430.7041 | S86: 439.38757 | T86: 448.86603 | U86: 457.52246 | V86: 465.40564 | W86: 473.54428 | X86: 482.68854 | Y86: 492.92075 | Z86: 503.04129 | AA86: 513.13824 | AB86: 523.14185 | AC86: 532.88605 | AD86: 543.34479 | AE86: 553.14648 | AF86: 562.17987 | AG86: 572.50073 | AH86: 582.86914 | AI86: 593.46039 | AJ86: 0.061
A87: Regional Jets | B87: Air Travel: Seat Miles Demanded: U.S.: Regional Jets: High oil and gas supply | C87: 57-AEO2021.95.highogs-d120120a | D87: billion miles | E87: 76.795761 | F87: 94.511925 | G87: 97.157516 | H87: 96.113319 | I87: 94.366493 | J87: 94.260971 | K87: 93.084595 | L87: 91.286995 | M87: 89.313004 | N87: 87.294876 | O87: 85.392189 | P87: 83.731415 | Q87: 82.465698 | R87: 81.251183 | S87: 80.253563 | T87: 79.43119 | U87: 78.442268 | V87: 77.313545 | W87: 76.25531 | X87: 75.401237 | Y87: 74.74707 | Z87: 74.070175 | AA87: 73.38871 | AB87: 72.693031 | AC87: 71.959335 | AD87: 71.34227 | AE87: 70.627945 | AF87: 69.809517 | AG87: 69.187897 | AH87: 68.577698 | AI87: 68.00264 | AJ87: -0.004
A88: Canada | B88: Air Travel: Seat Miles Demanded: Canada: High oil and gas supply | C88: 57-AEO2021.96.highogs-d120120a | D88: billion miles | E88: 53.555019 | F88: 101.23574 | G88: 122.83223 | H88: 134.92769 | I88: 144.75522 | J88: 151.90727 | K88: 156.095 | L88: 160.37956 | M88: 164.7484 | N88: 169.21594 | O88: 173.77072 | P88: 178.45181 | Q88: 183.26894 | R88: 188.22867 | S88: 193.30354 | T88: 198.47319 | U88: 203.82153 | V88: 209.27768 | W88: 214.84424 | X88: 220.54163 | Y88: 226.35352 | Z88: 232.21521 | AA88: 238.1927 | AB88: 244.28195 | AC88: 250.49162 | AD88: 256.83112 | AE88: 263.30536 | AF88: 269.9061 | AG88: 276.61163 | AH88: 283.4162 | AI88: 290.34723 | AJ88: 0.058
A89: Central America | B89: Air Travel: Seat Miles Demanded: Central America: High oil and gas supply | C89: 57-AEO2021.97.highogs-d120120a | D89: billion miles | E89: 58.478851 | F89: 115.64821 | G89: 141.88585 | H89: 156.68651 | I89: 169.00517 | J89: 177.72389 | K89: 184.24703 | L89: 190.99525 | M89: 197.97511 | N89: 205.19016 | O89: 212.634 | P89: 220.24878 | Q89: 228.09546 | R89: 236.20058 | S89: 244.57362 | T89: 253.22891 | U89: 262.09787 | V89: 271.25613 | W89: 280.71747 | X89: 290.49289 | Y89: 300.58841 | Z89: 310.94919 | AA89: 321.64206 | AB89: 332.68063 | AC89: 344.0759 | AD89: 355.83639 | AE89: 367.79312 | AF89: 380.1174 | AG89: 392.83237 | AH89: 405.9646 | AI89: 419.53629 | AJ89: 0.068
A90: South America | B90: Air Travel: Seat Miles Demanded: South America: High oil and gas supply | C90: 57-AEO2021.98.highogs-d120120a | D90: billion miles | E90: 119.22159 | F90: 180.1963 | G90: 204.77573 | H90: 217.60568 | I90: 232.0417 | J90: 246.76863 | K90: 260.95978 | L90: 275.59531 | M90: 290.77594 | N90: 306.48709 | O90: 322.68716 | P90: 339.45734 | Q90: 356.99619 | R90: 375.38892 | S90: 394.68012 | T90: 414.92593 | U90: 436.01178 | V90: 458.13092 | W90: 481.32828 | X90: 505.65424 | Y90: 531.1391 | Z90: 557.48969 | AA90: 585.10168 | AB90: 614.0354 | AC90: 644.3587 | AD90: 676.13525 | AE90: 708.98852 | AF90: 743.38202 | AG90: 779.39197 | AH90: 817.09735 | AI90: 856.58691 | AJ90: 0.068
A91: Europe | B91: Air Travel: Seat Miles Demanded: Europe: High oil and gas supply | C91: 57-AEO2021.99.highogs-d120120a | D91: billion miles | E91: 687.18518 | F91: 1076.8466 | G91: 1238.396 | H91: 1324.2706 | I91: 1398.6709 | J91: 1465.8832 | K91: 1519.1071 | L91: 1573.2361 | M91: 1628.6669 | N91: 1685.0665 | O91: 1742.3853 | P91: 1801.1421 | Q91: 1861.0247 | R91: 1922.5511 | S91: 1986.1877 | T91: 2051.8611 | U91: 2119.6223 | V91: 2189.7104 | W91: 2262.1658 | X91: 2337.094 | Y91: 2414.5933 | Z91: 2494.6533 | AA91: 2577.269 | AB91: 2662.4316 | AC91: 2750.1116 | AD91: 2840.5046 | AE91: 2933.6748 | AF91: 3029.7266 | AG91: 3129.0105 | AH91: 3231.7812 | AI91: 3338.1042 | AJ91: 0.054
A92: Africa | B92: Air Travel: Seat Miles Demanded: Africa: High oil and gas supply | C92: 57-AEO2021.100.highogs-d120120a | D92: billion miles | E92: 57.876575 | F92: 116.43413 | G92: 141.83621 | H92: 155.7079 | I92: 168.35617 | J92: 178.61581 | K92: 188.30887 | L92: 198.4341 | M92: 208.9975 | N92: 220.02802 | O92: 231.56171 | P92: 243.57718 | Q92: 256.19397 | R92: 269.48599 | S92: 283.50809 | T92: 298.31811 | U92: 313.9165 | V92: 330.36441 | W92: 347.70163 | X92: 366.00061 | Y92: 385.28778 | Z92: 405.51227 | AA92: 426.82489 | AB92: 449.3175 | AC92: 473.06168 | AD92: 498.12006 | AE92: 524.41242 | AF92: 552.17432 | AG92: 581.50519 | AH92: 612.52484 | AI92: 645.3418 | AJ92: 0.084
A93: Mideast | B93: Air Travel: Seat Miles Demanded: Mideast: High oil and gas supply | C93: 57-AEO2021.101.highogs-d120120a | D93: billion miles | E93: 188.03294 | F93: 323.76691 | G93: 385.31198 | H93: 420.45505 | I93: 452.54855 | J93: 475.72693 | K93: 498.76129 | L93: 522.74548 | M93: 547.80219 | N93: 573.90454 | O93: 601.11536 | P93: 629.11243 | Q93: 658.30585 | R93: 688.77179 | S93: 720.55676 | T93: 753.71277 | U93: 788.12256 | V93: 823.96155 | W93: 861.30835 | X93: 900.21851 | Y93: 940.7218 | Z93: 982.56714 | AA93: 1026.1021 | AB93: 1071.3953 | AC93: 1118.5142 | AD93: 1167.5333 | AE93: 1218.0035 | AF93: 1270.4926 | AG93: 1325.0739 | AH93: 1381.8195 | AI93: 1440.8356 | AJ93: 0.07
A94: Commonwealth of Independent States | B94: Air Travel: Seat Miles Demanded: CIS: High oil and gas supply | C94: 57-AEO2021.102.highogs-d120120a | D94: billion miles | E94: 140.6824 | F94: 185.27963 | G94: 203.79672 | H94: 213.67226 | I94: 221.72766 | J94: 230.02451 | K94: 236.05182 | L94: 242.25279 | M94: 248.71696 | N94: 255.46008 | O94: 262.47818 | P94: 269.8313 | Q94: 277.51712 | R94: 285.46219 | S94: 293.59375 | T94: 301.8479 | U94: 310.05011 | V94: 318.40402 | W94: 326.93613 | X94: 335.69125 | Y94: 344.68771 | Z94: 353.72818 | AA94: 362.99258 | AB94: 372.49612 | AC94: 382.24756 | AD94: 392.25263 | AE94: 402.25812 | AF94: 412.49091 | AG94: 422.99332 | AH94: 433.80521 | AI94: 444.9549 | AJ94: 0.039
A95: China | B95: Air Travel: Seat Miles Demanded: China: High oil and gas supply | C95: 57-AEO2021.103.highogs-d120120a | D95: billion miles | E95: 618.97699 | F95: 773.94257 | G95: 834.68506 | H95: 865.90063 | I95: 915.13147 | J95: 972.84937 | K95: 1029.2371 | L95: 1086.4056 | M95: 1144.9772 | N95: 1204.5637 | O95: 1265.0427 | P95: 1326.9542 | Q95: 1389.4308 | R95: 1452.5459 | S95: 1516.2791 | T95: 1581.0144 | U95: 1646.6306 | V95: 1712.6246 | W95: 1779.0205 | X95: 1846.3771 | Y95: 1915.2947 | Z95: 1986.276 | AA95: 2059.3171 | AB95: 2133.8938 | AC95: 2209.3337 | AD95: 2284.8486 | AE95: 2360.2358 | AF95: 2435.9556 | AG95: 2511.7476 | AH95: 2586.918 | AI95: 2660.7725 | AJ95: 0.05
... A100: Total World | B100: Air Travel: Seat Miles Demanded: World: High oil and gas supply | C100: 57-AEO2021.108.highogs-d120120a | D100: billion miles | E100: 3126.5522 | F100: 4820.5991 | G100: 5532.1162 | H100: 5913.2173 | I100: 6273.874 | J100: 6604.2437 | K100: 6878.603 | L100: 7149.3628 | M100: 7423.7388 | N100: 7702.3921 | O100: 7987.1445 | P100: 8281.5059 | Q100: 8587.8398 | R100: 8901.6406 | S100: 9226.9307 | T100: 9564.3506 | U100: 9906.5801 | V100: 10254.654 | W100: 10613.206 | X100: 10986.487 | Y100: 11376.045 | Z100: 11776.154 | AA100: 12188.618 | AB100: 12612.699 | AC100: 13047.407 | AD100: 13496.379 | AE100: 13950.43 | AF100: 14412.766 | AG100: 14892.927 | AH100: 15385.905 | AI100: 15892.688 | AJ100: 0.056
A101: Aircraft Sales | C101: 57-AEO2021.110.
A102: United States | B102: Air Travel: Aircraft Sales: U.S.: High oil and gas supply | C102: 57-AEO2021.111.highogs-d120120a | D102: units | E102: 12.766569 | F102: 0 | G102: 52.252617 | H102: 248.57483 | I102: 330.39148 | J102: 439.40299 | K102: 411.22607 | L102: 354.74939 | M102: 378.83044 | N102: 377.69354 | O102: 381.38245 | P102: 398.93677 | Q102: 431.60233 | R102: 435.10989 | S102: 454.00391 | T102: 505.74081 | U102: 485.64435 | V102: 465.7189 | W102: 467.2446 | X102: 484.81995 | Y102: 504.47668 | Z102: 500.82284 | AA102: 499.29114 | AB102: 497.2919 | AC102: 492.55853 | AD102: 508.42499 | AE102: 497.58765 | AF102: 485.03705 | AG102: 514.04175 | AH102: 519.24786 | AI102: 528.54553 | AJ102: 0.132
A103: Narrow Body Aircraft | B103: Air Travel: Aircraft Sales: U.S.: Narrow Body: High oil and gas supply | C103: 57-AEO2021.112.highogs-d120120a | D103: units | E103: 0 | F103: 0 | G103: 52.252617 | H103: 215.17271 | I103: 271.25543 | J103: 330.52179 | K103: 287.98703 | L103: 269.18115 | M103: 287.40625 | N103: 297.00684 | O103: 296.81982 | P103: 304.1084 | Q103: 321.96484 | R103: 321.38135 | S103: 331.68066 | T103: 341.06982 | U103: 328.57568 | V103: 316.87354 | W103: 319.95312 | X103: 334.36182 | Y103: 350.70898 | Z103: 351.05908 | AA103: 353.11475 | AB103: 354.75 | AC103: 354.50195 | AD103: 368.69385 | AE103: 363.92334 | AF103: 357.78955 | AG103: 381.7749 | AH103: 388.75439 | AI103: 398.66357 | AJ103: - -
A104: Wide Body Aircraft | B104: Air Travel: Aircraft Sales: U.S.: Wide Body: High oil and gas supply | C104: 57-AEO2021.113.highogs-d120120a | D104: units | E104: 12.766569 | F104: 0 | G104: 0 | H104: 33.402122 | I104: 59.136063 | J104: 104.87936 | K104: 92.835693 | L104: 85.568237 | M104: 82.376465 | N104: 80.686699 | O104: 80.313972 | P104: 81.061317 | Q104: 83.608932 | R104: 82.27906 | S104: 82.893784 | T104: 83.294044 | U104: 79.429276 | V104: 75.751373 | W104: 75.175995 | X104: 77.0233 | Y104: 79.270615 | Z104: 78.606293 | AA104: 78.231583 | AB104: 78.065331 | AC104: 77.528381 | AD104: 80.187073 | AE104: 79.02478 | AF104: 77.621887 | AG104: 81.843124 | AH104: 82.480042 | AI104: 83.674927 | AJ104: 0.065
A105: Regional Jets | B105: Air Travel: Aircraft Sales: U.S.: Regional Jets: High oil and gas supply | C105: 57-AEO2021.114.highogs-d120120a | D105: units | E105: 0 | F105: 0 | G105: 0 | H105: 0 | I105: 0 | J105: 4.001831 | K105: 30.403351 | L105: 0 | M105: 9.047726 | N105: 0 | O105: 4.248661 | P105: 13.767071 | Q105: 26.028538 | R105: 31.449505 | S105: 39.429432 | T105: 81.376953 | U105: 77.639404 | V105: 73.093994 | W105: 72.115479 | X105: 73.434814 | Y105: 74.49707 | Z105: 71.157471 | AA105: 67.944824 | AB105: 64.476562 | AC105: 60.528198 | AD105: 59.544067 | AE105: 54.639526 | AF105: 49.62561 | AG105: 50.423706 | AH105: 48.013428 | AI105: 46.207031 | AJ105: - -
A106: Canada | B106: Air Travel: Aircraft Sales: Canada: High oil and gas supply | C106: 57-AEO2021.115.highogs-d120120a | D106: units | E106: 0 | F106: 0 | G106: 11.480247 | H106: 23.06884 | I106: 51.716682 | J106: 46.809795 | K106: 46.414143 | L106: 47.910172 | M106: 49.151169 | N106: 50.310692 | O106: 52.48539 | P106: 55.767746 | Q106: 58.284195 | R106: 58.741089 | S106: 58.515366 | T106: 58.297241 | U106: 58.581818 | V106: 58.656479 | W106: 58.849564 | X106: 59.253311 | Y106: 59.697662 | Z106: 59.9655 | AA106: 60.650925 | AB106: 61.431274 | AC106: 62.362167 | AD106: 63.440262 | AE106: 64.637787 | AF106: 65.894577 | AG106: 67.150375 | AH106: 68.47467 | AI106: 70.012039 | AJ106: - -
A107: Narrow Body Aircraft | B107: Air Travel: Aircraft Sales: Canada: Narrow Body: High oil and gas supply | C107: 57-AEO2021.116.highogs-d120120a | D107: units | E107: 0 | F107: 0 | G107: 11.480247 | H107: 18.501953 | I107: 28.589088 | J107: 28.648199 | K107: 26.231873 | L107: 26.711853 | M107: 27.148743 | N107: 27.586273 | O107: 29.185669 | P107: 31.864899 | Q107: 31.920624 | R107: 32.034058 | S107: 32.151306 | T107: 32.279724 | U107: 32.670258 | V107: 32.964874 | W107: 33.331512 | X107: 33.82019 | Y107: 34.338623 | Z107: 34.777588 | AA107: 35.450134 | AB107: 36.188477 | AC107: 37.024292 | AD107: 37.955139 | AE107: 38.962952 | AF107: 40.013916 | AG107: 41.072693 | AH107: 42.169922 | AI107: 43.382263 | AJ107: - -
A108: Wide Body Aircraft | B108: Air Travel: Aircraft Sales: Canada: Wide Body: High oil and gas supply | C108: 57-AEO2021.117.highogs-d120120a | D108: units | E108: 0 | F108: 0 | G108: 0 | H108: 4.566887 | I108: 12.589356 | J108: 9.012822 | K108: 6.256765 | L108: 6.932693 | M108: 7.546217 | N108: 8.105157 | O108: 8.577063 | P108: 9.062393 | Q108: 11.429062 | R108: 11.703583 | S108: 11.357071 | T108: 11.05661 | U108: 10.912781 | V108: 10.758347 | W108: 10.664505 | X108: 10.645889 | Y108: 10.667847 | Z108: 10.660721 | AA108: 10.758011 | AB108: 10.88031 | AC108: 11.033249 | AD108: 11.21376 | AE108: 11.414612 | AF108: 11.621231 | AG108: 11.819351 | AH108: 12.029266 | AI108: 12.284683 | AJ108: - -
A109: Regional Jets | B109: Air Travel: Aircraft Sales: Canada: Regional Jets: High oil and gas supply | C109: 57-AEO2021.118.highogs-d120120a | D109: units | E109: 0 | F109: 0 | G109: 0 | H109: 0 | I109: 10.538239 | J109: 9.148773 | K109: 13.925507 | L109: 14.265625 | M109: 14.456207 | N109: 14.619263 | O109: 14.722656 | P109: 14.840454 | Q109: 14.934509 | R109: 15.003448 | S109: 15.006989 | T109: 14.960907 | U109: 14.998779 | V109: 14.933258 | W109: 14.853546 | X109: 14.787231 | Y109: 14.691193 | Z109: 14.527191 | AA109: 14.44278 | AB109: 14.362488 | AC109: 14.304626 | AD109: 14.271362 | AE109: 14.260223 | AF109: 14.25943 | AG109: 14.258331 | AH109: 14.275482 | AI109: 14.345093 | AJ109: - -
A110: Central America | B110: Air Travel: Aircraft Sales: Central America: High oil and gas supply | C110: 57-AEO2021.119.highogs-d120120a | D110: units | E110: 0 | F110: 0 | G110: 0 | H110: 14.142521 | I110: 35.199738 | J110: 33.541885 | K110: 29.704161 | L110: 37.478279 | M110: 40.383106 | N110: 43.874802 | O110: 47.267197 | P110: 49.578644 | Q110: 52.026058 | R110: 56.1483 | S110: 61.598576 | T110: 62.922504 | U110: 63.972118 | V110: 65.340553 | W110: 66.743408 | X110: 68.186028 | Y110: 69.637909 | Z110: 70.906448 | AA110: 72.419769 | AB110: 73.997643 | AC110: 75.639694 | AD110: 77.356674 | AE110: 78.551102 | AF110: 80.447159 | AG110: 82.517265 | AH110: 84.766594 | AI110: 87.225166 | AJ110: - -
A111: Narrow Body Aircraft | B111: Air Travel: Aircraft Sales: Central America: Narrow Body: High oil and gas supply | C111: 57-AEO2021.120.highogs-d120120a | D111: units | E111: 0 | F111: 0 | G111: 0 | H111: 13.620169 | I111: 28.143759 | J111: 27.264645 | K111: 25.290241 | L111: 27.489864 | M111: 29.75588 | N111: 32.031395 | O111: 34.265774 | P111: 36.307617 | Q111: 38.427319 | R111: 42.206665 | S111: 47.322815 | T111: 48.313538 | U111: 49.131348 | V111: 50.185547 | W111: 51.317261 | X111: 52.50708 | Y111: 53.729553 | Z111: 54.841431 | AA111: 56.153687 | AB111: 57.533997 | AC111: 58.981628 | AD111: 60.504883 | AE111: 61.633728 | AF111: 63.298462 | AG111: 65.119141 | AH111: 67.116272 | AI111: 69.284851 | AJ111: - -
A112: Wide Body Aircraft | B112: Air Travel: Aircraft Sales: Central America: Wide Body: High oil and gas supply | C112: 57-AEO2021.121.highogs-d120120a | D112: units | E112: 0 | F112: 0 | G112: 0 | H112: 0.522352 | I112: 2.82039 | J112: 2.39497 | K112: 1.310349 | L112: 1.610806 | M112: 1.823103 | N112: 2.719047 | O112: 3.587437 | P112: 3.645798 | Q112: 3.725327 | R112: 3.819534 | S112: 3.921635 | T112: 4.035694 | U112: 4.129955 | V112: 4.267509 | W112: 4.373707 | X112: 4.47567 | Y112: 4.575134 | Z112: 4.658844 | AA112: 4.751987 | AB112: 4.844322 | AC112: 4.934311 | AD112: 5.022783 | AE112: 5.093291 | AF112: 5.215441 | AG112: 5.332146 | AH112: 5.425579 | AI112: 5.53106 | AJ112: - -
A113: Regional Jets | B113: Air Travel: Aircraft Sales: Central America: Regional Jets: High oil and gas supply | C113: 57-AEO2021.122.highogs-d120120a | D113: units | E113: 0 | F113: 0 | G113: 0 | H113: 0 | I113: 4.235589 | J113: 3.882273 | K113: 3.103571 | L113: 8.377609 | M113: 8.804123 | N113: 9.124359 | O113: 9.413986 | P113: 9.625229 | Q113: 9.873413 | R113: 10.122101 | S113: 10.354126 | T113: 10.573273 | U113: 10.710815 | V113: 10.887497 | W113: 11.052444 | X113: 11.203278 | Y113: 11.333221 | Z113: 11.406174 | AA113: 11.514099 | AB113: 11.619324 | AC113: 11.723755 | AD113: 11.82901 | AE113: 11.824081 | AF113: 11.933258 | AG113: 12.065979 | AH113: 12.224747 | AI113: 12.409256 | AJ113: - -
...

Sheet AEO 2021 Table 49
A1: Freight Truck Stock Vehicle Miles Traveled (Case High oil and gas supply)
A2: https://www.eia.gov/outlooks/aeo/data/browser/#/?id=58-AEO2021&region=0-0&cases=highogs&start=2019&end=2050&f=A&linechart=highogs-d120120a.6-58-AEO2021~highogs-d120120a.7-58-AEO2021~highogs-d120120a.8-58-AEO2021~highogs-d120120a.9-58-AEO2021~highogs-d120120a.10-58-AEO2021~highogs-d120120a.11-58-AEO2021~highogs-d120120a.12-58-AEO2021~highogs-d120120a.13-58-AEO2021~highogs-d120120a.14-58-AEO2021~highogs-d120120a.15-58-AEO2021~highogs-d120120a.17-58-AEO2021~highogs-d120120a.18-58-AEO2021~highogs-d120120a.19-58-AEO2021~highogs-d120120a.20-58-AEO2021~highogs-d120120a.21-58-AEO2021~highogs-d120120a.22-58-AEO2021~highogs-d120120a.23-58-AEO2021~highogs-d120120a.24-58-AEO2021~highogs-d120120a.25-58-AEO2021~highogs-d120120a.26-58-AEO2021~highogs-d120120a.28-58-AEO2021~highogs-d120120a.29-58-AEO2021~highogs-d120120a.30-58-AEO2021~highogs-d120120a.31-58-AEO2021~highogs-d120120a.32-58-AEO2021~highogs-d120120a.33-58-AEO2021~highogs-d120120a.34-58-AEO2021~highogs-d120120a.35-58-AEO2021~highogs-d120120a.36-58-AEO2021~highogs-d120120a.37-58-AEO2021&sourcekey=0
A3: 07:53:28 GMT-0700 (Pacific Daylight Time)
A4: Source: U.S. Energy Information Administration
A5: Year | B5: 2050 | C5: 2049 | D5: 2048 | E5: 2047 | F5: 2046 | G5: 2045 | H5: 2044 | I5: 2043 | J5: 2042 | K5: 2041 | L5: 2040 | M5: 2039 | N5: 2038 | O5: 2037 | P5: 2036 | Q5: 2035 | R5: 2034 | S5: 2033 | T5: 2032 | U5: 2031 | V5: 2030 | W5: 2029 | X5: 2028 | Y5: 2027 | Z5: 2026 | AA5: 2025 | AB5: 2024 | AC5: 2023 | AD5: 2022 | AE5: 2021 | AF5: 2020 | AG5: 2019
A6: Light Medium: Diesel billion miles | B6: 70.972908 | C6: 70.541718 | D6: 70.15863 | E6: 69.753059 | F6: 69.495872 | G6: 69.274086 | H6: 68.873764 | I6: 68.498482 | J6: 67.93074 | K6: 67.447044 | L6: 66.942749 | M6: 66.457367 | N6: 65.736893 | O6: 64.989426 | P6: 64.250336 | Q6: 63.344463 | R6: 62.185032 | S6: 61.100975 | T6: 60.050926 | U6: 58.769749 | V6: 57.405666 | W6: 56.083549 | X6: 54.92065 | Y6: 53.847748 | Z6: 53.003296 | AA6: 52.169327 | AB6: 50.975182 | AC6: 49.78685 | AD6: 48.64381 | AE6: 46.46851 | AF6: 44.303616
A7: Light Medium: Motor Gasoline billion miles | B7: 23.896128 | C7: 23.335905 | D7: 22.800196 | E7: 22.258034 | F7: 21.763906 | G7: 21.284573 | H7: 20.762129 | I7: 20.256687 | J7: 19.709454 | K7: 19.203287 | L7: 18.703653 | M7: 18.240948 | N7: 17.729656 | O7: 17.217386 | P7: 16.727058 | Q7: 16.229515 | R7: 15.705617 | S7: 15.217308 | T7: 14.758368 | U7: 14.298347 | V7: 13.869823 | W7: 13.47327 | X7: 13.156378 | Y7: 12.904199 | Z7: 12.742443 | AA7: 12.633912 | AB7: 12.497584 | AC7: 12.398815 | AD7: 12.329393 | AE7: 12.01163 | AF7: 11.670487
A8: Light Medium: Propane billion miles | B8: 0.237484 | C8: 0.226093 | D8: 0.215387 | E8: 0.205157 | F8: 0.195868 | G8: 0.187076 | H8: 0.178193 | I8: 0.16979 | J8: 0.161202 | K8: 0.153057 | L8: 0.145181 | M8: 0.137584 | N8: 0.129664 | O8: 0.122013 | P8: 0.114736 | Q8: 0.107483 | R8: 0.10013 | S8: 0.093168 | T8: 0.086453 | U8: 0.079679 | V8: 0.073035 | W8: 0.06658 | X8: 0.060354 | Y8: 0.054351 | Z8: 0.048635 | AA8: 0.042852 | AB8: 0.03672 | AC8: 0.030636 | AD8: 0.024646 | AE8: 0.018281 | AF8: 0.012334
A9: Light Medium: Natural Gas billion miles | B9: 0.063147 | C9: 0.061027 | D9: 0.059118 | E9: 0.057357 | F9: 0.05586 | G9: 0.054511 | H9: 0.053101 | I9: 0.051773 | J9: 0.05033 | K9: 0.048953 | L9: 0.047577 | M9: 0.046205 | N9: 0.044604 | O9: 0.042967 | P9: 0.041355 | Q9: 0.039642 | R9: 0.037783 | S9: 0.035962 | T9: 0.034136 | U9: 0.032181 | V9: 0.03017 | W9: 0.028134 | X9: 0.0261 | Y9: 0.024058 | Z9: 0.022038 | AA9: 0.019891 | AB9: 0.017472 | AC9: 0.014945 | AD9: 0.012327 | AE9: 0.009375 | AF9: 0.00651
A10: Light Medium: Ethanol-Flex Fuel billion miles | B10: 22.046141 | C10: 20.989632 | D10: 19.985868 | E10: 19.022991 | F10: 18.134251 | G10: 17.294907 | H10: 16.454727 | I10: 15.670287 | J10: 14.881503 | K10: 14.153807 | L10: 13.488983 | M10: 12.885431 | N10: 12.272737 | O10: 11.685357 | P10: 11.123409 | Q10: 10.569487 | R10: 10.000749 | S10: 9.462119 | T10: 8.942436 | U10: 8.423628 | V10: 7.9248 | W10: 7.451281 | X10: 7.010355 | Y10: 6.612732 | Z10: 6.262032 | AA10: 5.943142 | AB10: 5.608263 | AC10: 5.281196 | AD10: 4.963326 | AE10: 4.540388 | AF10: 4.117043
A11: Light Medium: Electric billion miles | B11: 0.2443 | C11: 0.232416 | D11: 0.221283 | E11: 0.210581 | F11: 0.200721 | G11: 0.191288 | H11: 0.181706 | I11: 0.172473 | J11: 0.162937 | K11: 0.153739 | L11: 0.144896 | M11: 0.136441 | N11: 0.127863 | O11: 0.119563 | P11: 0.111743 | Q11: 0.104059 | R11: 0.096355 | S11: 0.089079 | T11: 0.082057 | U11: 0.074933 | V11: 0.067904 | W11: 0.061033 | X11: 0.054347 | Y11: 0.047812 | Z11: 0.041526 | AA11: 0.035238 | AB11: 0.02875 | AC11: 0.022448 | AD11: 0.01645 | AE11: 0.010535 | AF11: 0.00537
A12: Light Medium: Plug-in Diesel Hybrid billion miles | B12: 0.263491 | C12: 0.250669 | D12: 0.238653 | E12: 0.227098 | F12: 0.216448 | G12: 0.206252 | H12: 0.195889 | I12: 0.185904 | J12: 0.175606 | K12: 0.165678 | L12: 0.156132 | M12: 0.146996 | N12: 0.137715 | O12: 0.128729 | P12: 0.12025 | Q12: 0.111907 | R12: 0.103528 | S12: 0.095593 | T12: 0.087937 | U12: 0.080206 | V12: 0.072574 | W12: 0.065108 | X12: 0.057853 | Y12: 0.050772 | Z12: 0.043949 | AA12: 0.037112 | AB12: 0.030054 | AC12: 0.023188 | AD12: 0.016645 | AE12: 0.01022 | AF12: 0.004667
A13: Light Medium: Plug-in Gasoline Hybrid billion miles | B13: 0.267445 | C13: 0.25443 | D13: 0.242233 | E13: 0.230505 | F13: 0.219695 | G13: 0.209347 | H13: 0.198828 | I13: 0.188694 | J13: 0.178241 | K13: 0.168163 | L13: 0.158475 | M13: 0.149201 | N13: 0.139781 | O13: 0.13066 | P13: 0.122054 | Q13: 0.113586 | R13: 0.105081 | S13: 0.097027 | T13: 0.089257 | U13: 0.081409 | V13: 0.073662 | W13: 0.066085 | X13: 0.058721 | Y13: 0.051534 | Z13: 0.044608 | AA13: 0.037669 | AB13: 0.030505 | AC13: 0.023536 | AD13: 0.016895 | AE13: 0.010373 | AF13: 0.004737
A14: Light Medium: Fuel Cell billion miles | B14: 4.7e-05 | C14: 4.7e-05 | D14: 4.7e-05 | E14: 4.8e-05 | F14: 4.8e-05 | G14: 4.8e-05 | H14: 4.8e-05 | I14: 4.7e-05 | J14: 4.7e-05 | K14: 4.6e-05 | L14: 4.5e-05 | M14: 4.4e-05 | N14: 4.3e-05 | O14: 4.2e-05 | P14: 4e-05 | Q14: 3.9e-05 | R14: 3.7e-05 | S14: 3.5e-05 | T14: 3.4e-05 | U14: 3.1e-05 | V14: 2.9e-05 | W14: 2.7e-05 | X14: 2.4e-05 | Y14: 2.2e-05 | Z14: 1.9e-05 | AA14: 1.7e-05 | AB14: 1.4e-05 | AC14: 1.1e-05 | AD14: 8e-06 | AE14: 5e-06 | AF14: 2e-06
A15: Light Medium billion miles | B15: 117.99106 | C15: 115.89179 | D15: 113.92124 | E15: 111.96469 | F15: 110.28247 | G15: 108.70194 | H15: 106.89825 | I15: 105.19402 | J15: 103.25004 | K15: 101.49389 | L15: 99.787697 | M15: 98.200081 | N15: 96.318832 | O15: 94.436134 | P15: 92.610786 | Q15: 90.620224 | R15: 88.334435 | S15: 86.19136 | T15: 84.131516 | U15: 81.840126 | V15: 79.51767 | W15: 77.295067 | X15: 75.344856 | Y15: 73.593201 | Z15: 72.208496 | AA15: 70.919121 | AB15: 69.224518 | AC15: 67.581619 | AD15: 66.02356 | AE15: 63.079327 | AF15: 60.124729
A16: Medium: Diesel billion miles | B16: 75.230225 | C16: 73.088112 | D16: 71.089844 | E16: 69.220253 | F16: 67.480141 | G16: 65.736038 | H16: 63.896786 | I16: 62.128014 | J16: 60.255966 | K16: 58.566902 | L16: 56.955433 | M16: 55.482285 | N16: 54.011185 | O16: 52.670658 | P16: 51.413059 | Q16: 50.144363 | R16: 48.873032 | S16: 47.786671 | T16: 46.789398 | U16: 45.715141 | V16: 44.713017 | W16: 43.759945 | X16: 42.910355 | Y16: 42.068516 | Z16: 41.264 | AA16: 40.335888 | AB16: 39.124969 | AC16: 37.959641 | AD16: 36.95755 | AE16: 35.473495 | AF16: 34.473965
A17: Medium: Motor Gasoline billion miles | B17: 28.34454 | C17: 27.652967 | D17: 26.998093 | E17: 26.379553 | F17: 25.802208 | G17: 25.222775 | H17: 24.599024 | I17: 23.983839 | J17: 23.321432 | K17: 22.724649 | L17: 22.157524 | M17: 21.643822 | N17: 21.11458 | O17: 20.658173 | P17: 20.229515 | Q17: 19.829401 | R17: 19.403744 | S17: 19.043507 | T17: 18.731878 | U17: 18.393978 | V17: 18.10059 | W17: 17.829197 | X17: 17.610531 | Y17: 17.432796 | Z17: 17.329367 | AA17: 17.240475 | AB17: 17.099653 | AC17: 16.961668 | AD17: 16.901983 | AE17: 16.582535 | AF17: 16.394169
... A35: Heavy billion miles | B35: 213.61003 | C35: 212.18532 | D35: 210.98755 | E35: 209.9261 | F35: 209.0195 | G35: 207.89481 | H35: 206.2525 | I35: 204.62032 | J35: 202.42015 | K35: 200.58725 | L35: 198.97949 | M35: 197.70218 | N35: 196.24423 | O35: 194.91963 | P35: 193.74783 | Q35: 192.42334 | R35: 190.94826 | S35: 190.1557 | T35: 189.81662 | U35: 189.26286 | V35: 188.81807 | W35: 188.40834 | X35: 188.10358 | Y35: 187.33722 | Z35: 186.0614 | AA35: 183.65779 | AB35: 179.66538 | AC35: 175.75407 | AD35: 172.53108 | AE35: 166.90398 | AF35: 162.88361

Sheet AEO 2022 Table 7
B1: ref2022.d011222a | C1: 2021 | D1: 2022 | E1: 2023 | F1: 2024 | G1: 2025 | H1: 2026 | I1: 2027 | J1: 2028 | K1: 2029 | L1: 2030 | M1: 2031 | N1: 2032 | O1: 2033 | P1: 2034 | Q1: 2035 | R1: 2036 | S1: 2037 | T1: 2038 | U1: 2039 | V1: 2040 | W1: 2041 | X1: 2042 | Y1: 2043 | Z1: 2044 | AA1: 2045 | AB1: 2046 | AC1: 2047 | AD1: 2048 | AE1: 2049 | AF1: 2050
C3: Report | D3: Annual Energy Outlook 2022
C4: Scenario | D4: ref2022 | G4: Reference
C5: Datekey | D5: d011222a
C6: Release Date | E6: March 2022
A10: TKI000 | B10: 7. Transportation Sector Key Indicators and Delivered Energy Consumption | AG10: Average
AG11: Annual
AG12: Change
B13: Key Indicators and Consumption | C13: 2021 | D13: 2022 | E13: 2023 | F13: 2024 | G13: 2025 | H13: 2026 | I13: 2027 | J13: 2028 | K13: 2029 | L13: 2030 | M13: 2031 | N13: 2032 | O13: 2033 | P13: 2034 | Q13: 2035 | R13: 2036 | S13: 2037 | T13: 2038 | U13: 2039 | V13: 2040 | W13: 2041 | X13: 2042 | Y13: 2043 | Z13: 2044 | AA13: 2045 | AB13: 2046 | AC13: 2047 | AD13: 2048 | AE13: 2049 | AF13: 2050 | AG13: 2021–2050
B15: Key Indicators
B16: Travel Indicators
B17: (billion vehicle miles traveled)
A18: TKI000:ba_Light-DutyVeh | B18: Light-Duty Vehicles less than 8,501 pounds | C18: 2747.6179 | D18: 2846.677 | E18: 2931.8728 | F18: 2967.9756 | G18: 2996.2344 | H18: 3018.3296 | I18: 3033.9277 | J18: 3047.1858 | K18: 3059.5039 | L18: 3073.7705 | M18: 3089.7642 | N18: 3099.4092 | O18: 3109.8594 | P18: 3116.4043 | Q18: 3120.2698 | R18: 3124.3608 | S18: 3130.0383 | T18: 3137.4807 | U18: 3149.3428 | V18: 3162.8506 | W18: 3176.1882 | X18: 3191.043 | Y18: 3205.97 | Z18: 3221.543 | AA18: 3239.2712 | AB18: 3260.9126 | AC18: 3285.2683 | AD18: 3310.0818 | AE18: 3336.3101 | AF18: 3367.2725 | AG18: 0.007037
A19: TKI000:ba_CommercialLig | B19: Commercial Light Trucks 1/ | C19: 100.61561 | D19: 102.66715 | E19: 104.08694 | F19: 104.46276 | G19: 104.9213 | H19: 105.23949 | I19: 105.44544 | J19: 105.98221 | K19: 106.38637 | L19: 106.87366 | M19: 107.45149 | N19: 108.42069 | O19: 109.31638 | P19: 109.78484 | Q19: 110.32362 | R19: 110.9361 | S19: 111.71995 | T19: 112.58294 | U19: 113.58968 | V19: 114.5583 | W19: 115.50586 | X19: 116.58477 | Y19: 117.72004 | Z19: 118.65319 | AA19: 119.66279 | AB19: 120.99963 | AC19: 122.26018 | AD19: 123.28046 | AE19: 124.462 | AF19: 126.00561 | AG19: 0.007789
A20: TKI000:ba_FreightTrucks | B20: Freight Trucks greater than 10,000 pounds | C20: 296.81833 | D20: 301.98328 | E20: 303.74847 | F20: 304.30881 | G20: 305.88178 | H20: 306.79916 | I20: 307.34378 | J20: 308.85397 | K20: 309.89597 | L20: 311.4162 | M20: 312.75589 | N20: 314.68851 | O20: 316.40372 | P20: 317.39358 | Q20: 318.86368 | R20: 320.39639 | S20: 321.9324 | T20: 323.54294 | U20: 325.45184 | V20: 327.34589 | W20: 329.27771 | X20: 331.6514 | Y20: 334.19193 | Z20: 335.79553 | AA20: 337.64484 | AB20: 340.47848 | AC20: 342.78537 | AD20: 344.07126 | AE20: 345.77982 | AF20: 349.05408 | AG20: 0.005606
B21: (billion passenger miles traveled)
A22: TKI000:buspassmiles | B22: Bus Transportation | C22: 151.12511 | D22: 172.57625 | E22: 183.98444 | F22: 190.58797 | G22: 194.82553 | H22: 197.64862 | I22: 199.61533 | J22: 201.01901 | K22: 202.00473 | L22: 202.72675 | M22: 203.18738 | N22: 203.61855 | O22: 203.85323 | P22: 203.99608 | Q22: 204.04323 | R22: 204.0784 | S22: 204.18631 | T22: 204.21899 | U22: 203.99002 | V22: 203.79211 | W22: 203.48488 | X22: 203.15222 | Y22: 202.79279 | Z22: 202.38994 | AA22: 201.98462 | AB22: 201.58862 | AC22: 201.16939 | AD22: 200.72 | AE22: 200.25182 | AF22: 199.75125 | AG22: 0.009666
A23: TKI000:railpassmiles | B23: Passenger Rail | C23: 29.302727 | D23: 32.183659 | E23: 34.523235 | F23: 36.408005 | G23: 37.782608 | H23: 38.852116 | I23: 39.682259 | J23: 40.435604 | K23: 41.089024 | L23: 41.799473 | M23: 42.392326 | N23: 43.226955 | O23: 43.855072 | P23: 44.286602 | Q23: 44.641052 | R23: 44.98415 | S23: 45.384823 | T23: 45.809635 | U23: 46.217003 | V23: 46.77512 | W23: 47.199726 | X23: 47.657196 | Y23: 48.122261 | Z23: 48.558163 | AA23: 49.064247 | AB23: 49.669609 | AC23: 50.250259 | AD23: 50.763557 | AE23: 51.312565 | AF23: 51.905762 | AG23: 0.019911
B24: (billion seat miles available)
A25: TKI000:ba_Air | B25: Air | C25: 884.81805 | D25: 1076.55 | E25: 1230.1667 | F25: 1274.7023 | G25: 1318.1809 | H25: 1345.4996 | I25: 1366.0377 | J25: 1391.08 | K25: 1417.573 | L25: 1446.5729 | M25: 1474.0267 | N25: 1506.495 | O25: 1538.0137 | P25: 1562.5862 | Q25: 1585.3625 | R25: 1607.6597 | S25: 1633.062 | T25: 1659.3334 | U25: 1689.634 | V25: 1722.0522 | W25: 1750.3182 | X25: 1781.075 | Y25: 1813.511 | Z25: 1844.7888 | AA25: 1880.5153 | AB25: 1918.9608 | AC25: 1956.3782 | AD25: 1993.5126 | AE25: 2033.3671 | AF25: 2080.928 | AG25: 0.029928
B26: (billion ton miles traveled)
A27: TKI000:ba_Rail | B27: Rail | C27: 1642.4385 | D27: 1648.8412 | E27: 1642.1177 | F27: 1538.3422 | G27: 1550.6194 | H27: 1586.2102 | I27: 1584.9493 | J27: 1595.3766 | K27: 1596.9819 | L27: 1601.0176 | M27: 1607.3853 | N27: 1609.563 | O27: 1610.8304 | P27: 1600.2362 | Q27: 1594.3553 | R27: 1589.1704 | S27: 1589.8119 | T27: 1595.4429 | U27: 1599.4241 | V27: 1598.0879 | W27: 1603.0029 | X27: 1610.4822 | Y27: 1608.26 | Z27: 1612.2712 | AA27: 1606.3276 | AB27: 1612.4525 | AC27: 1612.1593 | AD27: 1614.0505 | AE27: 1618.0837 | AF27: 1632.7085 | AG27: -0.000205
A28: TKI000:ba_DomesticShipp | B28: Domestic Shipping | C28: 340.48767 | D28: 353.6615 | E28: 348.75345 | F28: 338.82715 | G28: 330.61054 | H28: 321.46387 | I28: 311.57352 | J28: 302.60565 | K28: 292.88565 | L28: 283.43982 | M28: 278.66483 | N28: 274.77252 | O28: 270.56769 | P28: 265.44858 | Q28: 260.36829 | R28: 255.54889 | S28: 251.06869 | T28: 246.48242 | U28: 242.55011 | V28: 238.31043 | W28: 236.52815 | X28: 234.91252 | Y28: 233.39484 | Z28: 231.42421 | AA28: 229.79132 | AB28: 228.7527 | AC28: 227.20117 | AD28: 224.90399 | AE28: 223.22272 | AF28: 222.72168 | AG28: -0.01453
B30: Energy Efficiency Indicators
B31: (miles per gallon)
A32: TKI000:ca_AvgCAFEStand | B32: New Light-Duty Vehicle CAFE Standard 2/ | C32: 35.223785 | D32: 35.448219 | E32: 35.773716 | F32: 36.137791 | G32: 36.521641 | H32: 37.052589 | I32: 37.014767 | J32: 36.989029 | K32: 36.961914 | L32: 36.958622 | M32: 36.939838 | N32: 36.985928 | O32: 36.985813 | P32: 36.980942 | Q32: 36.975254 | R32: 36.962643 | S32: 36.952339 | T32: 36.944729 | U32: 36.920826 | V32: 36.923 | W32: 36.914879 | X32: 36.909832 | Y32: 36.910637 | Z32: 36.90292 | AA32: 36.891422 | AB32: 36.8839 | AC32: 36.869686 | AD32: 36.851803 | AE32: 36.835728 | AF32: 36.799381 | AG32: 0.00151
A33: TKI000:ca_CarCAFEStand | B33: New Car 2/ | C33: 44.308037 | D33: 44.852161 | E33: 45.474854 | F33: 46.203018 | G33: 46.88335 | H33: 47.66552 | I33: 47.67852 | J33: 47.680176 | K33: 47.681534 | L33: 47.693249 | M33: 47.693249 | N33: 47.720654 | O33: 47.720654 | P33: 47.720654 | Q33: 47.720654 | R33: 47.720654 | S33: 47.720654 | T33: 47.720654 | U33: 47.720654 | V33: 47.723198 | W33: 47.723198 | X33: 47.723198 | Y33: 47.724876 | Z33: 47.724876 | AA33: 47.724876 | AB33: 47.725819 | AC33: 47.725819 | AD33: 47.725819 | AE33: 47.7272 | AF33: 47.7272 | AG33: 0.002567
A34: TKI000:ca_TwukCAFEStand | B34: New Light Truck 2/ | C34: 31.770002 | D34: 32.118862 | E34: 32.561729 | F34: 33.013966 | G34: 33.490234 | H34: 34.054272 | I34: 34.054272 | J34: 34.054337 | K34: 34.054375 | L34: 34.054375 | M34: 34.054428 | N34: 34.054428 | O34: 34.05447 | P34: 34.054501 | Q34: 34.054516 | R34: 34.054543 | S34: 34.054554 | T34: 34.054562 | U34: 34.054615 | V34: 34.054615 | W34: 34.054615 | X34: 34.054619 | Y34: 34.054619 | Z34: 34.054649 | AA34: 34.054672 | AB34: 34.05468 | AC34: 34.054707 | AD34: 34.054722 | AE34: 34.054733 | AF34: 34.054794 | AG34: 0.002398
A35: TKI000:ca_NewVehCred | B35: Compliance New Light-Duty Vehicle 3/ | C35: 36.206436 | D35: 37.252911 | E35: 37.623699 | F35: 37.920811 | G35: 37.962482 | H35: 38.013924 | I35: 38.047474 | J35: 38.095184 | K35: 38.134525 | L35: 38.218861 | M35: 38.268814 | N35: 38.471996 | O35: 38.578369 | P35: 38.669563 | Q35: 38.76865 | R35: 38.851624 | S35: 38.93512 | T35: 39.024349 | U35: 39.07325 | V35: 39.176624 | W35: 39.255142 | X35: 39.337894 | Y35: 39.448158 | Z35: 39.518944 | AA35: 39.566959 | AB35: 39.632595 | AC35: 39.679001 | AD35: 39.712738 | AE35: 39.753506 | AF35: 39.723286 | AG35: 0.003202
A36: TKI000:ca_NewCarCred | B36: New Car 3/ | C36: 45.484947 | D36: 46.512924 | E36: 46.912121 | F36: 47.579021 | G36: 48.273701 | H36: 48.75581 | I36: 48.774426 | J36: 48.750507 | K36: 48.759041 | L36: 48.841515 | M36: 48.888916 | N36: 49.057884 | O36: 49.201279 | P36: 49.326927 | Q36: 49.48447 | R36: 49.616722 | S36: 49.746288 | T36: 49.883045 | U36: 49.998047 | V36: 50.126984 | W36: 50.285145 | X36: 50.423515 | Y36: 50.602985 | Z36: 50.752964 | AA36: 50.870552 | AB36: 51.004326 | AC36: 51.13031 | AD36: 51.243896 | AE36: 51.368221 | AF36: 51.439392 | AG36: 0.004251
A37: TKI000:ca_NewTwukCred | B37: New Light Truck 3/ | C37: 32.672462 | D37: 33.914803 | E37: 34.468056 | F37: 34.848267 | G37: 34.908646 | H37: 34.96748 | I37: 35.051132 | J37: 35.143085 | K37: 35.220009 | L37: 35.309074 | M37: 35.380604 | N37: 35.537472 | O37: 35.634357 | P37: 35.722519 | Q37: 35.814598 | R37: 35.901054 | S37: 35.985985 | T37: 36.073086 | U37: 36.136738 | V37: 36.230877 | W37: 36.302101 | X37: 36.378498 | Y37: 36.472485 | Z37: 36.536041 | AA37: 36.5839 | AB37: 36.644684 | AC37: 36.692707 | AD37: 36.732998 | AE37: 36.777721 | AF37: 36.77499 | AG37: 0.004087
A38: TKI000:ca_TestedNewVeh | B38: Tested New Light-Duty Vehicle 4/ | C38: 35.99654 | D38: 36.858002 | E38: 37.158001 | F38: 37.42485 | G38: 37.463158 | H38: 37.513515 | I38: 37.541389 | J38: 37.580601 | K38: 37.60603 | L38: 37.667957 | M38: 37.699677 | N38: 37.863426 | O38: 37.940712 | P38: 38.004585 | Q38: 38.074978 | R38: 38.132923 | S38: 38.191898 | T38: 38.254623 | U38: 38.282417 | V38: 38.356304 | W38: 38.408718 | X38: 38.464462 | Y38: 38.544083 | Z38: 38.589527 | AA38: 38.616177 | AB38: 38.656784 | AC38: 38.680992 | AD38: 38.694092 | AE38: 38.712769 | AF38: 38.67157 | AG38: 0.002475
A39: TKI000:ca_TestedNewCar | B39: New Car 4/ | C39: 45.124638 | D39: 46.062195 | E39: 46.401501 | F39: 47.015823 | G39: 47.692608 | H39: 48.16629 | I39: 48.183952 | J39: 48.156532 | K39: 48.150143 | L39: 48.198467 | M39: 48.220913 | N39: 48.338505 | O39: 48.435463 | P39: 48.518211 | Q39: 48.627781 | R39: 48.717556 | S39: 48.805515 | T39: 48.897526 | U39: 48.971142 | V39: 49.053463 | W39: 49.16214 | X39: 49.251259 | Y39: 49.374622 | Z39: 49.473488 | AA39: 49.545494 | AB39: 49.62793 | AC39: 49.703941 | AD39: 49.768379 | AE39: 49.840511 | AF39: 49.869408 | AG39: 0.003453
A40: TKI000:ca_TestedNewTwuk | B40: New Light Truck 4/ | C40: 32.509567 | D40: 33.544163 | E40: 34.023964 | F40: 34.378746 | G40: 34.437973 | H40: 34.496552 | I40: 34.573219 | J40: 34.655514 | K40: 34.718678 | L40: 34.788059 | M40: 34.842812 | N40: 34.963966 | O40: 35.035858 | P40: 35.100307 | Q40: 35.168056 | R40: 35.233234 | S40: 35.297314 | T40: 35.361893 | U40: 35.408249 | V40: 35.476894 | W40: 35.526852 | X40: 35.58094 | Y40: 35.649826 | Z40: 35.693222 | AA40: 35.724327 | AB40: 35.765274 | AC40: 35.796162 | AD40: 35.820747 | AE40: 35.848598 | AF40: 35.838959 | AG40: 0.003368
A41: TKI000:ca_OnRoadNewVeh | B41: On-Road New Light-Duty Vehicle 5/ | C41: 29.36256 | D41: 30.064709 | E41: 30.308887 | F41: 30.525972 | G41: 30.556625 | H41: 30.597338 | I41: 30.619949 | J41: 30.651865 | K41: 30.672522 | L41: 30.723024 | M41: 30.748835 | N41: 30.882551 | O41: 30.945591 | P41: 30.997667 | Q41: 31.055063 | R41: 31.102282 | S41: 31.150343 | T41: 31.201481 | U41: 31.22406 | V41: 31.284332 | W41: 31.327047 | X41: 31.372492 | Y41: 31.437431 | Z41: 31.474463 | AA41: 31.496147 | AB41: 31.529242 | AC41: 31.548929 | AD41: 31.559546 | AE41: 31.574713 | AF41: 31.54097 | AG41: 0.002471
A42: TKI000:ca_OnRoadNewCar | B42: New Car 5/ | C42: 36.849445 | D42: 37.615067 | E42: 37.892151 | F42: 38.393814 | G42: 38.946487 | H42: 39.333302 | I42: 39.347725 | J42: 39.325333 | K42: 39.320118 | L42: 39.359581 | M42: 39.377907 | N42: 39.473934 | O42: 39.553112 | P42: 39.620686 | Q42: 39.710163 | R42: 39.783474 | S42: 39.855305 | T42: 39.930439 | U42: 39.990555 | V42: 40.057781 | W42: 40.14653 | X42: 40.219303 | Y42: 40.320045 | Z42: 40.40078 | AA42: 40.459579 | AB42: 40.526897 | AC42: 40.58897 | AD42: 40.641594 | AE42: 40.700497 | AF42: 40.724094 | AG42: 0.003453
A43: TKI000:ca_OnRoadNewTwuk | B43: New Light Truck 5/ | C43: 26.506937 | D43: 27.350502 | E43: 27.741713 | F43: 28.030987 | G43: 28.079279 | H43: 28.127041 | I43: 28.189552 | J43: 28.256651 | K43: 28.308153 | L43: 28.364723 | M43: 28.409367 | N43: 28.508152 | O43: 28.566769 | P43: 28.619318 | Q43: 28.674559 | R43: 28.727701 | S43: 28.779949 | T43: 28.832603 | U43: 28.870401 | V43: 28.926371 | W43: 28.967104 | X43: 29.011206 | Y43: 29.067373 | Z43: 29.102757 | AA43: 29.128117 | AB43: 29.161505 | AC43: 29.186687 | AD43: 29.206734 | AE43: 29.229443 | AF43: 29.221582 | AG43: 0.003368
... A47: TKI000:ca_FreightTruck | B47: Freight Truck | C47: 7.333722 | D47: 7.411123 | E47: 7.498699 | F47: 7.596442 | G47: 7.704683 | H47: 7.824306 | I47: 7.954823 | J47: 8.087138 | K47: 8.225566 | L47: 8.366446 | M47: 8.50761 | N47: 8.645619 | O47: 8.775343 | P47: 8.894295 | Q47: 9.00295 | R47: 9.103117 | S47: 9.194569 | T47: 9.277658 | U47: 9.353306 | V47: 9.422338 | W47: 9.48661 | X47: 9.543928 | Y47: 9.596098 | Z47: 9.642947 | AA47: 9.686286 | AB47: 9.728467 | AC47: 9.769426 | AD47: 9.810122 | AE47: 9.852329 | AF47: 9.893693 | AG47: 0.010378
B48: (seat miles per gallon)
A49: TKI000:ca_Aircraft | B49: Aircraft | C49: 73.643883 | D49: 74.164284 | E49: 74.678391 | F49: 75.103905 | G49: 75.577873 | H49: 75.855804 | I49: 76.291603 | J49: 76.782219 | K49: 77.283539 | L49: 77.818657 | M49: 78.392654 | N49: 79.043884 | O49: 79.726044 | P49: 80.462769 | Q49: 81.188049 | R49: 81.928444 | S49: 82.691994 | T49: 83.471085 | U49: 84.242378 | V49: 85.037781 | W49: 85.855034 | X49: 86.702995 | Y49: 87.537857 | Z49: 88.343834 | AA49: 89.164856 | AB49: 89.982239 | AC49: 90.78949 | AD49: 91.58223 | AE49: 92.350609 | AF49: 93.110046 | AG49: 0.00812
B50: (ton miles/thousand Btu)
A51: TKI000:ca_Rail | B51: Rail | C51: 3.512003 | D51: 3.534782 | E51: 3.55771 | F51: 3.580785 | G51: 3.60401 | H51: 3.627386 | I51: 3.650914 | J51: 3.674594 | K51: 3.698428 | L51: 3.722416 | M51: 3.74656 | N51: 3.77086 | O51: 3.795318 | P51: 3.819935 | Q51: 3.844712 | R51: 3.869649 | S51: 3.894748 | T51: 3.920009 | U51: 3.945435 | V51: 3.971025 | W51: 3.996782 | X51: 4.022705 | Y51: 4.048797 | Z51: 4.075058 | AA51: 4.101489 | AB51: 4.128091 | AC51: 4.154866 | AD51: 4.181815 | AE51: 4.208939 | AF51: 4.236238 | AG51: 0.006486
A52: TKI000:ca_DomesticShipp | B52: Domestic Shipping | C52: 4.870726 | D52: 4.899663 | E52: 4.928772 | F52: 4.958054 | G52: 4.987509 | H52: 5.01714 | I52: 5.046947 | J52: 5.076931 | K52: 5.107092 | L52: 5.137434 | M52: 5.167955 | N52: 5.198658 | O52: 5.229543 | P52: 5.260611 | Q52: 5.291864 | R52: 5.323303 | S52: 5.354929 | T52: 5.386742 | U52: 5.418745 | V52: 5.450938 | W52: 5.483322 | X52: 5.515898 | Y52: 5.548667 | Z52: 5.581632 | AA52: 5.614792 | AB52: 5.64815 | AC52: 5.681705 | AD52: 5.71546 | AE52: 5.749416 | AF52: 5.783573 | AG52: 0.005941
B54: Energy Use by Mode | C54: =SUM(C62:C63) -> 1.002543
B55: (quadrillion Btu)
A56: TKI000:da_Light-DutyVeh | B56: Light-Duty Vehicles | C56: 14.206476 | D56: 14.469707 | E56: 14.659187 | F56: 14.598367 | G56: 14.503467 | H56: 14.38808 | I56: 14.257594 | J56: 14.127343 | K56: 14.007595 | L56: 13.914637 | M56: 13.845855 | N56: 13.759979 | O56: 13.698157 | P56: 13.630536 | Q56: 13.554655 | R56: 13.488897 | S56: 13.43897 | T56: 13.402266 | U56: 13.387219 | V56: 13.385816 | W56: 13.388274 | X56: 13.398571 | Y56: 13.413081 | Z56: 13.442637 | AA56: 13.485066 | AB56: 13.548438 | AC56: 13.625167 | AD56: 13.70544 | AE56: 13.792853 | AF56: 13.901684 | AG56: -0.000748
A57: TKI000:da_CommercialLig | B57: Commercial Light Trucks 1/ | C57: 0.887078 | D57: 0.893868 | E57: 0.89429 | F57: 0.886659 | G57: 0.882875 | H57: 0.876934 | I57: 0.869392 | J57: 0.865477 | K57: 0.860391 | L57: 0.856658 | M57: 0.854119 | N57: 0.855325 | O57: 0.856481 | P57: 0.855142 | Q57: 0.854727 | R57: 0.85542 | S57: 0.858123 | T57: 0.861537 | U57: 0.866278 | V57: 0.871033 | W57: 0.87597 | X57: 0.881709 | Y57: 0.888585 | Z57: 0.894321 | AA57: 0.900751 | AB57: 0.910873 | AC57: 0.919058 | AD57: 0.925198 | AE57: 0.932484 | AF57: 0.942469 | AG57: 0.002091
A58: TKI000:da_BusTransporta | B58: Bus Transportation | C58: 0.175036 | D58: 0.198865 | E58: 0.211124 | F58: 0.217573 | G58: 0.221255 | H58: 0.223427 | I58: 0.224854 | J58: 0.225624 | K58: 0.225938 | L58: 0.226178 | M58: 0.226098 | N58: 0.226467 | O58: 0.226255 | P58: 0.225929 | Q58: 0.225453 | R58: 0.22502 | S58: 0.224739 | T58: 0.224416 | U58: 0.223595 | V58: 0.223088 | W58: 0.222307 | X58: 0.221529 | Y58: 0.220706 | Z58: 0.219736 | AA58: 0.218771 | AB58: 0.217844 | AC58: 0.216871 | AD58: 0.215827 | AE58: 0.214698 | AF58: 0.21332 | AG58: 0.006844
A59: TKI000:da_FreightTrucks | B59: Freight Trucks | C59: 5.566177 | D59: 5.604339 | E59: 5.571467 | F59: 5.510074 | G59: 5.460786 | H59: 5.39327 | I59: 5.31387 | J59: 5.2521 | K59: 5.180445 | L59: 5.117373 | M59: 5.053175 | N59: 5.002106 | O59: 4.953718 | P59: 4.90122 | Q59: 4.862717 | R59: 4.830275 | S59: 4.802789 | T59: 4.781016 | U59: 4.767426 | V59: 4.757022 | W59: 4.749592 | X59: 4.752261 | Y59: 4.760077 | Z59: 4.757321 | AA59: 4.760025 | AB59: 4.777221 | AC59: 4.787605 | AD59: 4.783873 | AE59: 4.785275 | AF59: 4.808629 | AG59: -0.005032
A60: TKI000:da_Rail,Passenge | B60: Rail, Passenger | C60: 0.035314 | D60: 0.039019 | E60: 0.042028 | F60: 0.044429 | G60: 0.046198 | H60: 0.047579 | I60: 0.048659 | J60: 0.049614 | K60: 0.050433 | L60: 0.0513 | M60: 0.052026 | N60: 0.053006 | O60: 0.053744 | P60: 0.054263 | Q60: 0.0547 | R60: 0.055121 | S60: 0.055597 | T60: 0.0561 | U60: 0.056588 | V60: 0.057244 | W60: 0.057752 | X60: 0.058301 | Y60: 0.058859 | Z60: 0.059386 | AA60: 0.059993 | AB60: 0.060714 | AC60: 0.06141 | AD60: 0.062035 | AE60: 0.062699 | AF60: 0.063409 | AG60: 0.020389
A61: TKI000:da_Rail,Freight | B61: Rail, Freight | C61: 0.467664 | D61: 0.466462 | E61: 0.461566 | F61: 0.42961 | G61: 0.430248 | H61: 0.437287 | I61: 0.434124 | J61: 0.434164 | K61: 0.4318 | L61: 0.430102 | M61: 0.42903 | N61: 0.426842 | O61: 0.424426 | P61: 0.418917 | Q61: 0.414688 | R61: 0.410676 | S61: 0.408194 | T61: 0.407 | U61: 0.405386 | V61: 0.402437 | W61: 0.401073 | X61: 0.400348 | Y61: 0.397219 | Z61: 0.395644 | AA61: 0.391645 | AB61: 0.390605 | AC61: 0.388017 | AD61: 0.385969 | AE61: 0.38444 | AF61: 0.385415 | AG61: -0.006648
A62: TKI000:da_Shipping,Dome | B62: Shipping, Domestic | C62: 0.07517 | D62: 0.077208 | E62: 0.075597 | F62: 0.073011 | G62: 0.070829 | H62: 0.06848 | I62: 0.065995 | J62: 0.063741 | K62: 0.061341 | L62: 0.059028 | M62: 0.057702 | N62: 0.05657 | O62: 0.055382 | P62: 0.054015 | Q62: 0.052689 | R62: 0.051423 | S62: 0.050232 | T62: 0.049037 | U62: 0.047978 | V62: 0.04687 | W62: 0.046252 | X62: 0.045674 | Y62: 0.045116 | Z62: 0.044477 | AA62: 0.043907 | AB62: 0.043461 | AC62: 0.042915 | AD62: 0.042233 | AE62: 0.041674 | AF62: 0.041336 | AG62: -0.02041
A63: TKI000:da_Shipping,Inte | B63: Shipping, International | C63: 0.927373 | D63: 0.989493 | E63: 0.882994 | F63: 0.88465 | G63: 0.887016 | H63: 0.885475 | I63: 0.881852 | J63: 0.880428 | K63: 0.880436 | L63: 0.879901 | M63: 0.879876 | N63: 0.883346 | O63: 0.88333 | P63: 0.883317 | Q63: 0.884185 | R63: 0.884685 | S63: 0.885367 | T63: 0.885716 | U63: 0.886788 | V63: 0.880226 | W63: 0.879765 | X63: 0.880413 | Y63: 0.878385 | Z63: 0.876437 | AA63: 0.876308 | AB63: 0.874585 | AC63: 0.874849 | AD63: 0.875354 | AE63: 0.87524 | AF63: 0.876128 | AG63: -0.001958
A64: TKI000:da_RecreationalB | B64: Recreational Boats | C64: 0.202608 | D64: 0.20267 | E64: 0.202302 | F64: 0.202258 | G64: 0.20154 | H64: 0.200466 | I64: 0.198825 | J64: 0.197571 | K64: 0.196387 | L64: 0.195377 | M64: 0.194215 | N64: 0.193455 | O64: 0.192654 | P64: 0.191359 | Q64: 0.190015 | R64: 0.188708 | S64: 0.18769 | T64: 0.186743 | U64: 0.185897 | V64: 0.185162 | W64: 0.184172 | X64: 0.183249 | Y64: 0.182375 | Z64: 0.181536 | AA64: 0.180867 | AB64: 0.180417 | AC64: 0.179854 | AD64: 0.179121 | AE64: 0.178563 | AF64: 0.178365 | AG64: -0.004385
A65: TKI000:da_Air | B65: Air | C65: 2.290121 | D65: 2.662098 | E65: 2.926571 | F65: 2.996366 | G65: 3.053528 | H65: 3.092441 | I65: 3.117277 | J65: 3.148944 | K65: 3.179444 | L65: 3.213575 | M65: 3.237388 | N65: 3.266196 | O65: 3.281667 | P65: 3.27887 | Q65: 3.289348 | R65: 3.301551 | S65: 3.321476 | T65: 3.34077 | U65: 3.368455 | V65: 3.399192 | W65: 3.422694 | X65: 3.451261 | Y65: 3.481256 | Z65: 3.507079 | AA65: 3.541613 | AB65: 3.577736 | AC65: 3.611276 | AD65: 3.642456 | AE65: 3.676511 | AF65: 3.722466 | AG65: 0.016892
A66: TKI000:da_MilitaryUse | B66: Military Use | C66: 0.537671 | D66: 0.545017 | E66: 0.538948 | F66: 0.538102 | G66: 0.541071 | H66: 0.543234 | I66: 0.544715 | J66: 0.546031 | K66: 0.543575 | L66: 0.544233 | M66: 0.542594 | N66: 0.541553 | O66: 0.540415 | P66: 0.539185 | Q66: 0.537864 | R66: 0.53664 | S66: 0.535439 | T66: 0.534178 | U66: 0.53286 | V66: 0.531481 | W66: 0.530053 | X66: 0.528581 | Y66: 0.527063 | Z66: 0.525501 | AA66: 0.523899 | AB66: 0.522267 | AC66: 0.52061 | AD66: 0.51893 | AE66: 0.517229 | AF66: 0.51551 | AG66: -0.00145
A67: TKI000:da_Lubricants | B67: Lubricants | C67: 0.125035 | D67: 0.126333 | E67: 0.127051 | F67: 0.127569 | G67: 0.127841 | H67: 0.128109 | I67: 0.128132 | J67: 0.12817 | K67: 0.128204 | L67: 0.128195 | M67: 0.128161 | N67: 0.128165 | O67: 0.12819 | P67: 0.128088 | Q67: 0.127913 | R67: 0.127749 | S67: 0.12763 | T67: 0.127583 | U67: 0.127601 | V67: 0.12764 | W67: 0.127663 | X67: 0.127659 | Y67: 0.127644 | Z67: 0.127614 | AA67: 0.127559 | AB67: 0.127549 | AC67: 0.127539 | AD67: 0.127511 | AE67: 0.127524 | AF67: 0.12753 | AG67: 0.000682
... A69: TKI000:da_Total | B69: Total | C69: 26.243639 | D69: 26.9743 | E69: 27.273109 | F69: 27.171753 | G69: 27.078533 | H69: 26.923626 | I69: 26.707367 | J69: 26.546474 | K69: 26.367313 | L69: 26.228493 | M69: 26.108463 | N69: 26.004044 | O69: 25.907568 | P69: 25.764507 | Q69: 25.650166 | R69: 25.558237 | S69: 25.504328 | T69: 25.47117 | U69: 25.476851 | V69: 25.493582 | W69: 25.515369 | X69: 25.565006 | Y69: 25.620152 | Z69: 25.678684 | AA69: 25.755495 | AB69: 25.880117 | AC69: 26.011936 | AD69: 26.128946 | AE69: 26.261543 | AF69: 26.453993 | AG69: 0.000275
B71: (million barrels per day oil equivalent)
A72: TKI000:ea_Light-DutyVeh | B72: Light-Duty Vehicles | C72: 7.704193 | D72: 7.846954 | E72: 7.949446 | F72: 7.915858 | G72: 7.865163 | H72: 7.803294 | I72: 7.733153 | J72: 7.663057 | K72: 7.598695 | L72: 7.548836 | M72: 7.512058 | N72: 7.465995 | O72: 7.433 | P72: 7.396846 | Q72: 7.356222 | R72: 7.320766 | S72: 7.293912 | T72: 7.274251 | U72: 7.266385 | V72: 7.265864 | W72: 7.267317 | X72: 7.272983 | Y72: 7.280959 | Z72: 7.297201 | AA72: 7.320408 | AB72: 7.355022 | AC72: 7.396894 | AD72: 7.440705 | AE72: 7.488386 | AF72: 7.547729 | AG72: -0.000707
A73: TKI000:ea_CommercialLig | B73: Commercial Light Trucks 1/ | C73: 0.463413 | D73: 0.467488 | E73: 0.468111 | F73: 0.464443 | G73: 0.462844 | H73: 0.460061 | I73: 0.456217 | J73: 0.454264 | K73: 0.451679 | L73: 0.449785 | M73: 0.448513 | N73: 0.449166 | O73: 0.449775 | P73: 0.449079 | Q73: 0.448869 | R73: 0.449232 | S73: 0.450656 | T73: 0.45246 | U73: 0.454959 | V73: 0.457489 | W73: 0.46011 | X73: 0.46315 | Y73: 0.466768 | Z73: 0.46979 | AA73: 0.473164 | AB73: 0.478447 | AC73: 0.482769 | AD73: 0.486031 | AE73: 0.489925 | AF73: 0.495245 | AG73: 0.002293
A74: TKI000:ea_BusTransporta | B74: Bus Transportation | C74: 0.085604 | D74: 0.097445 | E74: 0.103468 | F74: 0.106581 | G74: 0.108381 | H74: 0.109486 | I74: 0.11018 | J74: 0.11057 | K74: 0.110704 | L74: 0.110809 | M74: 0.110787 | N74: 0.110997 | O74: 0.110892 | P74: 0.110734 | Q74: 0.110503 | R74: 0.110282 | S74: 0.110141 | T74: 0.109987 | U74: 0.109583 | V74: 0.109342 | W74: 0.10896 | X74: 0.10859 | Y74: 0.108195 | Z74: 0.107721 | AA74: 0.107261 | AB74: 0.106797 | AC74: 0.106322 | AD74: 0.105816 | AE74: 0.105265 | AF74: 0.104573 | AG74: 0.006926
A75: TKI000:ea_FreightTrucks | B75: Freight Trucks | C75: 2.680613 | D75: 2.700198 | E75: 2.684349 | F75: 2.654433 | G75: 2.630163 | H75: 2.597959 | I75: 2.55924 | J75: 2.530019 | K75: 2.496034 | L75: 2.466156 | M75: 2.43592 | N75: 2.411911 | O75: 2.38938 | P75: 2.364964 | Q75: 2.347258 | R75: 2.332528 | S75: 2.320166 | T75: 2.310524 | U75: 2.304726 | V75: 2.300581 | W75: 2.297948 | X75: 2.300221 | Y75: 2.305018 | Z75: 2.304764 | AA75: 2.307121 | AB75: 2.3164 | AC75: 2.322643 | AD75: 2.321992 | AE75: 2.323969 | AF75: 2.336304 | AG75: -0.004729
A76: TKI000:ea_Rail,Passenge | B76: Rail, Passenger | C76: 0.016725 | D76: 0.018485 | E76: 0.019911 | F76: 0.021047 | G76: 0.021883 | H76: 0.022538 | I76: 0.023046 | J76: 0.0235 | K76: 0.023888 | L76: 0.024298 | M76: 0.024643 | N76: 0.025106 | O76: 0.025456 | P76: 0.025702 | Q76: 0.025909 | R76: 0.026109 | S76: 0.026335 | T76: 0.026573 | U76: 0.026804 | V76: 0.027114 | W76: 0.027355 | X76: 0.027616 | Y76: 0.02788 | Z76: 0.02813 | AA76: 0.028418 | AB76: 0.028758 | AC76: 0.029089 | AD76: 0.029385 | AE76: 0.029701 | AF76: 0.030036 | AG76: 0.020396
A77: TKI000:ea_Rail,Freight | B77: Rail, Freight | C77: 0.22212 | D77: 0.221673 | E77: 0.219345 | F77: 0.204128 | G77: 0.204375 | H77: 0.20772 | I77: 0.206137 | J77: 0.206148 | K77: 0.205007 | L77: 0.204174 | M77: 0.203649 | N77: 0.202579 | O77: 0.201415 | P77: 0.198787 | Q77: 0.196762 | R77: 0.194844 | S77: 0.193648 | T77: 0.193066 | U77: 0.192275 | V77: 0.190861 | W77: 0.1902 | X77: 0.189842 | Y77: 0.188345 | Z77: 0.187587 | AA77: 0.185676 | AB77: 0.18516 | AC77: 0.183926 | AD77: 0.182942 | AE77: 0.182211 | AF77: 0.182652 | AG77: -0.006723
A78: TKI000:ea_Shipping,Dome | B78: Shipping, Domestic | C78: 0.035635 | D78: 0.036628 | E78: 0.035869 | F78: 0.034641 | G78: 0.0336 | H78: 0.03249 | I78: 0.031304 | J78: 0.030238 | K78: 0.029102 | L78: 0.028006 | M78: 0.02738 | N78: 0.026843 | O78: 0.026282 | P78: 0.025636 | Q78: 0.025009 | R78: 0.02441 | S78: 0.023846 | T78: 0.023281 | U78: 0.022779 | V78: 0.022255 | W78: 0.021962 | X78: 0.021687 | Y78: 0.021423 | Z78: 0.02112 | AA78: 0.02085 | AB78: 0.020636 | AC78: 0.020378 | AD78: 0.020054 | AE78: 0.01979 | AF78: 0.019628 | AG78: -0.020354
A79: TKI000:ea_Shipping,Inte | B79: Shipping, International | C79: 0.419363 | D79: 0.441466 | E79: 0.399689 | F79: 0.40035 | G79: 0.401242 | H79: 0.40073 | I79: 0.399378 | J79: 0.398912 | K79: 0.398977 | L79: 0.398828 | M79: 0.398874 | N79: 0.400209 | O79: 0.400255 | P79: 0.400304 | Q79: 0.400674 | R79: 0.400911 | S79: 0.401209 | T79: 0.401385 | U79: 0.401824 | V79: 0.399433 | W79: 0.399314 | X79: 0.39961 | Y79: 0.39891 | Z79: 0.398244 | AA79: 0.398243 | AB79: 0.397645 | AC79: 0.397809 | AD79: 0.398055 | AE79: 0.398077 | AF79: 0.398458 | AG79: -0.001762
A80: TKI000:ea_RecreationalB | B80: Recreational Boats | C80: 0.109855 | D80: 0.109893 | E80: 0.109697 | F80: 0.109677 | G80: 0.109311 | H80: 0.108752 | I80: 0.107885 | J80: 0.107228 | K80: 0.106609 | L80: 0.106084 | M80: 0.105476 | N80: 0.105086 | O80: 0.104674 | P80: 0.103992 | Q80: 0.103284 | R80: 0.102591 | S80: 0.102055 | T80: 0.101558 | U80: 0.101114 | V80: 0.100732 | W80: 0.100208 | X80: 0.09972 | Y80: 0.099259 | Z80: 0.098816 | AA80: 0.098466 | AB80: 0.098235 | AC80: 0.097943 | AD80: 0.097558 | AE80: 0.097268 | AF80: 0.097174 | AG80: -0.004221
A81: TKI000:ea_Air | B81: Air | C81: 1.107903 | D81: 1.287641 | E81: 1.415433 | F81: 1.449158 | G81: 1.47678 | H81: 1.495585 | I81: 1.507588 | J81: 1.522892 | K81: 1.537632 | L81: 1.554126 | M81: 1.565635 | N81: 1.579558 | O81: 1.587036 | P81: 1.585687 | Q81: 1.590752 | R81: 1.596651 | S81: 1.60628 | T81: 1.615605 | U81: 1.628985 | V81: 1.643839 | W81: 1.655197 | X81: 1.669002 | Y81: 1.683497 | Z81: 1.695976 | AA81: 1.712665 | AB81: 1.730121 | AC81: 1.746329 | AD81: 1.761397 | AE81: 1.777854 | AF81: 1.800061 | AG81: 0.016877
A82: TKI000:ea_MilitaryUse | B82: Military Use | C82: 0.257883 | D82: 0.261482 | E82: 0.258618 | F82: 0.258205 | G82: 0.259617 | H82: 0.260659 | I82: 0.261352 | J82: 0.261988 | K82: 0.260811 | L82: 0.261125 | M82: 0.260341 | N82: 0.259838 | O82: 0.259294 | P82: 0.258706 | Q82: 0.258073 | R82: 0.257488 | S82: 0.256912 | T82: 0.256308 | U82: 0.255673 | V82: 0.255013 | W82: 0.254329 | X82: 0.253624 | Y82: 0.252897 | Z82: 0.25215 | AA82: 0.251381 | AB82: 0.250595 | AC82: 0.249803 | AD82: 0.248998 | AE82: 0.248186 | AF82: 0.247357 | AG82: -0.001436
A83: TKI000:ea_Lubricants | B83: Lubricants | C83: 0.059062 | D83: 0.059676 | E83: 0.060015 | F83: 0.060259 | G83: 0.060388 | H83: 0.060514 | I83: 0.060525 | J83: 0.060543 | K83: 0.060559 | L83: 0.060555 | M83: 0.060539 | N83: 0.060541 | O83: 0.060553 | P83: 0.060505 | Q83: 0.060422 | R83: 0.060344 | S83: 0.060288 | T83: 0.060266 | U83: 0.060275 | V83: 0.060293 | W83: 0.060304 | X83: 0.060302 | Y83: 0.060295 | Z83: 0.060281 | AA83: 0.060255 | AB83: 0.06025 | AC83: 0.060245 | AD83: 0.060232 | AE83: 0.060238 | AF83: 0.060241 | AG83: 0.000682
... A85: TKI000:ea_Total | B85: Total | C85: 13.515658 | D85: 13.879316 | E85: 14.045151 | F85: 13.991995 | G85: 13.941672 | H85: 13.861561 | I85: 13.749854 | J85: 13.66566 | K85: 13.573191 | L85: 13.501842 | M85: 13.44112 | N85: 13.386461 | O85: 13.337643 | P85: 13.266096 | Q85: 13.207728 | R85: 13.160557 | S85: 13.132689 | T85: 13.115678 | U85: 13.118619 | V85: 13.128693 | W85: 13.140699 | X85: 13.166513 | Y85: 13.195662 | Z85: 13.227399 | AA85: 13.268625 | AB85: 13.334352 | AC85: 13.404383 | AD85: 13.46729 | AE85: 13.538466 | AF85: 13.639596 | AG85: 0.000315
B87: 1/ Commercial trucks 8,501 to 10,000 pounds gross vehicle weight rating.
B88: 2/ CAFE standard based on projected new vehicle sales.
B89: 3/ Includes CAFE credits for alternative fueled vehicle sales and credit banking.
B90: 4/ Environmental Protection Agency rated miles per gallon.
B91: 5/ Tested new vehicle efficiency revised for on-road performance.
B92: 6/ Combined "on-the-road" estimate for all cars and light trucks.
B93: CAFE = Corporate average fuel economy.
B94: Btu = British thermal unit.
B95: Note: Totals may not equal sum of components due to independent rounding.
B96: Sources: 2021: U.S. Energy Information Administration (EIA), Short-Term Energy Outlook, November 2021 and EIA,
B97: AEO2022 National Energy Modeling System run ref2022.d011222a. Projections: EIA, AEO2022 National Energy Modeling System run ref2022.d011222a.

Sheet AEO 2022 Table 35 Raw
A1: Table 35. Transportation Sector Energy Use by Mode and Type
A2: https://www.eia.gov/outlooks/aeo/data/browser/#/?id=45-AEO2022&cases=lowmacro&sourcekey=0
A3: Wed Jul 13 2022 15:20:04 GMT-0400 (Eastern Daylight Time)
A4: Source: U.S. Energy Information Administration
B5: full name | C5: api key | D5: units | E5: 2020 | F5: 2021 | G5: 2022 | H5: 2023 | I5: 2024 | J5: 2025 | K5: 2026 | L5: 2027 | M5: 2028 | N5: 2029 | O5: 2030 | P5: 2031 | Q5: 2032 | R5: 2033 | S5: 2034 | T5: 2035 | U5: 2036 | V5: 2037 | W5: 2038 | X5: 2039 | Y5: 2040 | Z5: 2041 | AA5: 2042 | AB5: 2043 | AC5: 2044 | AD5: 2045 | AE5: 2046 | AF5: 2047 | AG5: 2048 | AH5: 2049 | AI5: 2050 | AJ5: Growth (2021-2050)
A6: Energy Use by Mode | C6: 45-AEO2022.2.
A7: Highway | C7: 45-AEO2022.3.
A8: Light-Duty Vehicles | B8: Transportation Energy Use: Highway: Light-Duty Vehicles: Low economic growth | C8: 45-AEO2022.4.lowmacro-d011222a | D8: trillion Btu | F8: 14206.474 | G8: 14469.706 | H8: 14659.188 | I8: 14598.368 | J8: 14503.467 | K8: 14388.081 | L8: 14257.595 | M8: 14127.344 | N8: 14007.598 | O8: 13914.639 | P8: 13845.857 | Q8: 13759.981 | R8: 13698.158 | S8: 13630.538 | T8: 13554.658 | U8: 13488.901 | V8: 13438.974 | W8: 13402.269 | X8: 13387.224 | Y8: 13385.82 | Z8: 13388.279 | AA8: 13398.576 | AB8: 13413.086 | AC8: 13442.642 | AD8: 13485.071 | AE8: 13548.444 | AF8: 13625.173 | AG8: 13705.443 | AH8: 13792.859 | AI8: 13901.69 | AJ8: -0.001
A9: Automobiles | B9: Transportation Energy Use: Highway: Light-Duty Vehicles: Automobiles: Low economic growth | C9: 45-AEO2022.5.lowmacro-d011222a | D9: trillion Btu | F9: 5631.8501 | G9: 5587.0234 | H9: 5492.9976 | I9: 5291.4448 | J9: 5070.6128 | K9: 4834.3223 | L9: 4592.436 | M9: 4355.2095 | N9: 4124.0532 | O9: 3908.6575 | P9: 3709.8555 | Q9: 3521.0327 | R9: 3352.0923 | S9: 3198.8306 | T9: 3057.4036 | U9: 2933.9958 | V9: 2830.0161 | W9: 2745.9658 | X9: 2677.7312 | Y9: 2624.7693 | Z9: 2581.687 | AA9: 2549.7239 | AB9: 2526.2866 | AC9: 2509.3564 | AD9: 2497.9119 | AE9: 2492.675 | AF9: 2491.1101 | AG9: 2490.6978 | AH9: 2491.8162 | AI9: 2496.1409 | AJ9: -0.028
A10: Light Trucks | B10: Transportation Energy Use: Highway: Light-Duty Vehicles: Light Trucks: Low economic growth | C10: 45-AEO2022.6.lowmacro-d011222a | D10: trillion Btu | F10: 8558.4277 | G10: 8866.6143 | H10: 9150.3926 | I10: 9291.7051 | J10: 9418.2715 | K10: 9539.8564 | L10: 9651.9531 | M10: 9759.6113 | N10: 9871.6865 | O10: 9994.7451 | P10: 10125.339 | Q10: 10228.831 | R10: 10336.436 | S10: 10422.52 | T10: 10488.475 | U10: 10546.482 | V10: 10600.835 | W10: 10648.424 | X10: 10701.81 | Y10: 10753.521 | Z10: 10799.186 | AA10: 10841.538 | AB10: 10879.551 | AC10: 10926.085 | AD10: 10979.99 | AE10: 11048.614 | AF10: 11126.91 | AG10: 11207.594 | AH10: 11293.886 | AI10: 11398.379 | AJ10: 0.01
A11: Motorcycles | B11: Transportation Energy Use: Highway: Light-Duty Vehicles: Motorcycles: Low economic growth | C11: 45-AEO2022.7.lowmacro-d011222a | D11: trillion Btu | F11: 16.196756 | G11: 16.06806 | H11: 15.797902 | I11: 15.21783 | J11: 14.582477 | K11: 13.902256 | L11: 13.205594 | M11: 12.522964 | N11: 11.857192 | O11: 11.236345 | P11: 10.662895 | Q11: 10.118478 | R11: 9.630422 | S11: 9.188295 | T11: 8.779905 | U11: 8.422959 | V11: 8.121965 | W11: 7.879196 | X11: 7.682385 | Y11: 7.529769 | Z11: 7.405809 | AA11: 7.314459 | AB11: 7.247967 | AC11: 7.200075 | AD11: 7.168805 | AE11: 7.155212 | AF11: 7.152213 | AG11: 7.152592 | AH11: 7.157367 | AI11: 7.171286 | AJ11: -0.028
A12: Commercial Light Trucks | B12: Transportation Energy Use: Highway: Commercial Light Trucks: Low economic growth | C12: 45-AEO2022.8.lowmacro-d011222a | D12: trillion Btu | F12: 887.07782 | G12: 893.86768 | H12: 894.28961 | I12: 886.65912 | J12: 882.87537 | K12: 876.93408 | L12: 869.39209 | M12: 865.47681 | N12: 860.39105 | O12: 856.65826 | P12: 854.1192 | Q12: 855.32477 | R12: 856.48071 | S12: 855.14209 | T12: 854.72675 | U12: 855.41986 | V12: 858.12305 | W12: 861.53656 | X12: 866.27771 | Y12: 871.03265 | Z12: 875.96985 | AA12: 881.7085 | AB12: 888.58466 | AC12: 894.3205 | AD12: 900.75098 | AE12: 910.87262 | AF12: 919.05756 | AG12: 925.19794 | AH12: 932.48407 | AI12: 942.46875 | AJ12: 0.002
A13: Buses | B13: Transportation Energy Use: Highway: Buses: Low economic growth | C13: 45-AEO2022.9.lowmacro-d011222a | D13: trillion Btu | F13: 175.03555 | G13: 198.86502 | H13: 211.12376 | I13: 217.57317 | J13: 221.25517 | K13: 223.4267 | L13: 224.85411 | M13: 225.6241 | N13: 225.9375 | O13: 226.17833 | P13: 226.09793 | Q13: 226.46729 | R13: 226.25546 | S13: 225.92949 | T13: 225.45317 | U13: 225.02034 | V13: 224.73885 | W13: 224.41641 | X13: 223.59464 | Y13: 223.08754 | Z13: 222.30707 | AA13: 221.52939 | AB13: 220.70592 | AC13: 219.7364 | AD13: 218.77069 | AE13: 217.84351 | AF13: 216.8708 | AG13: 215.82713 | AH13: 214.69788 | AI13: 213.3197 | AJ13: 0.007
A14: Transit | B14: Transportation Energy Use: Highway: Buses: Transit: Low economic growth | C14: 45-AEO2022.10.lowmacro-d011222a | D14: trillion Btu | F14: 74.852699 | G14: 81.355377 | H14: 86.454163 | I14: 89.928833 | J14: 92.255287 | K14: 93.902145 | L14: 95.211914 | M14: 96.014572 | N14: 96.477699 | O14: 96.971123 | P14: 97.218689 | Q14: 97.90551 | R14: 97.958015 | S14: 97.831581 | T14: 97.541344 | U14: 97.204292 | V14: 96.802773 | W14: 96.423637 | X14: 95.894089 | Y14: 95.695412 | Z14: 95.297791 | AA14: 94.935593 | AB14: 94.543076 | AC14: 94.018402 | AD14: 93.499649 | AE14: 93.016815 | AF14: 92.511353 | AG14: 91.954102 | AH14: 91.324509 | AI14: 90.447365 | AJ14: 0.007
A15: Intercity | B15: Transportation Energy Use: Highway: Buses: Intercity: Low economic growth | C15: 45-AEO2022.11.lowmacro-d011222a | D15: trillion Btu | F15: 24.178581 | G15: 26.924843 | H15: 29.074097 | I15: 30.763142 | J15: 32.087753 | K15: 33.140427 | L15: 33.983406 | M15: 34.669655 | N15: 35.238094 | O15: 35.71962 | P15: 36.13047 | Q15: 36.483799 | R15: 36.783035 | S15: 37.032639 | T15: 37.248863 | U15: 37.430058 | V15: 37.571205 | W15: 37.699574 | X15: 37.847202 | Y15: 37.985191 | Z15: 38.116562 | AA15: 38.244179 | AB15: 38.36713 | AC15: 38.485535 | AD15: 38.60136 | AE15: 38.716251 | AF15: 38.829079 | AG15: 38.938385 | AH15: 39.049194 | AI15: 39.16433 | AJ15: 0.017
A16: School | B16: Transportation Energy Use: Highway: Buses: School: Low economic growth | C16: 45-AEO2022.12.lowmacro-d011222a | D16: trillion Btu | F16: 76.00425 | G16: 90.584778 | H16: 95.595497 | I16: 96.881203 | J16: 96.912132 | K16: 96.384125 | L16: 95.658813 | M16: 94.939873 | N16: 94.221725 | O16: 93.487572 | P16: 92.748779 | Q16: 92.077988 | R16: 91.514435 | S16: 91.065262 | T16: 90.663017 | U16: 90.385994 | V16: 90.364883 | W16: 90.293182 | X16: 89.853371 | Y16: 89.406929 | Z16: 88.892708 | AA16: 88.349617 | AB16: 87.795708 | AC16: 87.232452 | AD16: 86.669685 | AE16: 86.110458 | AF16: 85.53038 | AG16: 84.934639 | AH16: 84.324181 | AI16: 83.708008 | AJ16: 0.003
A17: Freight Trucks | B17: Transportation Energy Use: Highway: Freight Trucks: Low economic growth | C17: 45-AEO2022.13.lowmacro-d011222a | D17: trillion Btu | F17: 5567.7749 | G17: 5606.2368 | H17: 5573.6108 | I17: 5512.4048 | J17: 5463.3071 | K17: 5395.9653 | L17: 5316.7314 | M17: 5255.1426 | N17: 5183.6689 | O17: 5120.7822 | P17: 5056.769 | Q17: 5005.8901 | R17: 4957.6914 | S17: 4905.3716 | T17: 4867.0518 | U17: 4834.7939 | V17: 4807.4922 | W17: 4785.9028 | X17: 4772.5151 | Y17: 4762.3008 | Z17: 4755.0874 | AA17: 4757.9648 | AB17: 4766.0405 | AC17: 4763.5718 | AD17: 4766.5581 | AE17: 4784.0742 | AF17: 4794.7812 | AG17: 4791.3721 | AH17: 4793.1113 | AI17: 4816.8691 | AJ17: -0.005
A18: Light Medium | B18: Transportation Energy Use: Highway: Freight Trucks: Light Medium: Low economic growth | C18: 45-AEO2022.14.lowmacro-d011222a | D18: trillion Btu | F18: 667.7785 | G18: 678.41467 | H18: 681.41339 | I18: 677.60236 | J18: 673.27124 | K18: 666.94269 | L18: 660.18646 | M18: 656.77063 | N18: 653.76807 | O18: 653.70758 | P18: 655.0354 | Q18: 658.81879 | R18: 663.2558 | S18: 667.38263 | T18: 673.36352 | U18: 679.79236 | V18: 685.76569 | W18: 691.31091 | X18: 696.8017 | Y18: 701.98004 | Z18: 707.80664 | AA18: 714.7096 | AB18: 722.49078 | AC18: 729.01422 | AD18: 736.52789 | AE18: 746.75049 | AF18: 756.18042 | AG18: 764.14563 | AH18: 773.96503 | AI18: 786.59027 | AJ18: 0.006
A19: Medium | B19: Transportation Energy Use: Highway: Freight Trucks: Medium: Low economic growth | C19: 45-AEO2022.15.lowmacro-d011222a | D19: trillion Btu | F19: 902.76593 | G19: 905.0816 | H19: 898.97089 | I19: 890.52478 | J19: 884.57471 | K19: 877.22315 | L19: 869.68115 | M19: 866.85889 | N19: 862.79327 | O19: 859.91382 | P19: 856.35919 | Q19: 855.5227 | R19: 854.70367 | S19: 853.12958 | T19: 854.27893 | U19: 857.00336 | V19: 861.31982 | W19: 865.80127 | X19: 872.67578 | Y19: 879.87744 | Z19: 888.08704 | AA19: 898.26007 | AB19: 910.17444 | AC19: 920.68384 | AD19: 932.53876 | AE19: 947.60352 | AF19: 961.82202 | AG19: 973.42322 | AH19: 986.31647 | AI19: 1004.3856 | AJ19: 0.004
A20: Large (> 26000 pounds) | B20: Transportation Energy Use: Highway: Freight Trucks: Large: Low economic growth | C20: 45-AEO2022.16.lowmacro-d011222a | D20: trillion Btu | F20: 3997.231 | G20: 4022.74 | H20: 3993.2268 | I20: 3944.2776 | J20: 3905.4612 | K20: 3851.7996 | L20: 3786.8643 | M20: 3731.5134 | N20: 3667.1077 | O20: 3607.1606 | P20: 3545.3743 | Q20: 3491.5488 | R20: 3439.7327 | S20: 3384.8596 | T20: 3339.4092 | U20: 3297.9978 | V20: 3260.4067 | W20: 3228.7903 | X20: 3203.0376 | Y20: 3180.4436 | Z20: 3159.1934 | AA20: 3144.9951 | AB20: 3133.3757 | AC20: 3113.8738 | AD20: 3097.4915 | AE20: 3089.7202 | AF20: 3076.7791 | AG20: 3053.8027 | AH20: 3032.8298 | AI20: 3025.8931 | AJ20: -0.01
A21: Non-Highway | C21: 45-AEO2022.18.
A22: Air | B22: Transportation Energy Use: Non-Highway: Air: Low economic growth | C22: 45-AEO2022.19.lowmacro-d011222a | D22: trillion Btu | F22: 2290.1211 | G22: 2662.0981 | H22: 2926.5713 | I22: 2996.3662 | J22: 3053.5276 | K22: 3092.4404 | L22: 3117.2766 | M22: 3148.9443 | N22: 3179.4436 | O22: 3213.5745 | P22: 3237.3872 | Q22: 3266.1953 | R22: 3281.667 | S22: 3278.8699 | T22: 3289.3474 | U22: 3301.5503 | V22: 3321.4758 | W22: 3340.7703 | X22: 3368.4548 | Y22: 3399.1912 | Z22: 3422.6946 | AA22: 3451.2617 | AB22: 3481.2554 | AC22: 3507.0789 | AD22: 3541.613 | AE22: 3577.7354 | AF22: 3611.2751 | AG22: 3642.4556 | AH22: 3676.5105 | AI22: 3722.4666 | AJ22: 0.017
A23: General Aviation | B23: Transportation Energy Use: Non-Highway: Air: General Aviation: Low economic growth | C23: 45-AEO2022.20.lowmacro-d011222a | D23: trillion Btu | F23: 130.41975 | G23: 148.12035 | H23: 160.70384 | I23: 164.01874 | J23: 166.73363 | K23: 168.58069 | L23: 169.75839 | M23: 171.26244 | N23: 172.7113 | O23: 174.33388 | P23: 175.4655 | Q23: 176.83534 | R23: 177.5705 | S23: 177.43608 | T23: 177.93398 | U23: 178.5141 | V23: 179.4623 | W23: 180.38036 | X23: 181.69818 | Y23: 183.16138 | Z23: 184.2804 | AA23: 185.64044 | AB23: 187.06842 | AC23: 188.29794 | AD23: 189.94231 | AE23: 191.66214 | AF23: 193.25919 | AG23: 194.74396 | AH23: 196.36546 | AI23: 198.55386 | AJ23: 0.015
A24: Domestic Passenger | B24: Transportation Energy Use: Non-Highway: Air: Domestic Passenger: Low economic growth | C24: 45-AEO2022.21.lowmacro-d011222a | D24: trillion Btu | F24: 1263.5565 | G24: 1452.0225 | H24: 1523.9451 | I24: 1546.8971 | J24: 1561.2332 | K24: 1577.4373 | L24: 1584.1204 | M24: 1595.3573 | N24: 1608.2111 | O24: 1622.9506 | P24: 1634.3375 | Q24: 1648.4358 | R24: 1659.7506 | S24: 1663.0459 | T24: 1665.0894 | U24: 1666.6385 | V24: 1671.3455 | W24: 1676.7516 | X24: 1686.338 | Y24: 1697.8873 | Z24: 1705.4935 | AA24: 1716.3497 | AB24: 1728.1514 | AC24: 1738.5205 | AD24: 1753.1283 | AE24: 1769.0199 | AF24: 1783.3528 | AG24: 1796.5834 | AH24: 1812.3373 | AI24: 1834.2035 | AJ24: 0.013
A25: International Passenger | B25: Transportation Energy Use: Non-Highway: Air: International Passenger: Low economic growth | C25: 45-AEO2022.22.lowmacro-d011222a | D25: trillion Btu | F25: 339.84116 | G25: 521.16034 | H25: 703.32452 | I25: 742.59875 | J25: 775.27966 | K25: 787.33655 | L25: 796.52142 | M25: 807.1037 | N25: 816.57593 | O25: 827.00336 | P25: 834.06171 | Q25: 842.44354 | R25: 845.88464 | S25: 844.03265 | T25: 848.60821 | U25: 854.13666 | V25: 862.00324 | W25: 869.35303 | X25: 878.98248 | Y25: 889.30731 | Z25: 897.79169 | AA25: 907.4184 | AB25: 917.36682 | AC25: 925.9801 | AD25: 937.00031 | AE25: 948.3042 | AF25: 959.00671 | AG25: 969.05395 | AH25: 979.53906 | AI25: 993.22095 | AJ25: 0.038
A26: Dedicated Freight | B26: Transportation Energy Use: Non-Highway: Air: Dedicated Freight: Low economic growth | C26: 45-AEO2022.23.lowmacro-d011222a | D26: trillion Btu | F26: 556.30365 | G26: 540.79498 | H26: 538.59778 | I26: 542.85156 | J26: 550.28094 | K26: 559.08594 | L26: 566.87653 | M26: 575.22089 | N26: 581.94531 | O26: 589.28656 | P26: 593.52258 | Q26: 598.48059 | R26: 598.46149 | S26: 594.35516 | T26: 597.71582 | U26: 602.26111 | V26: 608.6648 | W26: 614.2854 | X26: 621.43628 | Y26: 628.83527 | Z26: 635.12884 | AA26: 641.8529 | AB26: 648.66901 | AC26: 654.28027 | AD26: 661.54224 | AE26: 668.74915 | AF26: 675.65656 | AG26: 682.07428 | AH26: 688.26874 | AI26: 696.48822 | AJ26: 0.008
A27: Water | B27: Transportation Energy Use: Non-Highway: Water: Low economic growth | C27: 45-AEO2022.24.lowmacro-d011222a | D27: trillion Btu | F27: 1205.1506 | G27: 1269.3711 | H27: 1160.8929 | I27: 1159.9191 | J27: 1159.3843 | K27: 1154.42 | L27: 1146.6722 | M27: 1141.7399 | N27: 1138.1646 | O27: 1134.3064 | P27: 1131.7939 | Q27: 1133.3716 | R27: 1131.3661 | S27: 1128.6906 | T27: 1126.8889 | U27: 1124.8169 | V27: 1123.2894 | W27: 1121.4966 | X27: 1120.662 | Y27: 1112.2582 | Z27: 1110.1893 | AA27: 1109.3357 | AB27: 1105.8765 | AC27: 1102.4503 | AD27: 1101.0814 | AE27: 1098.4622 | AF27: 1097.6174 | AG27: 1096.707 | AH27: 1095.4762 | AI27: 1095.8292 | AJ27: -0.003
A28: Freight | B28: Transportation Energy Use: Non-Highway: Water: Freight: Low economic growth | C28: 45-AEO2022.25.lowmacro-d011222a | D28: trillion Btu | F28: 1002.543 | G28: 1066.7007 | H28: 958.59094 | I28: 957.66125 | J28: 957.84467 | K28: 953.95453 | L28: 947.84741 | M28: 944.16882 | N28: 941.77747 | O28: 938.92902 | P28: 937.57867 | Q28: 939.91656 | R28: 938.7121 | S28: 937.33179 | T28: 936.87408 | U28: 936.10895 | V28: 935.5993 | W28: 934.75311 | X28: 934.76544 | Y28: 927.09631 | Z28: 926.01733 | AA28: 926.08704 | AB28: 923.50134 | AC28: 920.91394 | AD28: 920.21484 | AE28: 918.04535 | AF28: 917.76361 | AG28: 917.58612 | AH28: 916.91357 | AI28: 917.46435 | AJ28: -0.003
A29: Domestic Shipping | B29: Transportation Energy Use: Non-Highway: Water: Freight: Domestic Shipping: Low economic growth | C29: 45-AEO2022.26.lowmacro-d011222a | D29: trillion Btu | F29: 75.170197 | G29: 77.208076 | H29: 75.596611 | I29: 73.010834 | J29: 70.828506 | K29: 68.479935 | L29: 65.995178 | M29: 63.741302 | N29: 61.341187 | O29: 59.028267 | P29: 57.702305 | Q29: 56.570229 | R29: 55.381996 | S29: 54.015034 | T29: 52.689022 | U29: 51.423496 | V29: 50.232204 | W29: 49.037437 | X29: 47.977844 | Y29: 46.870342 | Z29: 46.2523 | AA29: 45.673676 | AB29: 45.116436 | AC29: 44.47715 | AD29: 43.907368 | AE29: 43.460552 | AF29: 42.915054 | AG29: 42.232605 | AH29: 41.673977 | AI29: 41.336166 | AJ29: -0.02
A30: International Shipping | B30: Transportation Energy Use: Non-Highway: Water: Freight: International Shipping: Low economic growth | C30: 45-AEO2022.27.lowmacro-d011222a | D30: trillion Btu | F30: 927.3728 | G30: 989.49255 | H30: 882.99432 | I30: 884.65045 | J30: 887.01617 | K30: 885.47461 | L30: 881.85223 | M30: 880.42749 | N30: 880.43628 | O30: 879.90076 | P30: 879.87634 | Q30: 883.34631 | R30: 883.33008 | S30: 883.31677 | T30: 884.18506 | U30: 884.68543 | V30: 885.36713 | W30: 885.7157 | X30: 886.7876 | Y30: 880.22595 | Z30: 879.76501 | AA30: 880.41333 | AB30: 878.38489 | AC30: 876.43677 | AD30: 876.3075 | AE30: 874.58478 | AF30: 874.84857 | AG30: 875.35352 | AH30: 875.23962 | AI30: 876.12817 | AJ30: -0.002
A31: Recreational Boats | B31: Transportation Energy Use: Non-Highway: Water: Recreational Boats: Low economic growth | C31: 45-AEO2022.28.lowmacro-d011222a | D31: trillion Btu | F31: 202.60761 | G31: 202.67035 | H31: 202.30199 | I31: 202.25783 | J31: 201.53964 | K31: 200.46555 | L31: 198.82484 | M31: 197.57109 | N31: 196.38715 | O31: 195.37729 | P31: 194.21532 | Q31: 193.455 | R31: 192.65402 | S31: 191.35883 | T31: 190.0148 | U31: 188.70801 | V31: 187.69019 | W31: 186.74341 | X31: 185.89664 | Y31: 185.16185 | Z31: 184.172 | AA31: 183.24867 | AB31: 182.37503 | AC31: 181.53639 | AD31: 180.86662 | AE31: 180.41685 | AF31: 179.85387 | AG31: 179.12079 | AH31: 178.56261 | AI31: 178.36497 | AJ31: -0.004
A32: Rail | B32: Transportation Energy Use: Non-Highway: Rail: Low economic growth | C32: 45-AEO2022.29.lowmacro-d011222a | D32: trillion Btu | F32: 502.97836 | G32: 505.48096 | H32: 503.59439 | I32: 474.03946 | J32: 476.44681 | K32: 484.86603 | L32: 482.78296 | M32: 483.77783 | N32: 482.23377 | O32: 481.40125 | P32: 481.0557 | Q32: 479.84796 | R32: 478.1694 | S32: 473.18021 | T32: 469.38776 | U32: 465.79703 | V32: 463.79098 | W32: 463.09961 | X32: 461.97375 | Y32: 459.68088 | Z32: 458.82523 | AA32: 458.64899 | AB32: 456.07806 | AC32: 455.02957 | AD32: 451.63849 | AE32: 451.31867 | AF32: 449.42755 | AG32: 448.0036 | AH32: 447.13858 | AI32: 448.8241 | AJ32: -0.004
A33: Freight | B33: Transportation Energy Use: Non-Highway: Rail: Freight: Low economic growth | C33: 45-AEO2022.30.lowmacro-d011222a | D33: trillion Btu | F33: 467.66425 | G33: 466.46185 | H33: 461.56598 | I33: 429.61029 | J33: 430.24832 | K33: 437.28735 | L33: 434.12399 | M33: 434.16403 | N33: 431.80029 | O33: 430.10172 | P33: 429.02966 | Q33: 426.84235 | R33: 424.42566 | S33: 418.91717 | T33: 414.68787 | U33: 410.67566 | V33: 408.19385 | W33: 406.99979 | X33: 405.38599 | Y33: 402.43707 | Z33: 401.0734 | AA33: 400.34808 | AB33: 397.21927 | AC33: 395.6438 | AD33: 391.64502 | AE33: 390.60486 | AF33: 388.01709 | AG33: 385.96884 | AH33: 384.43982 | AI33: 385.4147 | AJ33: -0.007
... A44: Total | B44: Transportation Energy Use: Total: Low economic growth | C44: 45-AEO2022.43.lowmacro-d011222a | D44: trillion Btu | F44: 26245.234 | G44: 26976.199 | H44: 27275.254 | I44: 27174.082 | J44: 27081.055 | K44: 26926.322 | L44: 26710.229 | M44: 26549.518 | N44: 26370.535 | O44: 26231.902 | P44: 26112.062 | Q44: 26007.828 | R44: 25911.545 | S44: 25768.662 | T44: 25654.502 | U44: 25562.76 | V44: 25509.037 | W44: 25476.059 | X44: 25481.943 | Y44: 25498.867 | Z44: 25520.873 | AA44: 25570.719 | AB44: 25626.119 | AC44: 25684.939 | AD44: 25762.031 | AE44: 25886.98 | AF44: 26019.113 | AG44: 26136.447 | AH44: 26269.385 | AI44: 26462.24 | AJ44: 0
A45: Energy Use by Type | C45: 45-AEO2022.45.
A46: Motor Gasoline excluding E85 | B46: Transportation Energy Use: Petroleum: Motor Gasoline: Low economic growth | C46: 45-AEO2022.46.lowmacro-d011222a | D46: trillion Btu | F46: 15435.638 | G46: 15697.523 | H46: 15874.183 | I46: 15794.099 | J46: 15682.453 | K46: 15547.299 | L46: 15393.844 | M46: 15246.523 | N46: 15109.185 | O46: 15001.28 | P46: 14917.894 | Q46: 14823.203 | R46: 14752.456 | S46: 14673.993 | T46: 14589.887 | U46: 14517.541 | V46: 14463.548 | W46: 14422.658 | X46: 14405.047 | Y46: 14400.77 | Z46: 14401.635 | AA46: 14412.71 | AB46: 14428.078 | AC46: 14456.513 | AD46: 14499.708 | AE46: 14568.516 | AF46: 14648.495 | AG46: 14728.717 | AH46: 14818.203 | AI46: 14933.52 | AJ46: -0.001
A47: E85 | B47: Transportation Energy Use: E85: Low economic growth | C47: 45-AEO2022.47.lowmacro-d011222a | D47: trillion Btu | F47: 32.006447 | G47: 34.419018 | H47: 35.953335 | I47: 35.719009 | J47: 35.348183 | K47: 34.69883 | L47: 33.852615 | M47: 33.030506 | N47: 32.220005 | O47: 31.39999 | P47: 30.692623 | Q47: 29.953573 | R47: 29.405727 | S47: 28.890285 | T47: 28.521727 | U47: 28.288227 | V47: 28.189083 | W47: 28.201729 | X47: 28.518017 | Y47: 28.734303 | Z47: 29.134182 | AA47: 29.231506 | AB47: 29.773508 | AC47: 30.734493 | AD47: 31.427977 | AE47: 32.201042 | AF47: 33.008862 | AG47: 33.918106 | AH47: 34.828552 | AI47: 35.963299 | AJ47: 0.004
A48: Diesel | B48: Transportation Energy Use: Petroleum: Diesel: Low economic growth | C48: 45-AEO2022.48.lowmacro-d011222a | D48: trillion Btu | F48: 6491.6987 | G48: 6435.9546 | H48: 6510.9736 | I48: 6416.4653 | J48: 6363.3237 | K48: 6299.6499 | L48: 6216.127 | M48: 6150.666 | N48: 6068.5347 | O48: 5994.8247 | P48: 5920.1377 | Q48: 5856.1235 | R48: 5795.1997 | S48: 5725.7256 | T48: 5668.4751 | U48: 5617.1226 | V48: 5571.0229 | W48: 5532.2793 | X48: 5500.627 | Y48: 5477.1094 | Z48: 5451.4351 | AA48: 5433.96 | AB48: 5420.4438 | AC48: 5396.856 | AD48: 5374.9531 | AE48: 5370.2935 | AF48: 5355.9463 | AG48: 5329.8496 | AH48: 5307.6899 | AI48: 5306.2451 | AJ48: -0.007
A49: Jet Fuel (kerosene & naphtha) | B49: Transportation Energy Use: Petroleum: Jet Fuel: Low economic growth | C49: 45-AEO2022.49.lowmacro-d011222a | D49: trillion Btu | F49: 2669.78 | G49: 3048.0139 | H49: 3308.7346 | I49: 3377.9026 | J49: 3437.2991 | K49: 3477.8428 | L49: 3503.7979 | M49: 3536.4578 | N49: 3565.1162 | O49: 3599.7437 | P49: 3622.3281 | Q49: 3650.355 | R49: 3664.9744 | S49: 3661.2539 | T49: 3670.7402 | U49: 3682.0251 | V49: 3701.0479 | W49: 3719.3962 | X49: 3746.0911 | Y49: 3775.7952 | Z49: 3798.2261 | AA49: 3825.6873 | AB49: 3854.5432 | AC49: 3879.1946 | AD49: 3912.5259 | AE49: 3947.4236 | AF49: 3979.7197 | AG49: 4009.6382 | AH49: 4042.4163 | AI49: 4087.0811 | AJ49: 0.015
A50: Residual Fuel Oil | B50: Transportation Energy Use: Petroleum: Residual Fuel Oil: Low economic growth | C50: 45-AEO2022.50.lowmacro-d011222a | D50: trillion Btu | F50: 558.12506 | G50: 748.90088 | H50: 522.6416 | I50: 524.90814 | J50: 529.69861 | K50: 524.03589 | L50: 512.93726 | M50: 507.74628 | N50: 506.17285 | O50: 503.2898 | P50: 501.78506 | Q50: 509.74368 | R50: 508.35602 | S50: 506.9697 | T50: 507.99405 | U50: 507.99383 | V50: 508.50623 | W50: 508.11883 | X50: 509.57166 | Y50: 490.52374 | Z50: 487.88681 | AA50: 488.15933 | AB50: 481.1163 | AC50: 474.23474 | AD50: 472.38226 | AE50: 466.11859 | AF50: 465.16818 | AG50: 464.99081 | AH50: 463.17944 | AI50: 463.91602 | AJ50: -0.006
A51: Aviation Gasoline | B51: Transportation Energy Use: Petroleum: Aviation Gasoline: Low economic growth | C51: 45-AEO2022.51.lowmacro-d011222a | D51: trillion Btu | F51: 22.434891 | G51: 22.421618 | H51: 22.410635 | I51: 22.401548 | J51: 22.394032 | K51: 22.387812 | L51: 22.382666 | M51: 22.378407 | N51: 22.374884 | O51: 22.371969 | P51: 22.369558 | Q51: 22.367563 | R51: 22.365911 | S51: 22.364546 | T51: 22.363417 | U51: 22.36248 | V51: 22.361708 | W51: 22.361067 | X51: 22.360538 | Y51: 22.3601 | Z51: 22.359737 | AA51: 22.359438 | AB51: 22.35919 | AC51: 22.358984 | AD51: 22.358814 | AE51: 22.358673 | AF51: 22.358557 | AG51: 22.358461 | AH51: 22.358381 | AI51: 22.358315 | AJ51: 0
A52: Propane | B52: Transportation Energy Use: Petroleum: Propane: Low economic growth | C52: 45-AEO2022.52.lowmacro-d011222a | D52: trillion Btu | F52: 6.869474 | G52: 7.989438 | H52: 8.609376 | I52: 8.87498 | J52: 9.199483 | K52: 9.476545 | L52: 9.71358 | M52: 9.726265 | N52: 9.916169 | O52: 10.133162 | P52: 10.340009 | Q52: 10.566711 | R52: 10.792727 | S52: 11.015198 | T52: 11.2391 | U52: 11.471786 | V52: 11.722797 | W52: 11.97968 | X52: 12.230126 | Y52: 12.498428 | Z52: 12.769831 | AA52: 13.054031 | AB52: 13.345766 | AC52: 13.624531 | AD52: 13.921653 | AE52: 14.256479 | AF52: 14.597359 | AG52: 14.931116 | AH52: 15.284294 | AI52: 15.687407 | AJ52: 0.029
A53: Lubricants | B53: Transportation Energy Use: Petroleum: Lubricants: Low economic growth | C53: 45-AEO2022.53.lowmacro-d011222a | D53: trillion Btu | F53: 125.03456 | G53: 126.33339 | H53: 127.05102 | I53: 127.56862 | J53: 127.84139 | K53: 128.10916 | L53: 128.13182 | M53: 128.17013 | N53: 128.20395 | O53: 128.1955 | P53: 128.16147 | Q53: 128.16504 | R53: 128.19002 | S53: 128.08826 | T53: 127.91258 | U53: 127.74858 | V53: 127.63048 | W53: 127.58284 | X53: 127.60142 | Y53: 127.64003 | Z53: 127.66281 | AA53: 127.65943 | AB53: 127.64391 | AC53: 127.61406 | AD53: 127.55948 | AE53: 127.54861 | AF53: 127.53921 | AG53: 127.51091 | AH53: 127.52413 | AI53: 127.52957 | AJ53: 0.001
A54: Petroleum and Other Liquids Subtotal | B54: Transportation Energy Use: Petroleum Subtotal: Low economic growth | C54: 45-AEO2022.54.lowmacro-d011222a | D54: trillion Btu | F54: 25341.586 | G54: 26121.559 | H54: 26410.555 | I54: 26307.939 | J54: 26207.559 | K54: 26043.502 | L54: 25820.787 | M54: 25634.699 | N54: 25441.723 | O54: 25291.238 | P54: 25153.709 | Q54: 25030.477 | R54: 24911.74 | S54: 24758.301 | T54: 24627.131 | U54: 24514.557 | V54: 24434.027 | W54: 24372.578 | X54: 24352.049 | Y54: 24335.43 | Z54: 24331.109 | AA54: 24352.824 | AB54: 24377.305 | AC54: 24401.131 | AD54: 24454.836 | AE54: 24548.717 | AF54: 24646.834 | AG54: 24731.916 | AH54: 24831.482 | AI54: 24992.301 | AJ54: 0
A55: M85 | B55: Transportation Energy Use: M85: Low economic growth | C55: 45-AEO2022.55.lowmacro-d011222a | D55: trillion Btu | F55: 0 | G55: 0 | H55: 0 | I55: 0 | J55: 0 | K55: 0 | L55: 0 | M55: 0 | N55: 0 | O55: 0 | P55: 0 | Q55: 0 | R55: 0 | S55: 0 | T55: 0 | U55: 0 | V55: 0 | W55: 0 | X55: 0 | Y55: 0 | Z55: 0 | AA55: 0 | AB55: 0 | AC55: 0 | AD55: 0 | AE55: 0 | AF55: 0 | AG55: 0 | AH55: 0 | AI55: 0 | AJ55: - -
